Workbook

Sheet Cover
B2: UK Online Sports Betting
B4: Operator Market Share Time Series | UK, Australia, Italy | 2019 to 2025
B6: Overview
B7: Geography | C7: United Kingdom (UK-only; Flutter UKI used as close proxy, Ireland ~5%)
B8: Product scope | C8: Online sports betting only (sportsbook). Excludes iGaming, bingo, poker, lottery
B9: Metric | C9: Gross Gambling Yield (GGY) share by operator group
B10: Currency | C10: British pounds (£m)
B11: Period | C11: Calendar years 2019 to 2025
B12: Approach | C12: Top-down: total market anchored to UKGC; shares anchored to Flutter disclosed
B14: Workbook Map
B15: 1. Cover | C15: This page: scope, approach, key findings
B16: 2. UK sheets | C16: UK Share %, UK GGY GBPm, UK Market Size (3 tabs)
B17: 3. Australia sheets | C17: Australia Share %, Australia GGY A$m, Australia Market Size (3 tabs)
B18: 4. Italy sheets | C18: Italy Share %, Italy GGY EURm, Italy Market Size (3 tabs)
B19: 5. Sources | C19: Consolidated sources and methodology notes
B22: Key Findings
B23: UK: Flutter (Paddy Power, Sky Bet, Betfair) grew from 32% to 43% (2019 to 2025); bet365 steady at 21%; Entain and Evoke lost 6 ppts each.
B24: UK: Top 2 concentration rose from 53% to 64%. Clear oligopoly formation.
B25: Australia: Sportsbet (Flutter) ran up from 28% to 50% by 2021 post BetEasy merger; has since settled at 45%.
B26: Australia: Tabcorp (TAB) retail legacy visible in digital share decline (26% to 22%). Entain (Ladbrokes, Neds) stable at 17%.
B27: Italy: Lottomatica consolidated from 8% to 24% via Goldbet, Betflag and Planetwin365 acquisitions.
B28: Italy: Flutter combined (Sisal + Snai + PokerStars + Betfair) reaches c.34% in 2025 after the Apr-2025 Snaitech deal.
B29: All three markets show clear consolidation: Top 3 operators hold 60-75% across all geographies by 2025.
B32: Only Flutter (publicly listed) and Entain (publicly listed) disclose UK online market share. bet365 is private and non-disclosing. Evoke discloses segment data only. Shares for bet365, Betfred and the long tail are triangulated from: Regulus Partners / H2 Gambling Capital estimates cited in industry press; Similarweb traffic share; YouGov account-share surveys; Adthena PPC share. Figures should be read as ±1-2 ppt estimates, not audited.

Sheet UK Share %
B2: UK Online Sports Betting to Operator Market Share (%)
B4: Operator | C4: 2019 | D4: 2020 | E4: 2021 | F4: 2022 | G4: 2023 | H4: 2024 | I4: 2025 | J4: Δ 2019→2025
B5: Flutter (Paddy Power, Betfair, Sky Bet) | C5: 0.32 | D5: 0.34 | E5: 0.36 | F5: 0.38 | G5: 0.39 | H5: 0.42 | I5: 0.425 | J5: =I5-C5 -> 0.105
B6: bet365 | C6: 0.21 | D6: 0.21 | E6: 0.215 | F6: 0.21 | G6: 0.205 | H6: 0.205 | I6: 0.21 | J6: =I6-C6 -> 0
B7: Entain (Ladbrokes, Coral, bwin) | C7: 0.185 | D7: 0.18 | E7: 0.165 | F7: 0.15 | G7: 0.135 | H7: 0.12 | I7: 0.13 | J7: =I7-C7 -> -0.055
B8: Evoke (William Hill, 888) | C8: 0.15 | D8: 0.14 | E8: 0.13 | F8: 0.125 | G8: 0.11 | H8: 0.095 | I8: 0.085 | J8: =I8-C8 -> -0.065
B9: Betfred | C9: 0.035 | D9: 0.04 | E9: 0.045 | F9: 0.045 | G9: 0.05 | H9: 0.05 | I9: 0.05 | J9: =I9-C9 -> 0.015
B10: Betway (Super Group) | C10: 0.025 | D10: 0.025 | E10: 0.025 | F10: 0.025 | G10: 0.025 | H10: 0.025 | I10: 0.02 | J10: =I10-C10 -> -0.005
B11: BetVictor | C11: 0.015 | D11: 0.015 | E11: 0.015 | F11: 0.015 | G11: 0.015 | H11: 0.015 | I11: 0.015 | J11: =I11-C11 -> 0
B12: Unibet (Kindred) | C12: 0.015 | D12: 0.015 | E12: 0.015 | F12: 0.015 | G12: 0.015 | H12: 0.015 | I12: 0.015 | J12: =I12-C12 -> 0
B13: Other (Tote, DAZN Bet, Bet UK, LiveScore, etc.) | C13: 0.045 | D13: 0.035 | E13: 0.03 | F13: 0.035 | G13: 0.055 | H13: 0.055 | I13: 0.05 | J13: =I13-C13 -> 0.005
B14: Total | C14: =SUM(C5:C13) -> 1 | D14: =SUM(D5:D13) -> 1 | E14: =SUM(E5:E13) -> 1 | F14: =SUM(F5:F13) -> 1 | G14: =SUM(G5:G13) -> 1 | H14: =SUM(H5:H13) -> 1 | I14: =SUM(I5:I13) -> 1 | J14: =I14-C14 -> 0
B16: Concentration Metrics
B17: Top 2 (Flutter + bet365) | C17: =C5+C6 -> 0.53 | D17: =D5+D6 -> 0.55 | E17: =E5+E6 -> 0.575 | F17: =F5+F6 -> 0.59 | G17: =G5+G6 -> 0.595 | H17: =H5+H6 -> 0.625 | I17: =I5+I6 -> 0.635 | J17: =I17-C17 -> 0.105
B18: Top 4 (Flutter + bet365 + Entain + Evoke) | C18: =C5+C6+C7+C8 -> 0.865 | D18: =D5+D6+D7+D8 -> 0.87 | E18: =E5+E6+E7+E8 -> 0.87 | F18: =F5+F6+F7+F8 -> 0.865 | G18: =G5+G6+G7+G8 -> 0.84 | H18: =H5+H6+H7+H8 -> 0.84 | I18: =I5+I6+I7+I8 -> 0.85 | J18: =I18-C18 -> -0.015
B19: Long Tail (all others) | C19: =1-C18 -> 0.135 | D19: =1-D18 -> 0.13 | E19: =1-E18 -> 0.13 | F19: =1-F18 -> 0.135 | G19: =1-G18 -> 0.16 | H19: =1-H18 -> 0.16 | I19: =1-I18 -> 0.15 | J19: =I19-C19 -> 0.015
B21: HHI (Herfindahl-Hirschman Index) | C21: =SUMPRODUCT((C5:C13*100)^2) -> 2075.5 | D21: =SUMPRODUCT((D5:D13*100)^2) -> 2156 | E21: =SUMPRODUCT((E5:E13*100)^2) -> 2239.5 | F21: =SUMPRODUCT((F5:F13*100)^2) -> 2309.5 | G21: =SUMPRODUCT((G5:G13*100)^2) -> 2310.5 | H21: =SUMPRODUCT((H5:H13*100)^2) -> 2484.5 | I21: =SUMPRODUCT((I5:I13*100)^2) -> 2547
B22: HHI interpretation: <1,500 = unconcentrated; 1,500-2,500 = moderately concentrated; >2,500 = highly concentrated.
B24: Notes:
B25: • Blue figures are hardcoded inputs; black figures are formulas.
B26: • Flutter UKI = UK + Ireland combined. Ireland is ~5% of UKI; shares apply directly as UK proxy.
B27: • Evoke = rebrand of 888 Holdings (July 2024). Pre-July 2022, figures combine 888 + pre-merger William Hill.
B28: • Bet365, Betfred and long-tail shares are triangulated estimates (see Sources tab).
B29: • See 'Sources' tab for detailed methodology and citations.

Sheet UK GGY GBPm
B2: UK Online Sports Betting to Operator GGY (£m)
B4: Operator | C4: 2019 | D4: 2020 | E4: 2021 | F4: 2022 | G4: 2023 | H4: 2024 | I4: 2025 | J4: CAGR 19-25
B5: Total UK Online Sports Betting GGY (£m) | C5: ='UK Market Size'!C6 -> 2350 | D5: ='UK Market Size'!D6 -> 2050 | E5: ='UK Market Size'!E6 -> 2250 | F5: ='UK Market Size'!F6 -> 2400 | G5: ='UK Market Size'!G6 -> 2430 | H5: ='UK Market Size'!H6 -> 2400 | I5: ='UK Market Size'!I6 -> 2380
B7: Flutter (Paddy Power, Betfair, Sky Bet) | C7: ='UK Share %'!C5*C5 -> 752 | D7: ='UK Share %'!D5*D5 -> 697 | E7: ='UK Share %'!E5*E5 -> 810 | F7: ='UK Share %'!F5*F5 -> 912 | G7: ='UK Share %'!G5*G5 -> 947.7 | H7: ='UK Share %'!H5*H5 -> 1008 | I7: ='UK Share %'!I5*I5 -> 1011.5 | J7: =(I7/C7)^(1/6)-1 -> 0.050649862
B8: bet365 | C8: ='UK Share %'!C6*C5 -> 493.5 | D8: ='UK Share %'!D6*D5 -> 430.5 | E8: ='UK Share %'!E6*E5 -> 483.75 | F8: ='UK Share %'!F6*F5 -> 504 | G8: ='UK Share %'!G6*G5 -> 498.15 | H8: ='UK Share %'!H6*H5 -> 492 | I8: ='UK Share %'!I6*I5 -> 499.8 | J8: =(I8/C8)^(1/6)-1 -> 0.0021164297
B9: Entain (Ladbrokes, Coral, bwin) | C9: ='UK Share %'!C7*C5 -> 434.75 | D9: ='UK Share %'!D7*D5 -> 369 | E9: ='UK Share %'!E7*E5 -> 371.25 | F9: ='UK Share %'!F7*F5 -> 360 | G9: ='UK Share %'!G7*G5 -> 328.05 | H9: ='UK Share %'!H7*H5 -> 288 | I9: ='UK Share %'!I7*I5 -> 309.4 | J9: =(I9/C9)^(1/6)-1 -> -0.055112465
B10: Evoke (William Hill, 888) | C10: ='UK Share %'!C8*C5 -> 352.5 | D10: ='UK Share %'!D8*D5 -> 287 | E10: ='UK Share %'!E8*E5 -> 292.5 | F10: ='UK Share %'!F8*F5 -> 300 | G10: ='UK Share %'!G8*G5 -> 267.3 | H10: ='UK Share %'!H8*H5 -> 228 | I10: ='UK Share %'!I8*I5 -> 202.3 | J10: =(I10/C10)^(1/6)-1 -> -0.0883962
B11: Betfred | C11: ='UK Share %'!C9*C5 -> 82.25 | D11: ='UK Share %'!D9*D5 -> 82 | E11: ='UK Share %'!E9*E5 -> 101.25 | F11: ='UK Share %'!F9*F5 -> 108 | G11: ='UK Share %'!G9*G5 -> 121.5 | H11: ='UK Share %'!H9*H5 -> 120 | I11: ='UK Share %'!I9*I5 -> 119 | J11: =(I11/C11)^(1/6)-1 -> 0.063494323
B12: Betway (Super Group) | C12: ='UK Share %'!C10*C5 -> 58.75 | D12: ='UK Share %'!D10*D5 -> 51.25 | E12: ='UK Share %'!E10*E5 -> 56.25 | F12: ='UK Share %'!F10*F5 -> 60 | G12: ='UK Share %'!G10*G5 -> 60.75 | H12: ='UK Share %'!H10*H5 -> 60 | I12: ='UK Share %'!I10*I5 -> 47.6 | J12: =(I12/C12)^(1/6)-1 -> -0.034468352
B13: BetVictor | C13: ='UK Share %'!C11*C5 -> 35.25 | D13: ='UK Share %'!D11*D5 -> 30.75 | E13: ='UK Share %'!E11*E5 -> 33.75 | F13: ='UK Share %'!F11*F5 -> 36 | G13: ='UK Share %'!G11*G5 -> 36.45 | H13: ='UK Share %'!H11*H5 -> 36 | I13: ='UK Share %'!I11*I5 -> 35.7 | J13: =(I13/C13)^(1/6)-1 -> 0.0021164297
B14: Unibet (Kindred) | C14: ='UK Share %'!C12*C5 -> 35.25 | D14: ='UK Share %'!D12*D5 -> 30.75 | E14: ='UK Share %'!E12*E5 -> 33.75 | F14: ='UK Share %'!F12*F5 -> 36 | G14: ='UK Share %'!G12*G5 -> 36.45 | H14: ='UK Share %'!H12*H5 -> 36 | I14: ='UK Share %'!I12*I5 -> 35.7 | J14: =(I14/C14)^(1/6)-1 -> 0.0021164297
B15: Other (Tote, DAZN Bet, Bet UK, LiveScore, etc.) | C15: ='UK Share %'!C13*C5 -> 105.75 | D15: ='UK Share %'!D13*D5 -> 71.75 | E15: ='UK Share %'!E13*E5 -> 67.5 | F15: ='UK Share %'!F13*F5 -> 84 | G15: ='UK Share %'!G13*G5 -> 133.65 | H15: ='UK Share %'!H13*H5 -> 132 | I15: ='UK Share %'!I13*I5 -> 119 | J15: =(I15/C15)^(1/6)-1 -> 0.019869093
B16: Total (check vs market) | C16: =SUM(C7:C15) -> 2350 | D16: =SUM(D7:D15) -> 2050 | E16: =SUM(E7:E15) -> 2250 | F16: =SUM(F7:F15) -> 2400 | G16: =SUM(G7:G15) -> 2430 | H16: =SUM(H7:H15) -> 2400 | I16: =SUM(I7:I15) -> 2380 | J16: =(I16/C16)^(1/6)-1 -> 0.0021164297
B17: Variance vs market (should be 0) | C17: =C16-C5 -> 0 | D17: =D16-D5 -> 0 | E17: =E16-E5 -> 0 | F17: =F16-F5 -> 0 | G17: =G16-G5 -> 0 | H17: =H16-H5 -> 0 | I17: =I16-I5 -> 0

Sheet UK Market Size
B2: UK Online Sports Betting to Total Market GGY (£m)
B4: Metric | C4: 2019 | D4: 2020 | E4: 2021 | F4: 2022 | G4: 2023 | H4: 2024 | I4: 2025
B5: Calendar year (Jan - Dec)
B6: Total UK online sports betting GGY (£m) | C6: 2350 | D6: 2050 | E6: 2250 | F6: 2400 | G6: 2430 | H6: 2400 | I6: 2380
B7: YoY growth | C7: n/a | D7: =D6/C6-1 -> -0.12765957 | E7: =E6/D6-1 -> 0.097560976 | F7: =F6/E6-1 -> 0.066666667 | G7: =G6/F6-1 -> 0.0125 | H7: =H6/G6-1 -> -0.012345679 | I7: =I6/H6-1 -> -0.0083333333
B9: CAGR 2019 - 2025 | C9: =(I6/C6)^(1/6)-1 -> 0.0021164297
B12: Methodology & Sources
B13: Primary source: | C13: UK Gambling Commission Industry Statistics (remote real-event betting GGY)
B14: Reporting basis: | C14: UKGC reports financial-year (Apr to Mar); figures converted to calendar year pro-rata
B15: Scope exclusions: | C15: Excludes pool betting, B2B exchange, spread betting, virtual sports
B16: FY2019/20 GGY: | C16: £2.33bn reported (real-event remote betting)
B17: FY2020/21 GGY: | C17: ~£2.0bn (COVID: sports calendar halted Mar-Jun 2020)
B18: FY2022/23 GGY: | C18: £2.48bn reported
B19: FY2023/24 GGY: | C19: £2.4bn reported
B20: 2025 estimate: | C20: £2.38bn to statutory levy, stake limits, affordability checks as headwinds
B21: Cross-check: | C21: Bottom-up via operator disclosures (Flutter $1.46bn UKI sports 2023)

Sheet Australia Share %
B2: Australia Online Sports Betting - Operator Market Share (%)
B3: Note: 'Online wagering' combines racing and sports betting as reported by AU operators
B4: Operator | C4: 2019 | D4: 2020 | E4: 2021 | F4: 2022 | G4: 2023 | H4: 2024 | I4: 2025 | J4: Delta 19 to 25
B5: Sportsbet (Flutter) | C5: 0.28 | D5: 0.4 | E5: 0.5 | F5: 0.48 | G5: 0.45 | H5: 0.45 | I5: 0.45 | J5: =I5-C5 -> 0.17
B6: Tabcorp (TAB) | C6: 0.28 | D6: 0.25 | E6: 0.22 | F6: 0.21 | G6: 0.229 | H6: 0.229 | I6: 0.22 | J6: =I6-C6 -> -0.06
B7: Entain (Ladbrokes, Neds) | C7: 0.14 | D7: 0.15 | E7: 0.16 | F7: 0.16 | G7: 0.165 | H7: 0.17 | I7: 0.17 | J7: =I7-C7 -> 0.03
B8: bet365 Australia | C8: 0.06 | D8: 0.05 | E8: 0.045 | F8: 0.05 | G8: 0.05 | H8: 0.05 | I8: 0.05 | J8: =I8-C8 -> -0.01
B9: PointsBet | C9: 0.03 | D9: 0.035 | E9: 0.035 | F9: 0.03 | G9: 0.025 | H9: 0.02 | I9: 0.015 | J9: =I9-C9 -> -0.015
B10: Unibet (Kindred) | C10: 0.025 | D10: 0.025 | E10: 0.02 | F10: 0.02 | G10: 0.02 | H10: 0.015 | I10: 0.01 | J10: =I10-C10 -> -0.015
B11: Bluebet | C11: 0.005 | D11: 0.01 | E11: 0.01 | F11: 0.01 | G11: 0.015 | H11: 0.015 | I11: 0.015 | J11: =I11-C11 -> 0.01
B12: Betr (News Corp) | C12: 0 | D12: 0 | E12: 0 | F12: 0.01 | G12: 0.02 | H12: 0.015 | I12: 0.015 | J12: =I12-C12 -> 0.015
B13: Other (Picklebet, Palmerbet, Dabble, etc.) | C13: 0.18 | D13: 0.08 | E13: 0.01 | F13: 0.03 | G13: 0.026 | H13: 0.036 | I13: 0.055 | J13: =I13-C13 -> -0.125
B14: Total | C14: =SUM(C5:C13) -> 1 | D14: =SUM(D5:D13) -> 1 | E14: =SUM(E5:E13) -> 1 | F14: =SUM(F5:F13) -> 1 | G14: =SUM(G5:G13) -> 1 | H14: =SUM(H5:H13) -> 1 | I14: =SUM(I5:I13) -> 1 | J14: =I14-C14 -> 0
B16: Concentration Metrics
B17: Top 3 share | C17: =LARGE(C5:C13,1)+LARGE(C5:C13,2)+LARGE(C5:C13,3) -> 0.74 | D17: =LARGE(D5:D13,1)+LARGE(D5:D13,2)+LARGE(D5:D13,3) -> 0.8 | E17: =LARGE(E5:E13,1)+LARGE(E5:E13,2)+LARGE(E5:E13,3) -> 0.88 | F17: =LARGE(F5:F13,1)+LARGE(F5:F13,2)+LARGE(F5:F13,3) -> 0.85 | G17: =LARGE(G5:G13,1)+LARGE(G5:G13,2)+LARGE(G5:G13,3) -> 0.844 | H17: =LARGE(H5:H13,1)+LARGE(H5:H13,2)+LARGE(H5:H13,3) -> 0.849 | I17: =LARGE(I5:I13,1)+LARGE(I5:I13,2)+LARGE(I5:I13,3) -> 0.84 | J17: =I17-C17 -> 0.1
B18: Long tail (non Top 3) | C18: =1-C17 -> 0.26 | D18: =1-D17 -> 0.2 | E18: =1-E17 -> 0.12 | F18: =1-F17 -> 0.15 | G18: =1-G17 -> 0.156 | H18: =1-H17 -> 0.151 | I18: =1-I17 -> 0.16 | J18: =I18-C18 -> -0.1
B19: HHI (Herfindahl index) | C19: =SUMPRODUCT((C5:C13*100)^2) -> 2139.5 | D19: =SUMPRODUCT((D5:D13*100)^2) -> 2558.5 | E19: =SUMPRODUCT((E5:E13*100)^2) -> 3278.5 | F19: =SUMPRODUCT((F5:F13*100)^2) -> 3050 | G19: =SUMPRODUCT((G5:G13*100)^2) -> 2869.92 | H19: =SUMPRODUCT((H5:H13*100)^2) -> 2887.12 | I19: =SUMPRODUCT((I5:I13*100)^2) -> 2861
B22: Sources & Notes
B23: Scope: 'Online wagering' in AU combines racing and sports betting; regulated operators typically report these together.
B24: Market anchor: Sportsbet reached 50% share in 2021 (Flutter 2021 Annual Results) and 48% in 2022 (confirmed by Flutter FY22 results).
B25: Sportsbet 2023 and 2024: 45% share per Flutter FY23 / Q1 2025 disclosures (Inside Asian Gaming, The Straight).
B26: Tabcorp digital: 22.9% digital share FY24 per Tabcorp FY24 Annual Report; TAB25 strategy originally targeted 30% by FY25 (unmet).
B27: Entain AU: 16% (2021) rising to 17% (2025) per Entain Market Spotlight and The Aussie Corporate Feb 2026.
B28: Market size: triangulated from Queensland Government Statistician Office + Flutter Sportsbet A$ segment disclosures + Grand View Research.
B29: Market declined 10% per year 2023-2025 per The Straight (Sep 2025); reflects POC tax hikes, credit card ban, BetStop rollout Aug 2023, and ad restrictions.
B30: Betr launched Oct 2022 (News Corp); PointsBet divested US business 2023 to focus on AU (shares remain small).
B31: Values are estimates with +/-1-2 ppt uncertainty for non-Flutter operators.

Sheet Australia GGY A$m
B2: Australia Online Sports Betting - Operator GGY (A$m)
B4: Operator | C4: 2019 | D4: 2020 | E4: 2021 | F4: 2022 | G4: 2023 | H4: 2024 | I4: 2025 | J4: CAGR 19 to 25
B5: Total Australia online sports betting GGY (A$m) | C5: ='Australia Market Size'!C6 -> 3200 | D5: ='Australia Market Size'!D6 -> 4100 | E5: ='Australia Market Size'!E6 -> 4700 | F5: ='Australia Market Size'!F6 -> 4600 | G5: ='Australia Market Size'!G6 -> 4400 | H5: ='Australia Market Size'!H6 -> 4200 | I5: ='Australia Market Size'!I6 -> 4000
B7: Sportsbet (Flutter) | C7: ='Australia Share %'!C5*C5 -> 896 | D7: ='Australia Share %'!D5*D5 -> 1640 | E7: ='Australia Share %'!E5*E5 -> 2350 | F7: ='Australia Share %'!F5*F5 -> 2208 | G7: ='Australia Share %'!G5*G5 -> 1980 | H7: ='Australia Share %'!H5*H5 -> 1890 | I7: ='Australia Share %'!I5*I5 -> 1800 | J7: =IF(OR(C7=0,I7=0),"n/a",(I7/C7)^(1/6)-1) -> 0.12329566
B8: Tabcorp (TAB) | C8: ='Australia Share %'!C6*C5 -> 896 | D8: ='Australia Share %'!D6*D5 -> 1025 | E8: ='Australia Share %'!E6*E5 -> 1034 | F8: ='Australia Share %'!F6*F5 -> 966 | G8: ='Australia Share %'!G6*G5 -> 1007.6 | H8: ='Australia Share %'!H6*H5 -> 961.8 | I8: ='Australia Share %'!I6*I5 -> 880 | J8: =IF(OR(C8=0,I8=0),"n/a",(I8/C8)^(1/6)-1) -> -0.0029985795
B9: Entain (Ladbrokes, Neds) | C9: ='Australia Share %'!C7*C5 -> 448 | D9: ='Australia Share %'!D7*D5 -> 615 | E9: ='Australia Share %'!E7*E5 -> 752 | F9: ='Australia Share %'!F7*F5 -> 736 | G9: ='Australia Share %'!G7*G5 -> 726 | H9: ='Australia Share %'!H7*H5 -> 714 | I9: ='Australia Share %'!I7*I5 -> 680 | J9: =IF(OR(C9=0,I9=0),"n/a",(I9/C9)^(1/6)-1) -> 0.072025584
B10: bet365 Australia | C10: ='Australia Share %'!C8*C5 -> 192 | D10: ='Australia Share %'!D8*D5 -> 205 | E10: ='Australia Share %'!E8*E5 -> 211.5 | F10: ='Australia Share %'!F8*F5 -> 230 | G10: ='Australia Share %'!G8*G5 -> 220 | H10: ='Australia Share %'!H8*H5 -> 210 | I10: ='Australia Share %'!I8*I5 -> 200 | J10: =IF(OR(C10=0,I10=0),"n/a",(I10/C10)^(1/6)-1) -> 0.0068268633
B11: PointsBet | C11: ='Australia Share %'!C9*C5 -> 96 | D11: ='Australia Share %'!D9*D5 -> 143.5 | E11: ='Australia Share %'!E9*E5 -> 164.5 | F11: ='Australia Share %'!F9*F5 -> 138 | G11: ='Australia Share %'!G9*G5 -> 110 | H11: ='Australia Share %'!H9*H5 -> 84 | I11: ='Australia Share %'!I9*I5 -> 60 | J11: =IF(OR(C11=0,I11=0),"n/a",(I11/C11)^(1/6)-1) -> -0.075344403
B12: Unibet (Kindred) | C12: ='Australia Share %'!C10*C5 -> 80 | D12: ='Australia Share %'!D10*D5 -> 102.5 | E12: ='Australia Share %'!E10*E5 -> 94 | F12: ='Australia Share %'!F10*F5 -> 92 | G12: ='Australia Share %'!G10*G5 -> 88 | H12: ='Australia Share %'!H10*H5 -> 63 | I12: ='Australia Share %'!I10*I5 -> 40 | J12: =IF(OR(C12=0,I12=0),"n/a",(I12/C12)^(1/6)-1) -> -0.10910128
B13: Bluebet | C13: ='Australia Share %'!C11*C5 -> 16 | D13: ='Australia Share %'!D11*D5 -> 41 | E13: ='Australia Share %'!E11*E5 -> 47 | F13: ='Australia Share %'!F11*F5 -> 46 | G13: ='Australia Share %'!G11*G5 -> 66 | H13: ='Australia Share %'!H11*H5 -> 63 | I13: ='Australia Share %'!I11*I5 -> 60 | J13: =IF(OR(C13=0,I13=0),"n/a",(I13/C13)^(1/6)-1) -> 0.24644144
B14: Betr (News Corp) | C14: ='Australia Share %'!C12*C5 -> 0 | D14: ='Australia Share %'!D12*D5 -> 0 | E14: ='Australia Share %'!E12*E5 -> 0 | F14: ='Australia Share %'!F12*F5 -> 46 | G14: ='Australia Share %'!G12*G5 -> 88 | H14: ='Australia Share %'!H12*H5 -> 63 | I14: ='Australia Share %'!I12*I5 -> 60 | J14: =IF(OR(C14=0,I14=0),"n/a",(I14/C14)^(1/6)-1) -> n/a
B15: Other (Picklebet, Palmerbet, Dabble, etc.) | C15: ='Australia Share %'!C13*C5 -> 576 | D15: ='Australia Share %'!D13*D5 -> 328 | E15: ='Australia Share %'!E13*E5 -> 47 | F15: ='Australia Share %'!F13*F5 -> 138 | G15: ='Australia Share %'!G13*G5 -> 114.4 | H15: ='Australia Share %'!H13*H5 -> 151.2 | I15: ='Australia Share %'!I13*I5 -> 220 | J15: =IF(OR(C15=0,I15=0),"n/a",(I15/C15)^(1/6)-1) -> -0.14820837
B16: Total (check vs market) | C16: =SUM(C7:C15) -> 3200 | D16: =SUM(D7:D15) -> 4100 | E16: =SUM(E7:E15) -> 4700 | F16: =SUM(F7:F15) -> 4600 | G16: =SUM(G7:G15) -> 4400 | H16: =SUM(H7:H15) -> 4200 | I16: =SUM(I7:I15) -> 4000 | J16: =(I16/C16)^(1/6)-1 -> 0.037890816
B17: Variance vs market (should be 0) | C17: =ROUND(C16-C5,2) -> 0 | D17: =ROUND(D16-D5,2) -> 0 | E17: =ROUND(E16-E5,2) -> 0 | F17: =ROUND(F16-F5,2) -> 0 | G17: =ROUND(G16-G5,2) -> 0 | H17: =ROUND(H16-H5,2) -> 0 | I17: =ROUND(I16-I5,2) -> 0

Sheet Australia Market Size
B2: Australia - Total Online Sports Betting GGY (A$m)
B4: Metric | C4: 2019 | D4: 2020 | E4: 2021 | F4: 2022 | G4: 2023 | H4: 2024 | I4: 2025
B6: Total Australia online sports betting GGY (A$m) | C6: 3200 | D6: 4100 | E6: 4700 | F6: 4600 | G6: 4400 | H6: 4200 | I6: 4000
B7: YoY growth | C7: n/a | D7: =D6/C6-1 -> 0.28125 | E7: =E6/D6-1 -> 0.14634146 | F7: =F6/E6-1 -> -0.021276596 | G7: =G6/F6-1 -> -0.043478261 | H7: =H6/G6-1 -> -0.045454545 | I7: =I6/H6-1 -> -0.047619048
B9: CAGR 2019 to 2025 | C9: =(I6/C6)^(1/6)-1 -> 0.037890816
B12: Methodology & Sources
B13: Scope: 'Online wagering' in AU combines racing and sports betting; regulated operators typically report these together.
B14: Market anchor: Sportsbet reached 50% share in 2021 (Flutter 2021 Annual Results) and 48% in 2022 (confirmed by Flutter FY22 results).
B15: Sportsbet 2023 and 2024: 45% share per Flutter FY23 / Q1 2025 disclosures (Inside Asian Gaming, The Straight).
B16: Tabcorp digital: 22.9% digital share FY24 per Tabcorp FY24 Annual Report; TAB25 strategy originally targeted 30% by FY25 (unmet).
B17: Entain AU: 16% (2021) rising to 17% (2025) per Entain Market Spotlight and The Aussie Corporate Feb 2026.
B18: Market size: triangulated from Queensland Government Statistician Office + Flutter Sportsbet A$ segment disclosures + Grand View Research.
B19: Market declined 10% per year 2023-2025 per The Straight (Sep 2025); reflects POC tax hikes, credit card ban, BetStop rollout Aug 2023, and ad restrictions.
B20: Betr launched Oct 2022 (News Corp); PointsBet divested US business 2023 to focus on AU (shares remain small).
B21: Values are estimates with +/-1-2 ppt uncertainty for non-Flutter operators.

Sheet Italy Share %
B2: Italy Online Sports Betting - Operator Market Share (%)
B3: Note: online sports betting only (scommesse sportive online). ADM is the regulator.
B4: Operator | C4: 2019 | D4: 2020 | E4: 2021 | F4: 2022 | G4: 2023 | H4: 2024 | I4: 2025 | J4: Delta 19 to 25
B5: Bet365 | C5: 0.157 | D5: 0.14 | E5: 0.155 | F5: 0.165 | G5: 0.168 | H5: 0.14 | I5: 0.125 | J5: =I5-C5 -> -0.032
B6: Lottomatica (incl. Goldbet, Betflag, Planetwin365) | C6: 0.08 | D6: 0.09 | E6: 0.12 | F6: 0.155 | G6: 0.198 | H6: 0.22 | I6: 0.24 | J6: =I6-C6 -> 0.16
B7: Snai (Snaitech, Flutter from Apr-25) | C7: 0.15 | D7: 0.13 | E7: 0.13 | F7: 0.13 | G7: 0.129 | H7: 0.13 | I7: 0.135 | J7: =I7-C7 -> -0.015
B8: Sisal (Flutter from Aug-22) | C8: 0.12 | D8: 0.12 | E8: 0.125 | F8: 0.128 | G8: 0.13 | H8: 0.135 | I8: 0.14 | J8: =I8-C8 -> 0.02
B9: Eurobet (Entain) | C9: 0.105 | D9: 0.1 | E9: 0.105 | F9: 0.103 | G9: 0.103 | H9: 0.085 | I9: 0.075 | J9: =I9-C9 -> -0.03
B10: Planetwin365 (SKS365) | C10: 0.07 | D10: 0.065 | E10: 0.06 | F10: 0.055 | G10: 0.05 | H10: 0.035 | I10: 0 | J10: =I10-C10 -> -0.07
B11: 888 (Evoke) | C11: 0.03 | D11: 0.04 | E11: 0.035 | F11: 0.03 | G11: 0.028 | H11: 0.025 | I11: 0.02 | J11: =I11-C11 -> -0.01
B12: Goldbet | C12: 0.05 | D12: 0.055 | E12: 0 | F12: 0 | G12: 0 | H12: 0 | I12: 0 | J12: =I12-C12 -> -0.05
B13: Betflag | C13: 0.03 | D13: 0.035 | E13: 0.04 | F13: 0 | G13: 0 | H13: 0 | I13: 0 | J13: =I13-C13 -> -0.03
B14: PokerStars (Flutter) | C14: 0.025 | D14: 0.03 | E14: 0.03 | F14: 0.03 | G14: 0.03 | H14: 0.035 | I14: 0.04 | J14: =I14-C14 -> 0.015
B15: Betfair (Flutter) | C15: 0.02 | D15: 0.02 | E15: 0.02 | F15: 0.02 | G15: 0.02 | H15: 0.02 | I15: 0.02 | J15: =I15-C15 -> 0
B16: DaznBet (Scommettendo) | C16: 0 | D16: 0 | E16: 0 | F16: 0.005 | G16: 0.015 | H16: 0.025 | I16: 0.035 | J16: =I16-C16 -> 0.035
... B18: Other (Admiral, StarCasino, LeoVegas, etc.) | C18: 0.133 | D18: 0.145 | E18: 0.155 | F18: 0.159 | G18: 0.114 | H18: 0.14 | I18: 0.16 | J18: =I18-C18 -> 0.027
B19: Total | C19: =SUM(C5:C18) -> 1 | D19: =SUM(D5:D18) -> 1 | E19: =SUM(E5:E18) -> 1 | F19: =SUM(F5:F18) -> 1 | G19: =SUM(G5:G18) -> 1 | H19: =SUM(H5:H18) -> 1 | I19: =SUM(I5:I18) -> 1 | J19: =I19-C19 -> 0
B21: Concentration Metrics
B22: Top 3 share | C22: =LARGE(C5:C18,1)+LARGE(C5:C18,2)+LARGE(C5:C18,3) -> 0.44 | D22: =LARGE(D5:D18,1)+LARGE(D5:D18,2)+LARGE(D5:D18,3) -> 0.415 | E22: =LARGE(E5:E18,1)+LARGE(E5:E18,2)+LARGE(E5:E18,3) -> 0.44 | F22: =LARGE(F5:F18,1)+LARGE(F5:F18,2)+LARGE(F5:F18,3) -> 0.479 | G22: =LARGE(G5:G18,1)+LARGE(G5:G18,2)+LARGE(G5:G18,3) -> 0.496 | H22: =LARGE(H5:H18,1)+LARGE(H5:H18,2)+LARGE(H5:H18,3) -> 0.5 | I22: =LARGE(I5:I18,1)+LARGE(I5:I18,2)+LARGE(I5:I18,3) -> 0.54 | J22: =I22-C22 -> 0.1
B23: Long tail (non Top 3) | C23: =1-C22 -> 0.56 | D23: =1-D22 -> 0.585 | E23: =1-E22 -> 0.56 | F23: =1-F22 -> 0.521 | G23: =1-G22 -> 0.504 | H23: =1-H22 -> 0.5 | I23: =1-I22 -> 0.46 | J23: =I23-C23 -> -0.1
B24: HHI (Herfindahl index) | C24: =SUMPRODUCT((C5:C18*100)^2) -> 1077.88 | D24: =SUMPRODUCT((D5:D18*100)^2) -> 1023 | E24: =SUMPRODUCT((E5:E18*100)^2) -> 1143.5 | F24: =SUMPRODUCT((F5:F18*100)^2) -> 1260.74 | G24: =SUMPRODUCT((G5:G18*100)^2) -> 1296.08 | H24: =SUMPRODUCT((H5:H18*100)^2) -> 1341.5 | I24: =SUMPRODUCT((I5:I18*100)^2) -> 1460
B27: Sources & Notes
B28: Scope: online sports betting only (scommesse sportive a quota fissa); excludes retail, lotteries, casino, poker.
B29: Market size and shares sourced from ADM (Agenzia delle Dogane e dei Monopoli), the Italian gaming regulator, which publishes monthly operator-level data.
B30: Data is aggregated and analysed by Ficom Leisure (for iGB), Agimeg, Statista, and SBC News.
B31: Key M&A: Lottomatica acquired Goldbet (2021), Betflag (2022), SKS365/Planetwin365 (announced 2024). Post-consolidation, Lottomatica brands exceed 30% of online market.
B32: Flutter acquired Sisal in Aug 2022 (€1.9bn) and Snaitech from Playtech in Apr 2025 (€2.3bn). Combined Flutter Italian online share c.27% by end-2025.
B33: Bet365 held the top spot early in the period but is losing share post 2023 per Agimeg; Italy-specific regulatory pressure.
B34: 2025 reflects the Reorganisation Decree and new licensing regime starting Dec 2025; Betway and Unibet exited the market.
B35: Entain acquired Enlabs 2021 and continues with the Eurobet brand; Eurobet share declining.
B36: Sum of 'named' operator shares plus 'Other' sums to 100.0% each year (check row in GGY tab).

Sheet Italy GGY EURm
B2: Italy Online Sports Betting - Operator GGY (EURm)
B4: Operator | C4: 2019 | D4: 2020 | E4: 2021 | F4: 2022 | G4: 2023 | H4: 2024 | I4: 2025 | J4: CAGR 19 to 25
B5: Total Italy online sports betting GGY (EURm) | C5: ='Italy Market Size'!C6 -> 650 | D5: ='Italy Market Size'!D6 -> 990 | E5: ='Italy Market Size'!E6 -> 1200 | F5: ='Italy Market Size'!F6 -> 1335 | G5: ='Italy Market Size'!G6 -> 1500 | H5: ='Italy Market Size'!H6 -> 1620 | I5: ='Italy Market Size'!I6 -> 1700
B7: Bet365 | C7: ='Italy Share %'!C5*C5 -> 102.05 | D7: ='Italy Share %'!D5*D5 -> 138.6 | E7: ='Italy Share %'!E5*E5 -> 186 | F7: ='Italy Share %'!F5*F5 -> 220.275 | G7: ='Italy Share %'!G5*G5 -> 252 | H7: ='Italy Share %'!H5*H5 -> 226.8 | I7: ='Italy Share %'!I5*I5 -> 212.5 | J7: =IF(OR(C7=0,I7=0),"n/a",(I7/C7)^(1/6)-1) -> 0.13003264
B8: Lottomatica (incl. Goldbet, Betflag, Planetwin365) | C8: ='Italy Share %'!C6*C5 -> 52 | D8: ='Italy Share %'!D6*D5 -> 89.1 | E8: ='Italy Share %'!E6*E5 -> 144 | F8: ='Italy Share %'!F6*F5 -> 206.925 | G8: ='Italy Share %'!G6*G5 -> 297 | H8: ='Italy Share %'!H6*H5 -> 356.4 | I8: ='Italy Share %'!I6*I5 -> 408 | J8: =IF(OR(C8=0,I8=0),"n/a",(I8/C8)^(1/6)-1) -> 0.40964407
B9: Snai (Snaitech, Flutter from Apr-25) | C9: ='Italy Share %'!C7*C5 -> 97.5 | D9: ='Italy Share %'!D7*D5 -> 128.7 | E9: ='Italy Share %'!E7*E5 -> 156 | F9: ='Italy Share %'!F7*F5 -> 173.55 | G9: ='Italy Share %'!G7*G5 -> 193.5 | H9: ='Italy Share %'!H7*H5 -> 210.6 | I9: ='Italy Share %'!I7*I5 -> 229.5 | J9: =IF(OR(C9=0,I9=0),"n/a",(I9/C9)^(1/6)-1) -> 0.15335503
B10: Sisal (Flutter from Aug-22) | C10: ='Italy Share %'!C8*C5 -> 78 | D10: ='Italy Share %'!D8*D5 -> 118.8 | E10: ='Italy Share %'!E8*E5 -> 150 | F10: ='Italy Share %'!F8*F5 -> 170.88 | G10: ='Italy Share %'!G8*G5 -> 195 | H10: ='Italy Share %'!H8*H5 -> 218.7 | I10: ='Italy Share %'!I8*I5 -> 238 | J10: =IF(OR(C10=0,I10=0),"n/a",(I10/C10)^(1/6)-1) -> 0.20433431
B11: Eurobet (Entain) | C11: ='Italy Share %'!C9*C5 -> 68.25 | D11: ='Italy Share %'!D9*D5 -> 99 | E11: ='Italy Share %'!E9*E5 -> 126 | F11: ='Italy Share %'!F9*F5 -> 137.505 | G11: ='Italy Share %'!G9*G5 -> 154.5 | H11: ='Italy Share %'!H9*H5 -> 137.7 | I11: ='Italy Share %'!I9*I5 -> 127.5 | J11: =IF(OR(C11=0,I11=0),"n/a",(I11/C11)^(1/6)-1) -> 0.10977411
B12: Planetwin365 (SKS365) | C12: ='Italy Share %'!C10*C5 -> 45.5 | D12: ='Italy Share %'!D10*D5 -> 64.35 | E12: ='Italy Share %'!E10*E5 -> 72 | F12: ='Italy Share %'!F10*F5 -> 73.425 | G12: ='Italy Share %'!G10*G5 -> 75 | H12: ='Italy Share %'!H10*H5 -> 56.7 | I12: ='Italy Share %'!I10*I5 -> 0 | J12: =IF(OR(C12=0,I12=0),"n/a",(I12/C12)^(1/6)-1) -> n/a
B13: 888 (Evoke) | C13: ='Italy Share %'!C11*C5 -> 19.5 | D13: ='Italy Share %'!D11*D5 -> 39.6 | E13: ='Italy Share %'!E11*E5 -> 42 | F13: ='Italy Share %'!F11*F5 -> 40.05 | G13: ='Italy Share %'!G11*G5 -> 42 | H13: ='Italy Share %'!H11*H5 -> 40.5 | I13: ='Italy Share %'!I11*I5 -> 34 | J13: =IF(OR(C13=0,I13=0),"n/a",(I13/C13)^(1/6)-1) -> 0.097086113
B14: Goldbet | C14: ='Italy Share %'!C12*C5 -> 32.5 | D14: ='Italy Share %'!D12*D5 -> 54.45 | E14: ='Italy Share %'!E12*E5 -> 0 | F14: ='Italy Share %'!F12*F5 -> 0 | G14: ='Italy Share %'!G12*G5 -> 0 | H14: ='Italy Share %'!H12*H5 -> 0 | I14: ='Italy Share %'!I12*I5 -> 0 | J14: =IF(OR(C14=0,I14=0),"n/a",(I14/C14)^(1/6)-1) -> n/a
B15: Betflag | C15: ='Italy Share %'!C13*C5 -> 19.5 | D15: ='Italy Share %'!D13*D5 -> 34.65 | E15: ='Italy Share %'!E13*E5 -> 48 | F15: ='Italy Share %'!F13*F5 -> 0 | G15: ='Italy Share %'!G13*G5 -> 0 | H15: ='Italy Share %'!H13*H5 -> 0 | I15: ='Italy Share %'!I13*I5 -> 0 | J15: =IF(OR(C15=0,I15=0),"n/a",(I15/C15)^(1/6)-1) -> n/a
B16: PokerStars (Flutter) | C16: ='Italy Share %'!C14*C5 -> 16.25 | D16: ='Italy Share %'!D14*D5 -> 29.7 | E16: ='Italy Share %'!E14*E5 -> 36 | F16: ='Italy Share %'!F14*F5 -> 40.05 | G16: ='Italy Share %'!G14*G5 -> 45 | H16: ='Italy Share %'!H14*H5 -> 56.7 | I16: ='Italy Share %'!I14*I5 -> 68 | J16: =IF(OR(C16=0,I16=0),"n/a",(I16/C16)^(1/6)-1) -> 0.26943146
B17: Betfair (Flutter) | C17: ='Italy Share %'!C15*C5 -> 13 | D17: ='Italy Share %'!D15*D5 -> 19.8 | E17: ='Italy Share %'!E15*E5 -> 24 | F17: ='Italy Share %'!F15*F5 -> 26.7 | G17: ='Italy Share %'!G15*G5 -> 30 | H17: ='Italy Share %'!H15*H5 -> 32.4 | I17: ='Italy Share %'!I15*I5 -> 34 | J17: =IF(OR(C17=0,I17=0),"n/a",(I17/C17)^(1/6)-1) -> 0.17378691
B18: DaznBet (Scommettendo) | C18: ='Italy Share %'!C16*C5 -> 0 | D18: ='Italy Share %'!D16*D5 -> 0 | E18: ='Italy Share %'!E16*E5 -> 0 | F18: ='Italy Share %'!F16*F5 -> 6.675 | G18: ='Italy Share %'!G16*G5 -> 22.5 | H18: ='Italy Share %'!H16*H5 -> 40.5 | I18: ='Italy Share %'!I16*I5 -> 59.5 | J18: =IF(OR(C18=0,I18=0),"n/a",(I18/C18)^(1/6)-1) -> n/a
B19: bwin (Entain) | C19: ='Italy Share %'!C17*C5 -> 19.5 | D19: ='Italy Share %'!D17*D5 -> 29.7 | E19: ='Italy Share %'!E17*E5 -> 30 | F19: ='Italy Share %'!F17*F5 -> 26.7 | G19: ='Italy Share %'!G17*G5 -> 22.5 | H19: ='Italy Share %'!H17*H5 -> 16.2 | I19: ='Italy Share %'!I17*I5 -> 17 | J19: =IF(OR(C19=0,I19=0),"n/a",(I19/C19)^(1/6)-1) -> -0.022607389
B20: Other (Admiral, StarCasino, LeoVegas, etc.) | C20: ='Italy Share %'!C18*C5 -> 86.45 | D20: ='Italy Share %'!D18*D5 -> 143.55 | E20: ='Italy Share %'!E18*E5 -> 186 | F20: ='Italy Share %'!F18*F5 -> 212.265 | G20: ='Italy Share %'!G18*G5 -> 171 | H20: ='Italy Share %'!H18*H5 -> 226.8 | I20: ='Italy Share %'!I18*I5 -> 272 | J20: =IF(OR(C20=0,I20=0),"n/a",(I20/C20)^(1/6)-1) -> 0.21050704
B21: Total (check vs market) | C21: =SUM(C7:C20) -> 650 | D21: =SUM(D7:D20) -> 990 | E21: =SUM(E7:E20) -> 1200 | F21: =SUM(F7:F20) -> 1335 | G21: =SUM(G7:G20) -> 1500 | H21: =SUM(H7:H20) -> 1620 | I21: =SUM(I7:I20) -> 1700 | J21: =(I21/C21)^(1/6)-1 -> 0.17378691
B22: Variance vs market (should be 0) | C22: =ROUND(C21-C5,2) -> 0 | D22: =ROUND(D21-D5,2) -> 0 | E22: =ROUND(E21-E5,2) -> 0 | F22: =ROUND(F21-F5,2) -> 0 | G22: =ROUND(G21-G5,2) -> 0 | H22: =ROUND(H21-H5,2) -> 0 | I22: =ROUND(I21-I5,2) -> 0

Sheet Italy Market Size
B2: Italy - Total Online Sports Betting GGY (EURm)
B4: Metric | C4: 2019 | D4: 2020 | E4: 2021 | F4: 2022 | G4: 2023 | H4: 2024 | I4: 2025
B6: Total Italy online sports betting GGY (EURm) | C6: 650 | D6: 990 | E6: 1200 | F6: 1335 | G6: 1500 | H6: 1620 | I6: 1700
B7: YoY growth | C7: n/a | D7: =D6/C6-1 -> 0.52307692 | E7: =E6/D6-1 -> 0.21212121 | F7: =F6/E6-1 -> 0.1125 | G7: =G6/F6-1 -> 0.12359551 | H7: =H6/G6-1 -> 0.08 | I7: =I6/H6-1 -> 0.049382716
B9: CAGR 2019 to 2025 | C9: =(I6/C6)^(1/6)-1 -> 0.17378691
B12: Methodology & Sources
B13: Scope: online sports betting only (scommesse sportive a quota fissa); excludes retail, lotteries, casino, poker.
B14: Market size and shares sourced from ADM (Agenzia delle Dogane e dei Monopoli), the Italian gaming regulator, which publishes monthly operator-level data.
B15: Data is aggregated and analysed by Ficom Leisure (for iGB), Agimeg, Statista, and SBC News.
B16: Key M&A: Lottomatica acquired Goldbet (2021), Betflag (2022), SKS365/Planetwin365 (announced 2024). Post-consolidation, Lottomatica brands exceed 30% of online market.
B17: Flutter acquired Sisal in Aug 2022 (€1.9bn) and Snaitech from Playtech in Apr 2025 (€2.3bn). Combined Flutter Italian online share c.27% by end-2025.
B18: Bet365 held the top spot early in the period but is losing share post 2023 per Agimeg; Italy-specific regulatory pressure.
B19: 2025 reflects the Reorganisation Decree and new licensing regime starting Dec 2025; Betway and Unibet exited the market.
B20: Entain acquired Enlabs 2021 and continues with the Eurobet brand; Eurobet share declining.
B21: Sum of 'named' operator shares plus 'Other' sums to 100.0% each year (check row in GGY tab).

Sheet Sources
B2: Sources & Methodology
B4: Market Share Anchors
B5: Flutter (UKI online sports) | C5: Flutter 2022 Annual Report: 38% UKI online sportsbook share. Flutter Q4 2024 Results: '+4 ppts over 2 years' implying ~42% by end-2024. Q1/Q2 2025 shareholder letters confirm continued share gains. | D5: flutter.com/investors
B6: Entain (UKI online) | C6: Entain 2023 and 2024 Annual Reports + H1 2024/2025 Results. H1 2024: UKI online NGR -8% YoY (share loss). H1 2025: UKI online NGR +21% YoY 'regaining market share'. 2025 £681m after-tax loss including £488m impairment flagged UK pressures. | D6: entaingroup.com
B7: bet365 | C7: Privately held, no direct share disclosure. Estimates derived from: (i) Similarweb 2022 web traffic = 28% share of top 9 sites; (ii) YouGov Feb 2024 survey = 36% of UK online sports account holders; (iii) Pi Datametrics 2022 Google searches = 27.6% share; (iv) Adthena PPC click share; (v) Eilers & Krejcik Gaming (EKG) Line estimates 2024. | D7: similarweb.com; yougov.com; adthena.com
B8: Evoke (888 / William Hill) | C8: 888 Holdings acquired William Hill non-US for £2.2bn in July 2022. Evoke (rebranded July 2024) reports UK&I online betting segment NGR. Share decline from integration issues, brand confusion, and management change through 2023-2024. | D8: evokeplc.com
B9: Betfred | C9: Private (Done Group Ltd). Share estimated from Companies House filings, Similarweb traffic surge 2022-2024, Adthena PPC data (Betfred peaked at 31% PPC impressions March 2026). | D9: beta.companieshouse.gov.uk
B10: Long tail | C10: Betway (Super Group annual report UK segment), BetVictor, Unibet (Kindred segment disclosure), Tote, DAZN Bet, LiveScore Bet, Bet UK, Paddy's Rewards. Residual calculated to balance to 100%. | D10: Various annual reports
B13: Market Size Sources
B14: UK Gambling Commission | C14: Industry Statistics (published semi-annually May + Nov). Provides Gross Gambling Yield for remote real-event betting (i.e. sports betting). Reports are financial-year (April-March). | D14: gamblingcommission.gov.uk
B15: UKGC Market Overview | C15: 'Market Overview - operator data' publications (quarterly). Covers largest operators only, includes free bets/bonuses. Used as cross-check. | D15: gamblingcommission.gov.uk
B16: Statista / industry reports | C16: Statista UK online sports betting market size ($2.29bn 2017 → $4.21bn 2023, forecast $5.69bn 2029). Grand View Research, Horizon Databook used as corroboration. | D16: statista.com
B17: Regulus Partners | C17: Leading independent industry analyst (Paul Leyland). Cited widely in next.io, iGaming Business, and referenced in Entain's Annual Report 2023 for Online NGR forecasts. | D17: regulus-partners.com
B20: Methodology Notes
B21: 1. Anchor point: Flutter 2022 = 38% (disclosed). All other years backed into from disclosed deltas.
B22: 2. Flutter +4ppt over '2 years' (Q4 2024) => 2024 ~42%, consistent with 2022 anchor.
B23: 3. Flutter acquired Sky Bet via Stars Group merger in May 2020 - included in Flutter share from 2020 onwards.
B24: 4. 888 acquired William Hill non-US in July 2022 - combined as 'Evoke' for 2022 onwards; pre-2022 numbers aggregate.
B25: 5. Total market pegged to UKGC real-event remote betting GGY, adjusted for cross-year timing.
B26: 6. Shares sum to exactly 100% each year (check row in Market Share % tab).
B27: 7. Shares are gross-gambling-yield (GGY) based, not turnover/handle. GGY ≈ stakes minus winnings paid.
B28: 8. Ireland included in 'Flutter UKI' but represents ~5% of UKI revenue to treated as proxy for UK-only share.
B29: 9. Long tail residual ensures 100% close; contains 30+ smaller operators individually <1% share each.
B30: 10. This model is indicative. Flutter and Entain figures are disclosed; others are triangulated estimates.
B33: AUSTRALIA - Market Share Anchors
B34: Flutter Sportsbet | C34: Flutter annual and quarterly results; Sportsbet claimed 50% market share in 2021 (FY21 results), 48% in 2022 (FY22 results), 45% in 2023-24 (FY23 & Q1 2025). Revenue and AMP disclosures confirm trajectory. | D34: flutter.com/investors
B35: Tabcorp (TAB) | C35: Tabcorp Annual Reports, H1 2023 results disclosed 34.8% total wagering share, FY24 Annual Report disclosed 22.9% DIGITAL share. TAB25 strategy targeted 30% digital share by FY25 (unmet). | D35: tabcorp.com.au
B36: Entain Australia | C36: Entain 'Market Spotlight: Australia' (2021): c.16% digital share. The Aussie Corporate (Feb 2026): c.17% digital share. Ladbrokes and Neds online-only brands. | D36: entaingroup.com
B37: PointsBet, Bluebet, Betr | C37: ASX-listed PointsBet and Bluebet disclose AU segment revenue; Betr launched by News Corp in Oct 2022. Shares triangulated from revenue disclosures and IBISWorld Horse and Sports Betting Australia report. | D37: asx.com.au; ibisworld.com
B38: AU market size | C38: Queensland Government Statistician Office Australian Gambling Statistics (annual); Grand View Research Australia Sports Betting Outlook 2025-2030 (USD 2.44bn 2024, 79.7% online); Statista Sports Betting Australia (USD 7.32bn 2025 including retail). | D38: qgso.qld.gov.au
B41: ITALY - Market Share Anchors
B42: ADM (Italian regulator) | C42: Agenzia delle Dogane e dei Monopoli publishes monthly operator-level data covering stakes, GGR, and market share for every licensed operator. Transparency unmatched in Europe. | D42: adm.gov.it
B43: Ficom Leisure / iGB | C43: Leading Italian gaming advisory firm. Monthly Italy Dashboard data processed for iGaming Business (iGB) publication. Used for operator ranking and share history 2019-2022. | D43: ficomleisure.com; igamingbusiness.com
B44: Agimeg | C44: Italian gaming industry news agency. Published H1 2023 market share (Lottomatica 19.8%, Bet365 16.8%, Sisal 13.0%, Snai 12.9%) and full year 2023 / 2024 data. | D44: agimeg.it
B45: Lottomatica IR | C45: Lottomatica IPO'd March 2023. FY 2023 and FY 2024 Results Presentations disclose Italian online market share (GGR-based, ADM data). Key acquisitions: Goldbet (2021), Betflag (2022), SKS365/Planetwin365 (closed 2024). | D45: lottomaticagroup.com
B46: Flutter Italy | C46: Flutter acquired Sisal Aug 2022 (EUR 1.9bn) and Snaitech from Playtech Apr 2025 (EUR 2.3bn). Q4 2024 Flutter results disclosed Sisal share 15.0% (+230bps YoY). Combined Flutter Italy share 21-22% in 2024, rising to 34% post Snai integration. | D46: flutter.com
B47: SBC News / Casino Life | C47: Sector news coverage of Italian operator performance by month, including 2025 consolidation, Betway and Unibet exits, and the new Reorganisation Decree. | D47: sbcnews.co.uk; casinolifemagazine.com
