Workbook

Sheet Summary
A1: The K-pop boom is a Live Nation story
A2: Joint note · LYV section · the geographic case + the moat. Source: Pollstar Data Cloud (Boxoffice), Asian Pop, pulled Jun-2026.
A4: US = largest K-pop market | D4: LN share of US K-pop | G4: LN share of Western K-pop | J4: Self-promotion risk
A5: =Analysis_Geographic!B11/1000 -> 1.0147558 | D5: =Analysis_Geographic!D11 -> 0.45216031 | G5: =Analysis_Geographic!D6 -> 0.50200042 | J5: HYBE only
A8: Two exhibits, two jobs
A9: EX 1 (Geography) — assert the thesis.
A10: The US is the single largest K-pop touring market in the world (~$1.0bn, ahead of Japan) and Spotify's #1 K-pop streaming market. LN promotes ~45% of US K-pop, ~80% of Mexico via OCESA, ~59% of France/UK — and ~50% of all Western K-pop gross, vs ~2% in Asia. The boom is Western; the West is LN's.
A13: EX 2 (Segmentation) — defend it.
A14: Promoter tracks the agency, not the genre. JYP's touring is ~95-97% Live Nation (Stray Kids, TWICE); the other majors largely ride LN or AEG. Self-promotion — the one structural threat — is contained to HYBE alone.
A17: Precision (what the exhibits don't say).
A18: LN's Western share is sticky, not rising — ~half across the cycle but lumpy year to year on tour timing. The geographic claim is that the US is the largest and highest-ARPU market, not that the West is taking share from a still-growing Asia. Even HYBE co-promotes ~35% of its US grosses with LN.
A22: Tabs: Exhibit_1_Geography · Exhibit_2_Segmentation · Analysis_Geographic · Analysis_ActSegmentation · Data_AsianPop (1,629 boxscores). All figures live SUMIFS over the data.

Sheet Exhibit_1_Geography
A1: Exhibit 1 — The K-pop boom is migrating into Live Nation's markets
A2: K-pop touring gross by market ($mm, tracked lifetime); Live Nation share noted. US is the largest market; ~half is LN. Source: Pollstar Data Cloud.
A4: Market | B4: LN ($mm) | C4: Other ($mm)
A5: United States | B5: =SUMIFS(Data_AsianPop!$V$2:$V$1630,Data_AsianPop!$H$2:$H$1630,A5,Data_AsianPop!$X$2:$X$1630,1)/1000000 -> 458.8323 | C5: =(SUMIFS(Data_AsianPop!$V$2:$V$1630,Data_AsianPop!$H$2:$H$1630,A5)-SUMIFS(Data_AsianPop!$V$2:$V$1630,Data_AsianPop!$H$2:$H$1630,A5,Data_AsianPop!$X$2:$X$1630,1))/1000000 -> 555.9235
A6: Japan | B6: =SUMIFS(Data_AsianPop!$V$2:$V$1630,Data_AsianPop!$H$2:$H$1630,A6,Data_AsianPop!$X$2:$X$1630,1)/1000000 -> 0 | C6: =(SUMIFS(Data_AsianPop!$V$2:$V$1630,Data_AsianPop!$H$2:$H$1630,A6)-SUMIFS(Data_AsianPop!$V$2:$V$1630,Data_AsianPop!$H$2:$H$1630,A6,Data_AsianPop!$X$2:$X$1630,1))/1000000 -> 734.47539
A7: China | B7: =SUMIFS(Data_AsianPop!$V$2:$V$1630,Data_AsianPop!$H$2:$H$1630,A7,Data_AsianPop!$X$2:$X$1630,1)/1000000 -> 4.4031176 | C7: =(SUMIFS(Data_AsianPop!$V$2:$V$1630,Data_AsianPop!$H$2:$H$1630,A7)-SUMIFS(Data_AsianPop!$V$2:$V$1630,Data_AsianPop!$H$2:$H$1630,A7,Data_AsianPop!$X$2:$X$1630,1))/1000000 -> 144.35296
A8: Mexico | B8: =SUMIFS(Data_AsianPop!$V$2:$V$1630,Data_AsianPop!$H$2:$H$1630,A8,Data_AsianPop!$X$2:$X$1630,1)/1000000 -> 115.38847 | C8: =(SUMIFS(Data_AsianPop!$V$2:$V$1630,Data_AsianPop!$H$2:$H$1630,A8)-SUMIFS(Data_AsianPop!$V$2:$V$1630,Data_AsianPop!$H$2:$H$1630,A8,Data_AsianPop!$X$2:$X$1630,1))/1000000 -> 27.956869
A9: South Korea | B9: =SUMIFS(Data_AsianPop!$V$2:$V$1630,Data_AsianPop!$H$2:$H$1630,A9,Data_AsianPop!$X$2:$X$1630,1)/1000000 -> 0 | C9: =(SUMIFS(Data_AsianPop!$V$2:$V$1630,Data_AsianPop!$H$2:$H$1630,A9)-SUMIFS(Data_AsianPop!$V$2:$V$1630,Data_AsianPop!$H$2:$H$1630,A9,Data_AsianPop!$X$2:$X$1630,1))/1000000 -> 135.13456
A10: Hong Kong | B10: =SUMIFS(Data_AsianPop!$V$2:$V$1630,Data_AsianPop!$H$2:$H$1630,A10,Data_AsianPop!$X$2:$X$1630,1)/1000000 -> 6.8391455 | C10: =(SUMIFS(Data_AsianPop!$V$2:$V$1630,Data_AsianPop!$H$2:$H$1630,A10)-SUMIFS(Data_AsianPop!$V$2:$V$1630,Data_AsianPop!$H$2:$H$1630,A10,Data_AsianPop!$X$2:$X$1630,1))/1000000 -> 122.37408
A11: France | B11: =SUMIFS(Data_AsianPop!$V$2:$V$1630,Data_AsianPop!$H$2:$H$1630,A11,Data_AsianPop!$X$2:$X$1630,1)/1000000 -> 52.039415 | C11: =(SUMIFS(Data_AsianPop!$V$2:$V$1630,Data_AsianPop!$H$2:$H$1630,A11)-SUMIFS(Data_AsianPop!$V$2:$V$1630,Data_AsianPop!$H$2:$H$1630,A11,Data_AsianPop!$X$2:$X$1630,1))/1000000 -> 36.182069
A12: United Kingdom | B12: =SUMIFS(Data_AsianPop!$V$2:$V$1630,Data_AsianPop!$H$2:$H$1630,A12,Data_AsianPop!$X$2:$X$1630,1)/1000000 -> 50.247136 | C12: =(SUMIFS(Data_AsianPop!$V$2:$V$1630,Data_AsianPop!$H$2:$H$1630,A12)-SUMIFS(Data_AsianPop!$V$2:$V$1630,Data_AsianPop!$H$2:$H$1630,A12,Data_AsianPop!$X$2:$X$1630,1))/1000000 -> 35.143145
A13: Australia | B13: =SUMIFS(Data_AsianPop!$V$2:$V$1630,Data_AsianPop!$H$2:$H$1630,A13,Data_AsianPop!$X$2:$X$1630,1)/1000000 -> 14.416621 | C13: =(SUMIFS(Data_AsianPop!$V$2:$V$1630,Data_AsianPop!$H$2:$H$1630,A13)-SUMIFS(Data_AsianPop!$V$2:$V$1630,Data_AsianPop!$H$2:$H$1630,A13,Data_AsianPop!$X$2:$X$1630,1))/1000000 -> 60.324753

Sheet Exhibit_2_Segmentation
A1: Exhibit 2 — Promoter tracks the agency: the moat is broad, the risk is named
A2: Lifetime tracked gross by act, split by promoter, clustered by agency. JYP rides Live Nation (~95%); self-promotion is contained to HYBE. Source: Pollstar Data Cloud.
A4: Act | B4: LN ($mm) | C4: Other ($mm)
A5: BTS (HYBE) | B5: =SUMIFS(Data_AsianPop!$V$2:$V$1630,Data_AsianPop!$C$2:$C$1630,"BTS",Data_AsianPop!$X$2:$X$1630,1)/1000000 -> 138.55167 | C5: =(SUMIFS(Data_AsianPop!$V$2:$V$1630,Data_AsianPop!$C$2:$C$1630,"BTS")-SUMIFS(Data_AsianPop!$V$2:$V$1630,Data_AsianPop!$C$2:$C$1630,"BTS",Data_AsianPop!$X$2:$X$1630,1))/1000000 -> 287.51612
A6: SEVENTEEN (HYBE) | B6: =SUMIFS(Data_AsianPop!$V$2:$V$1630,Data_AsianPop!$C$2:$C$1630,"SEVENTEEN",Data_AsianPop!$X$2:$X$1630,1)/1000000 -> 60.960052 | C6: =(SUMIFS(Data_AsianPop!$V$2:$V$1630,Data_AsianPop!$C$2:$C$1630,"SEVENTEEN")-SUMIFS(Data_AsianPop!$V$2:$V$1630,Data_AsianPop!$C$2:$C$1630,"SEVENTEEN",Data_AsianPop!$X$2:$X$1630,1))/1000000 -> 341.60145
A7: TXT (HYBE) | B7: =SUMIFS(Data_AsianPop!$V$2:$V$1630,Data_AsianPop!$C$2:$C$1630,"TOMORROW X TOGETHER",Data_AsianPop!$X$2:$X$1630,1)/1000000 -> 20.204609 | C7: =(SUMIFS(Data_AsianPop!$V$2:$V$1630,Data_AsianPop!$C$2:$C$1630,"TOMORROW X TOGETHER")-SUMIFS(Data_AsianPop!$V$2:$V$1630,Data_AsianPop!$C$2:$C$1630,"TOMORROW X TOGETHER",Data_AsianPop!$X$2:$X$1630,1))/1000000 -> 217.59703
A8: ENHYPEN (HYBE) | B8: =SUMIFS(Data_AsianPop!$V$2:$V$1630,Data_AsianPop!$C$2:$C$1630,"ENHYPEN",Data_AsianPop!$X$2:$X$1630,1)/1000000 -> 0 | C8: =(SUMIFS(Data_AsianPop!$V$2:$V$1630,Data_AsianPop!$C$2:$C$1630,"ENHYPEN")-SUMIFS(Data_AsianPop!$V$2:$V$1630,Data_AsianPop!$C$2:$C$1630,"ENHYPEN",Data_AsianPop!$X$2:$X$1630,1))/1000000 -> 192.90105
A9: j-hope (HYBE) | B9: =SUMIFS(Data_AsianPop!$V$2:$V$1630,Data_AsianPop!$C$2:$C$1630,"j-hope",Data_AsianPop!$X$2:$X$1630,1)/1000000 -> 34.2336 | C9: =(SUMIFS(Data_AsianPop!$V$2:$V$1630,Data_AsianPop!$C$2:$C$1630,"j-hope")-SUMIFS(Data_AsianPop!$V$2:$V$1630,Data_AsianPop!$C$2:$C$1630,"j-hope",Data_AsianPop!$X$2:$X$1630,1))/1000000 -> 44.948614
A10: Stray Kids (JYP) | B10: =SUMIFS(Data_AsianPop!$V$2:$V$1630,Data_AsianPop!$C$2:$C$1630,"Stray Kids",Data_AsianPop!$X$2:$X$1630,1)/1000000 -> 210.61829 | C10: =(SUMIFS(Data_AsianPop!$V$2:$V$1630,Data_AsianPop!$C$2:$C$1630,"Stray Kids")-SUMIFS(Data_AsianPop!$V$2:$V$1630,Data_AsianPop!$C$2:$C$1630,"Stray Kids",Data_AsianPop!$X$2:$X$1630,1))/1000000 -> 5.7073576
A11: TWICE (JYP) | B11: =SUMIFS(Data_AsianPop!$V$2:$V$1630,Data_AsianPop!$C$2:$C$1630,"TWICE",Data_AsianPop!$X$2:$X$1630,1)/1000000 -> 129.31251 | C11: =(SUMIFS(Data_AsianPop!$V$2:$V$1630,Data_AsianPop!$C$2:$C$1630,"TWICE")-SUMIFS(Data_AsianPop!$V$2:$V$1630,Data_AsianPop!$C$2:$C$1630,"TWICE",Data_AsianPop!$X$2:$X$1630,1))/1000000 -> 6.692779
A12: BLACKPINK (YG) | B12: =SUMIFS(Data_AsianPop!$V$2:$V$1630,Data_AsianPop!$C$2:$C$1630,"BLACKPINK",Data_AsianPop!$X$2:$X$1630,1)/1000000 -> 21.129327 | C12: =(SUMIFS(Data_AsianPop!$V$2:$V$1630,Data_AsianPop!$C$2:$C$1630,"BLACKPINK")-SUMIFS(Data_AsianPop!$V$2:$V$1630,Data_AsianPop!$C$2:$C$1630,"BLACKPINK",Data_AsianPop!$X$2:$X$1630,1))/1000000 -> 64.239779
A13: ATEEZ (KQ) | B13: =SUMIFS(Data_AsianPop!$V$2:$V$1630,Data_AsianPop!$C$2:$C$1630,"ATEEZ",Data_AsianPop!$X$2:$X$1630,1)/1000000 -> 3.7668679 | C13: =(SUMIFS(Data_AsianPop!$V$2:$V$1630,Data_AsianPop!$C$2:$C$1630,"ATEEZ")-SUMIFS(Data_AsianPop!$V$2:$V$1630,Data_AsianPop!$C$2:$C$1630,"ATEEZ",Data_AsianPop!$X$2:$X$1630,1))/1000000 -> 75.253525
E26: HYBE acts (pink) self-promote — mostly 'Other'. JYP acts (teal) ride Live Nation — mostly 'LN'.

Sheet Analysis_Geographic
A1: Geographic analysis — where the K-pop boom lands, and who promotes it
A2: Source: Pollstar Data Cloud (Boxoffice), Asian Pop genre. OCESA grouped into Live Nation. 2026 = on-sales. Live SUMIFS over Data_AsianPop.
A4: Region rollup
A5: Region | B5: Total ($mm) | C5: LN ($mm) | D5: LN share | E5: % of all K-pop
A6: Americas + Europe + ANZ | B6: =SUMIFS(Data_AsianPop!$V$2:$V$1630,Data_AsianPop!$Y$2:$Y$1630,A6)/1000000 -> 1599.7059 | C6: =SUMIFS(Data_AsianPop!$V$2:$V$1630,Data_AsianPop!$Y$2:$Y$1630,A6,Data_AsianPop!$X$2:$X$1630,1)/1000000 -> 803.05302 | D6: =IFERROR(C6/B6,0) -> 0.50200042 | E6: =B6/($B$6+$B$7) -> 0.52803374
A7: Asia / home markets | B7: =SUMIFS(Data_AsianPop!$V$2:$V$1630,Data_AsianPop!$Y$2:$Y$1630,A7)/1000000 -> 1429.8465 | C7: =SUMIFS(Data_AsianPop!$V$2:$V$1630,Data_AsianPop!$Y$2:$Y$1630,A7,Data_AsianPop!$X$2:$X$1630,1)/1000000 -> 25.448444 | D7: =IFERROR(C7/B7,0) -> 0.017798025 | E7: =B7/($B$6+$B$7) -> 0.47196626
A9: Top markets | F9: United States — LN share by year
A10: Country | B10: Total ($mm) | C10: LN ($mm) | D10: LN share | F10: Year | G10: US total ($mm) | H10: LN ($mm) | I10: LN share
A11: United States | B11: =SUMIFS(Data_AsianPop!$V$2:$V$1630,Data_AsianPop!$H$2:$H$1630,A11)/1000000 -> 1014.7558 | C11: =SUMIFS(Data_AsianPop!$V$2:$V$1630,Data_AsianPop!$H$2:$H$1630,A11,Data_AsianPop!$X$2:$X$1630,1)/1000000 -> 458.8323 | D11: =IFERROR(C11/B11,0) -> 0.45216031 | F11: 2019 | G11: =SUMIFS(Data_AsianPop!$V$2:$V$1630,Data_AsianPop!$H$2:$H$1630,"United States",Data_AsianPop!$U$2:$U$1630,F11)/1000000 -> 72.016506 | H11: =SUMIFS(Data_AsianPop!$V$2:$V$1630,Data_AsianPop!$H$2:$H$1630,"United States",Data_AsianPop!$U$2:$U$1630,F11,Data_AsianPop!$X$2:$X$1630,1)/1000000 -> 50.80566 | I11: =IFERROR(H11/G11,0) -> 0.70547244
A12: Japan | B12: =SUMIFS(Data_AsianPop!$V$2:$V$1630,Data_AsianPop!$H$2:$H$1630,A12)/1000000 -> 734.47539 | C12: =SUMIFS(Data_AsianPop!$V$2:$V$1630,Data_AsianPop!$H$2:$H$1630,A12,Data_AsianPop!$X$2:$X$1630,1)/1000000 -> 0 | D12: =IFERROR(C12/B12,0) -> 0 | F12: 2020 | G12: =SUMIFS(Data_AsianPop!$V$2:$V$1630,Data_AsianPop!$H$2:$H$1630,"United States",Data_AsianPop!$U$2:$U$1630,F12)/1000000 -> 3.5290402 | H12: =SUMIFS(Data_AsianPop!$V$2:$V$1630,Data_AsianPop!$H$2:$H$1630,"United States",Data_AsianPop!$U$2:$U$1630,F12,Data_AsianPop!$X$2:$X$1630,1)/1000000 -> 1.369149 | I12: =IFERROR(H12/G12,0) -> 0.38796639
A13: China | B13: =SUMIFS(Data_AsianPop!$V$2:$V$1630,Data_AsianPop!$H$2:$H$1630,A13)/1000000 -> 148.75608 | C13: =SUMIFS(Data_AsianPop!$V$2:$V$1630,Data_AsianPop!$H$2:$H$1630,A13,Data_AsianPop!$X$2:$X$1630,1)/1000000 -> 4.4031176 | D13: =IFERROR(C13/B13,0) -> 0.029599581 | F13: 2021 | G13: =SUMIFS(Data_AsianPop!$V$2:$V$1630,Data_AsianPop!$H$2:$H$1630,"United States",Data_AsianPop!$U$2:$U$1630,F13)/1000000 -> 34.389625 | H13: =SUMIFS(Data_AsianPop!$V$2:$V$1630,Data_AsianPop!$H$2:$H$1630,"United States",Data_AsianPop!$U$2:$U$1630,F13,Data_AsianPop!$X$2:$X$1630,1)/1000000 -> 0 | I13: =IFERROR(H13/G13,0) -> 0
A14: Mexico | B14: =SUMIFS(Data_AsianPop!$V$2:$V$1630,Data_AsianPop!$H$2:$H$1630,A14)/1000000 -> 143.34533 | C14: =SUMIFS(Data_AsianPop!$V$2:$V$1630,Data_AsianPop!$H$2:$H$1630,A14,Data_AsianPop!$X$2:$X$1630,1)/1000000 -> 115.38847 | D14: =IFERROR(C14/B14,0) -> 0.8049684 | F14: 2022 | G14: =SUMIFS(Data_AsianPop!$V$2:$V$1630,Data_AsianPop!$H$2:$H$1630,"United States",Data_AsianPop!$U$2:$U$1630,F14)/1000000 -> 156.02668 | H14: =SUMIFS(Data_AsianPop!$V$2:$V$1630,Data_AsianPop!$H$2:$H$1630,"United States",Data_AsianPop!$U$2:$U$1630,F14,Data_AsianPop!$X$2:$X$1630,1)/1000000 -> 43.577077 | I14: =IFERROR(H14/G14,0) -> 0.27929248
A15: South Korea | B15: =SUMIFS(Data_AsianPop!$V$2:$V$1630,Data_AsianPop!$H$2:$H$1630,A15)/1000000 -> 135.13456 | C15: =SUMIFS(Data_AsianPop!$V$2:$V$1630,Data_AsianPop!$H$2:$H$1630,A15,Data_AsianPop!$X$2:$X$1630,1)/1000000 -> 0 | D15: =IFERROR(C15/B15,0) -> 0 | F15: 2023 | G15: =SUMIFS(Data_AsianPop!$V$2:$V$1630,Data_AsianPop!$H$2:$H$1630,"United States",Data_AsianPop!$U$2:$U$1630,F15)/1000000 -> 194.03332 | H15: =SUMIFS(Data_AsianPop!$V$2:$V$1630,Data_AsianPop!$H$2:$H$1630,"United States",Data_AsianPop!$U$2:$U$1630,F15,Data_AsianPop!$X$2:$X$1630,1)/1000000 -> 107.13756 | I15: =IFERROR(H15/G15,0) -> 0.55216065
A16: Hong Kong | B16: =SUMIFS(Data_AsianPop!$V$2:$V$1630,Data_AsianPop!$H$2:$H$1630,A16)/1000000 -> 129.21322 | C16: =SUMIFS(Data_AsianPop!$V$2:$V$1630,Data_AsianPop!$H$2:$H$1630,A16,Data_AsianPop!$X$2:$X$1630,1)/1000000 -> 6.8391455 | D16: =IFERROR(C16/B16,0) -> 0.052929145 | F16: 2024 | G16: =SUMIFS(Data_AsianPop!$V$2:$V$1630,Data_AsianPop!$H$2:$H$1630,"United States",Data_AsianPop!$U$2:$U$1630,F16)/1000000 -> 133.06454 | H16: =SUMIFS(Data_AsianPop!$V$2:$V$1630,Data_AsianPop!$H$2:$H$1630,"United States",Data_AsianPop!$U$2:$U$1630,F16,Data_AsianPop!$X$2:$X$1630,1)/1000000 -> 48.470808 | I16: =IFERROR(H16/G16,0) -> 0.36426541
A17: France | B17: =SUMIFS(Data_AsianPop!$V$2:$V$1630,Data_AsianPop!$H$2:$H$1630,A17)/1000000 -> 88.221484 | C17: =SUMIFS(Data_AsianPop!$V$2:$V$1630,Data_AsianPop!$H$2:$H$1630,A17,Data_AsianPop!$X$2:$X$1630,1)/1000000 -> 52.039415 | D17: =IFERROR(C17/B17,0) -> 0.58987236 | F17: 2025 | G17: =SUMIFS(Data_AsianPop!$V$2:$V$1630,Data_AsianPop!$H$2:$H$1630,"United States",Data_AsianPop!$U$2:$U$1630,F17)/1000000 -> 238.47534 | H17: =SUMIFS(Data_AsianPop!$V$2:$V$1630,Data_AsianPop!$H$2:$H$1630,"United States",Data_AsianPop!$U$2:$U$1630,F17,Data_AsianPop!$X$2:$X$1630,1)/1000000 -> 143.42257 | I17: =IFERROR(H17/G17,0) -> 0.60141466
A18: United Kingdom | B18: =SUMIFS(Data_AsianPop!$V$2:$V$1630,Data_AsianPop!$H$2:$H$1630,A18)/1000000 -> 85.390281 | C18: =SUMIFS(Data_AsianPop!$V$2:$V$1630,Data_AsianPop!$H$2:$H$1630,A18,Data_AsianPop!$X$2:$X$1630,1)/1000000 -> 50.247136 | D18: =IFERROR(C18/B18,0) -> 0.58844093 | F18: 2026 | G18: =SUMIFS(Data_AsianPop!$V$2:$V$1630,Data_AsianPop!$H$2:$H$1630,"United States",Data_AsianPop!$U$2:$U$1630,F18)/1000000 -> 105.56774 | H18: =SUMIFS(Data_AsianPop!$V$2:$V$1630,Data_AsianPop!$H$2:$H$1630,"United States",Data_AsianPop!$U$2:$U$1630,F18,Data_AsianPop!$X$2:$X$1630,1)/1000000 -> 35.889313 | I18: =IFERROR(H18/G18,0) -> 0.33996477
A19: Australia | B19: =SUMIFS(Data_AsianPop!$V$2:$V$1630,Data_AsianPop!$H$2:$H$1630,A19)/1000000 -> 74.741375 | C19: =SUMIFS(Data_AsianPop!$V$2:$V$1630,Data_AsianPop!$H$2:$H$1630,A19,Data_AsianPop!$X$2:$X$1630,1)/1000000 -> 14.416621 | D19: =IFERROR(C19/B19,0) -> 0.19288676
A20: Thailand | B20: =SUMIFS(Data_AsianPop!$V$2:$V$1630,Data_AsianPop!$H$2:$H$1630,A20)/1000000 -> 61.481621 | C20: =SUMIFS(Data_AsianPop!$V$2:$V$1630,Data_AsianPop!$H$2:$H$1630,A20,Data_AsianPop!$X$2:$X$1630,1)/1000000 -> 2.3121519 | D20: =IFERROR(C20/B20,0) -> 0.037607206

Sheet Analysis_ActSegmentation
A1: Act-level promoter segmentation — agency determines the promoter
A2: Lifetime tracked gross by act, split LN vs other. Label = artist's agency (analyst-assigned). HYBE self-promotes; JYP rides Live Nation.
A4: Act | B4: Label | C4: Total ($mm) | D4: LN ($mm) | E4: Other ($mm) | F4: LN share
A5: BTS | B5: HYBE | C5: =SUMIFS(Data_AsianPop!$V$2:$V$1630,Data_AsianPop!$C$2:$C$1630,A5)/1000000 -> 426.06779 | D5: =SUMIFS(Data_AsianPop!$V$2:$V$1630,Data_AsianPop!$C$2:$C$1630,A5,Data_AsianPop!$X$2:$X$1630,1)/1000000 -> 138.55167 | E5: =C5-D5 -> 287.51612 | F5: =IFERROR(D5/C5,0) -> 0.32518691
A6: SEVENTEEN | B6: HYBE | C6: =SUMIFS(Data_AsianPop!$V$2:$V$1630,Data_AsianPop!$C$2:$C$1630,A6)/1000000 -> 402.5615 | D6: =SUMIFS(Data_AsianPop!$V$2:$V$1630,Data_AsianPop!$C$2:$C$1630,A6,Data_AsianPop!$X$2:$X$1630,1)/1000000 -> 60.960052 | E6: =C6-D6 -> 341.60145 | F6: =IFERROR(D6/C6,0) -> 0.15143041
A7: TOMORROW X TOGETHER | B7: HYBE | C7: =SUMIFS(Data_AsianPop!$V$2:$V$1630,Data_AsianPop!$C$2:$C$1630,A7)/1000000 -> 237.80164 | D7: =SUMIFS(Data_AsianPop!$V$2:$V$1630,Data_AsianPop!$C$2:$C$1630,A7,Data_AsianPop!$X$2:$X$1630,1)/1000000 -> 20.204609 | E7: =C7-D7 -> 217.59703 | F7: =IFERROR(D7/C7,0) -> 0.084964128
A8: ENHYPEN | B8: HYBE | C8: =SUMIFS(Data_AsianPop!$V$2:$V$1630,Data_AsianPop!$C$2:$C$1630,A8)/1000000 -> 192.90105 | D8: =SUMIFS(Data_AsianPop!$V$2:$V$1630,Data_AsianPop!$C$2:$C$1630,A8,Data_AsianPop!$X$2:$X$1630,1)/1000000 -> 0 | E8: =C8-D8 -> 192.90105 | F8: =IFERROR(D8/C8,0) -> 0
A9: j-hope | B9: HYBE | C9: =SUMIFS(Data_AsianPop!$V$2:$V$1630,Data_AsianPop!$C$2:$C$1630,A9)/1000000 -> 79.182215 | D9: =SUMIFS(Data_AsianPop!$V$2:$V$1630,Data_AsianPop!$C$2:$C$1630,A9,Data_AsianPop!$X$2:$X$1630,1)/1000000 -> 34.2336 | E9: =C9-D9 -> 44.948614 | F9: =IFERROR(D9/C9,0) -> 0.43233952
A10: Stray Kids | B10: JYP | C10: =SUMIFS(Data_AsianPop!$V$2:$V$1630,Data_AsianPop!$C$2:$C$1630,A10)/1000000 -> 216.32565 | D10: =SUMIFS(Data_AsianPop!$V$2:$V$1630,Data_AsianPop!$C$2:$C$1630,A10,Data_AsianPop!$X$2:$X$1630,1)/1000000 -> 210.61829 | E10: =C10-D10 -> 5.7073576 | F10: =IFERROR(D10/C10,0) -> 0.97361682
A11: TWICE | B11: JYP | C11: =SUMIFS(Data_AsianPop!$V$2:$V$1630,Data_AsianPop!$C$2:$C$1630,A11)/1000000 -> 136.00529 | D11: =SUMIFS(Data_AsianPop!$V$2:$V$1630,Data_AsianPop!$C$2:$C$1630,A11,Data_AsianPop!$X$2:$X$1630,1)/1000000 -> 129.31251 | E11: =C11-D11 -> 6.692779 | F11: =IFERROR(D11/C11,0) -> 0.9507903
A12: BLACKPINK | B12: YG | C12: =SUMIFS(Data_AsianPop!$V$2:$V$1630,Data_AsianPop!$C$2:$C$1630,A12)/1000000 -> 85.369106 | D12: =SUMIFS(Data_AsianPop!$V$2:$V$1630,Data_AsianPop!$C$2:$C$1630,A12,Data_AsianPop!$X$2:$X$1630,1)/1000000 -> 21.129327 | E12: =C12-D12 -> 64.239779 | F12: =IFERROR(D12/C12,0) -> 0.24750555
A13: ATEEZ | B13: KQ | C13: =SUMIFS(Data_AsianPop!$V$2:$V$1630,Data_AsianPop!$C$2:$C$1630,A13)/1000000 -> 79.020393 | D13: =SUMIFS(Data_AsianPop!$V$2:$V$1630,Data_AsianPop!$C$2:$C$1630,A13,Data_AsianPop!$X$2:$X$1630,1)/1000000 -> 3.7668679 | E13: =C13-D13 -> 75.253525 | F13: =IFERROR(D13/C13,0) -> 0.047669567

Sheet Data_AsianPop
A1: Event Date | B1: Shows | C1: Headliner | D1: Support | E1: Venue | F1: City | G1: State | H1: Country | I1: Market | J1: Venue Type | K1: Currency | L1: Promoter | M1: Genre | N1: Avg Tickets Sold | O1: Avg Gross (USD) | P1: Avg Event Capacity | Q1: Avg Capacity Sold | R1: Tkt Min (USD) | S1: Tkt Max (USD) | T1: Tkt Avg (USD) | U1: Year | V1: Total Gross (USD) | W1: Total Tickets | X1: LN | Y1: Region
A2: 46172 | B2: 1 | C2: i-dle | E2: Qudos Bank Arena | F2: Sydney | H2: Australia | J2: Arena | K2: Australian | L2: IME | M2: Asian Pop | N2: 4754 | O2: 807138.94 | P2: 5999 | Q2: 0.79 | R2: 78.41 | S2: 387.76 | T2: 169.78 | U2: =IFERROR(YEAR(A2),"") -> 2026 | V2: =IFERROR(O2*B2,0) -> 807138.94 | W2: =IFERROR(N2*B2,0) -> 4754 | X2: =IF(OR(ISNUMBER(SEARCH("live nation",L2)),ISNUMBER(SEARCH("ocesa",L2))),1,0) -> 0 | Y2: Americas + Europe + ANZ
A3: 46165 | B3: 1 | C3: "GOLDEN: A K-Pop Party!" | E3: Music Farm | F3: Charleston | G3: South Carolina | H3: United States | I3: Charleston, SC | J3: Club | K3: US DOLLAR | L3: Live Nation, NS2 | M3: Asian Pop, Dance / Electronic | N3: 615 | O3: 11047 | P3: 700 | Q3: 0.87 | R3: 15 | S3: 60 | T3: 17.96 | U3: =IFERROR(YEAR(A3),"") -> 2026 | V3: =IFERROR(O3*B3,0) -> 11047 | W3: =IFERROR(N3*B3,0) -> 615 | X3: =IF(OR(ISNUMBER(SEARCH("live nation",L3)),ISNUMBER(SEARCH("ocesa",L3))),1,0) -> 1 | Y3: Americas + Europe + ANZ
A4: 46152 | B4: 1 | C4: Kstyle PARTY | E4: K-Arena Yokohama | F4: Yokohama | H4: Japan | J4: Arena | K4: Yen | L4: Sogo Tokyo Corporation | M4: Asian Pop | N4: 18909 | O4: 1642995.8 | P4: 18909 | Q4: 1 | R4: 89.36 | S4: 89.36 | T4: 86.89 | U4: =IFERROR(YEAR(A4),"") -> 2026 | V4: =IFERROR(O4*B4,0) -> 1642995.8 | W4: =IFERROR(N4*B4,0) -> 18909 | X4: =IF(OR(ISNUMBER(SEARCH("live nation",L4)),ISNUMBER(SEARCH("ocesa",L4))),1,0) -> 0 | Y4: Asia / home markets
A5: 46151 | B5: 1 | C5: Kstyle PARTY | D5: EYES, TWS, Taemin, BOYNEXTDOOR | E5: K-Arena Yokohama | F5: Yokohama | H5: Japan | J5: Arena | K5: Yen | L5: Sogo Tokyo Corporation | M5: Asian Pop | N5: 18909 | O5: 1689758 | P5: 18909 | Q5: 1 | R5: 89.36 | S5: 89.36 | T5: 89.36 | U5: =IFERROR(YEAR(A5),"") -> 2026 | V5: =IFERROR(O5*B5,0) -> 1689758 | W5: =IFERROR(N5*B5,0) -> 18909 | X5: =IF(OR(ISNUMBER(SEARCH("live nation",L5)),ISNUMBER(SEARCH("ocesa",L5))),1,0) -> 0 | Y5: Asia / home markets
A6: 46150 | B6: 1 | C6: "Forever K-Pop" | E6: Gila River Resorts and Casinos - The Showroom at Wildhorse Pass | F6: Chandler | G6: Arizona | H6: United States | I6: Phoenix (Prescott) | J6: Auditorium / Theatre | K6: US DOLLAR | L6: (In-House Promotion) | M6: Asian Pop, Tribute Acts | N6: 782 | O6: 35900 | P6: 884 | Q6: 0.88 | R6: 29 | S6: 59 | T6: 45.91 | U6: =IFERROR(YEAR(A6),"") -> 2026 | V6: =IFERROR(O6*B6,0) -> 35900 | W6: =IFERROR(N6*B6,0) -> 782 | X6: =IF(OR(ISNUMBER(SEARCH("live nation",L6)),ISNUMBER(SEARCH("ocesa",L6))),1,0) -> 0 | Y6: Americas + Europe + ANZ
A7: 46150 | B7: 1 | C7: EVERGLOW | E7: L'Olympia | F7: Montreal | G7: Quebec | H7: Canada | J7: Club | K7: Canadian | L7: ADEM Company, Inc | M7: Asian Pop | N7: 511 | O7: 46092.88 | P7: 636 | Q7: 0.8 | R7: 65.66 | S7: 242.43 | T7: 90.2 | U7: =IFERROR(YEAR(A7),"") -> 2026 | V7: =IFERROR(O7*B7,0) -> 46092.88 | W7: =IFERROR(N7*B7,0) -> 511 | X7: =IF(OR(ISNUMBER(SEARCH("live nation",L7)),ISNUMBER(SEARCH("ocesa",L7))),1,0) -> 0 | Y7: Americas + Europe + ANZ
A8: 46149 | B8: 3 | C8: BTS | E8: Estadio GNP Seguros | F8: Mexico City | H8: Mexico | J8: Stadium | K8: Pesos | L8: OCESA | M8: Asian Pop | N8: 48587 | O8: 14492588 | P8: 48625 | Q8: 0.99 | R8: 115.95 | S8: 1014.55 | T8: 298.28 | U8: =IFERROR(YEAR(A8),"") -> 2026 | V8: =IFERROR(O8*B8,0) -> 43477766 | W8: =IFERROR(N8*B8,0) -> 145761 | X8: =IF(OR(ISNUMBER(SEARCH("live nation",L8)),ISNUMBER(SEARCH("ocesa",L8))),1,0) -> 1 | Y8: Americas + Europe + ANZ
A9: 46148 | B9: 1 | C9: SIXFONIA | E9: K-Arena Yokohama | F9: Yokohama | H9: Japan | J9: Arena | K9: Yen | L9: Sogo Tokyo Corporation | M9: Asian Pop | N9: 12534 | O9: 714967.72 | P9: 12534 | Q9: 1 | R9: 57.04 | S9: 57.04 | T9: 57.04 | U9: =IFERROR(YEAR(A9),"") -> 2026 | V9: =IFERROR(O9*B9,0) -> 714967.72 | W9: =IFERROR(N9*B9,0) -> 12534 | X9: =IF(OR(ISNUMBER(SEARCH("live nation",L9)),ISNUMBER(SEARCH("ocesa",L9))),1,0) -> 0 | Y9: Asia / home markets
A10: 46147 | B10: 1 | C10: SIXFONIA | E10: K-Arena Yokohama | F10: Yokohama | H10: Japan | J10: Arena | K10: Yen | L10: Sogo Tokyo Corporation | M10: Asian Pop | N10: 12534 | O10: 717282.53 | P10: 12534 | Q10: 1 | R10: 57.23 | S10: 57.23 | T10: 57.23 | U10: =IFERROR(YEAR(A10),"") -> 2026 | V10: =IFERROR(O10*B10,0) -> 717282.53 | W10: =IFERROR(N10*B10,0) -> 12534 | X10: =IF(OR(ISNUMBER(SEARCH("live nation",L10)),ISNUMBER(SEARCH("ocesa",L10))),1,0) -> 0 | Y10: Asia / home markets
A11: 46145 | B11: 1 | C11: HoYoFair Fan Concert | E11: Beacon Theatre | F11: New York | G11: New York | H11: United States | I11: New York | J11: Auditorium / Theatre | K11: US DOLLAR | L11: Mammoth | M11: Asian Pop | N11: 1899 | O11: 174121.1 | P11: 2744 | Q11: 0.69 | R11: 67 | S11: 147 | T11: 91.69 | U11: =IFERROR(YEAR(A11),"") -> 2026 | V11: =IFERROR(O11*B11,0) -> 174121.1 | W11: =IFERROR(N11*B11,0) -> 1899 | X11: =IF(OR(ISNUMBER(SEARCH("live nation",L11)),ISNUMBER(SEARCH("ocesa",L11))),1,0) -> 0 | Y11: Americas + Europe + ANZ
A12: 46144 | B12: 2 | C12: BTS | E12: Sun Bowl Stadium | F12: El Paso | G12: Texas | H12: United States | I12: El Paso (Las Cruces) | J12: Stadium | K12: US DOLLAR | L12: HYBE Co. Ltd. | M12: Asian Pop | N12: 48861 | O12: 10009328 | P12: 49115 | Q12: 0.99 | R12: 69.5 | S12: 649.5 | T12: 204.85 | U12: =IFERROR(YEAR(A12),"") -> 2026 | V12: =IFERROR(O12*B12,0) -> 20018656 | W12: =IFERROR(N12*B12,0) -> 97722 | X12: =IF(OR(ISNUMBER(SEARCH("live nation",L12)),ISNUMBER(SEARCH("ocesa",L12))),1,0) -> 0 | Y12: Americas + Europe + ANZ
A13: 46143 | B13: 3 | C13: ENHYPEN | E13: KSPO Dome | F13: Seoul | H13: South Korea | J13: Arena | K13: Won | L13: HYBE Co. Ltd. | M13: Asian Pop | N13: 10404 | O13: 1216289.5 | P13: 10511 | Q13: 0.98 | R13: 111.89 | S13: 171.56 | T13: 116.9 | U13: =IFERROR(YEAR(A13),"") -> 2026 | V13: =IFERROR(O13*B13,0) -> 3648868.6 | W13: =IFERROR(N13*B13,0) -> 31212 | X13: =IF(OR(ISNUMBER(SEARCH("live nation",L13)),ISNUMBER(SEARCH("ocesa",L13))),1,0) -> 0 | Y13: Asia / home markets
A14: 46141 | B14: 1 | C14: XLOV | E14: Pepsi Center Mexico | F14: Mexico City | H14: Mexico | J14: Auditorium / Theatre, Convention Center | K14: Pesos | L14: Ninshi | M14: Asian Pop | N14: 2266 | O14: 704439.31 | P14: 6486 | Q14: 0.34 | R14: 56.91 | S14: 344.35 | T14: 310.87 | U14: =IFERROR(YEAR(A14),"") -> 2026 | V14: =IFERROR(O14*B14,0) -> 704439.31 | W14: =IFERROR(N14*B14,0) -> 2266 | X14: =IF(OR(ISNUMBER(SEARCH("live nation",L14)),ISNUMBER(SEARCH("ocesa",L14))),1,0) -> 0 | Y14: Americas + Europe + ANZ
A15: 46140 | B15: 1 | C15: Jackson Wang | D15: Karen Paola | E15: Movistar Arena | F15: Santiago | H15: Chile | J15: Arena | K15: Peso | L15: DG Medios, Live Nation | M15: Asian Pop | N15: 7487 | O15: 533889.76 | P15: 11453 | Q15: 0.65 | R15: 44.69 | S15: 117.32 | T15: 71.31 | U15: =IFERROR(YEAR(A15),"") -> 2026 | V15: =IFERROR(O15*B15,0) -> 533889.76 | W15: =IFERROR(N15*B15,0) -> 7487 | X15: =IF(OR(ISNUMBER(SEARCH("live nation",L15)),ISNUMBER(SEARCH("ocesa",L15))),1,0) -> 1 | Y15: Americas + Europe + ANZ
A16: 46140 | B16: 1 | C16: "Forever K-Pop" | E16: State Theatre | F16: Minneapolis | G16: Minnesota | H16: United States | I16: Minneapolis-St. Paul | J16: Auditorium / Theatre | K16: US DOLLAR | L16: (In-House Promotion), Hennepin Arts | M16: Asian Pop, Tribute Acts | N16: 684 | O16: 27666.6 | P16: 1831 | Q16: 0.37 | R16: 27.5 | S16: 65 | T16: 40.45 | U16: =IFERROR(YEAR(A16),"") -> 2026 | V16: =IFERROR(O16*B16,0) -> 27666.6 | W16: =IFERROR(N16*B16,0) -> 684 | X16: =IF(OR(ISNUMBER(SEARCH("live nation",L16)),ISNUMBER(SEARCH("ocesa",L16))),1,0) -> 0 | Y16: Americas + Europe + ANZ
A17: 46137 | B17: 3 | C17: BTS | E17: Raymond James Stadium | F17: Tampa | G17: Florida | H17: United States | I17: Tampa-St. Petersburg (Sarasota) | J17: Stadium | K17: US DOLLAR | L17: HYBE Co. Ltd. | M17: Asian Pop | N17: 64778 | O17: 13578814 | P17: 64857 | Q17: 0.99 | R17: 69.5 | S17: 649.5 | T17: 209.62 | U17: =IFERROR(YEAR(A17),"") -> 2026 | V17: =IFERROR(O17*B17,0) -> 40736443 | W17: =IFERROR(N17*B17,0) -> 194334 | X17: =IF(OR(ISNUMBER(SEARCH("live nation",L17)),ISNUMBER(SEARCH("ocesa",L17))),1,0) -> 0 | Y17: Americas + Europe + ANZ
A18: 46137 | B18: 1 | C18: "K-Pop Forever" | E18: Unipol Forum | F18: Assago | H18: Italy | J18: Arena | K18: Euro | L18: Vivo Concerti | M18: Asian Pop, Tribute Acts | N18: 9951 | O18: 637578.12 | P18: 10062 | Q18: 0.98 | R18: 40.44 | S18: 107.84 | T18: 64.07 | U18: =IFERROR(YEAR(A18),"") -> 2026 | V18: =IFERROR(O18*B18,0) -> 637578.12 | W18: =IFERROR(N18*B18,0) -> 9951 | X18: =IF(OR(ISNUMBER(SEARCH("live nation",L18)),ISNUMBER(SEARCH("ocesa",L18))),1,0) -> 0 | Y18: Americas + Europe + ANZ
A19: 46130 | B19: 1 | C19: TWICE | E19: Moody Center | F19: Austin | G19: Texas | H19: United States | I19: Austin | J19: Arena | K19: US DOLLAR | L19: Live Nation | M19: Asian Pop | N19: 12997 | O19: 1682909.5 | P19: 12997 | Q19: 1 | R19: 33.5 | S19: 223.5 | T19: 129.48 | U19: =IFERROR(YEAR(A19),"") -> 2026 | V19: =IFERROR(O19*B19,0) -> 1682909.5 | W19: =IFERROR(N19*B19,0) -> 12997 | X19: =IF(OR(ISNUMBER(SEARCH("live nation",L19)),ISNUMBER(SEARCH("ocesa",L19))),1,0) -> 1 | Y19: Americas + Europe + ANZ
A20: 46130 | B20: 1 | C20: "Forever K-Pop" | E20: Embassy Theatre | F20: Fort Wayne | G20: Indiana | H20: United States | I20: Fort Wayne | J20: Auditorium / Theatre | K20: US DOLLAR | L20: (In-House Promotion) | M20: Asian Pop, Tribute Acts | N20: 1307 | O20: 70599 | P20: 1767 | Q20: 0.73 | R20: 37 | S20: 77 | T20: 54.02 | U20: =IFERROR(YEAR(A20),"") -> 2026 | V20: =IFERROR(O20*B20,0) -> 70599 | W20: =IFERROR(N20*B20,0) -> 1307 | X20: =IF(OR(ISNUMBER(SEARCH("live nation",L20)),ISNUMBER(SEARCH("ocesa",L20))),1,0) -> 0 | Y20: Americas + Europe + ANZ
A21: 46130 | B21: 1 | C21: TV Anime 'Detective Conan' 30th Anniversary Special Concert 2026 | D21: Mai Kuraki | E21: K-Arena Yokohama | F21: Yokohama | H21: Japan | J21: Arena | K21: Yen | L21: Kyodo Tokyo | M21: Asian Pop | N21: 10000 | O21: 441236.71 | P21: 10000 | Q21: 1 | R21: 44.12 | S21: 44.12 | T21: 44.12 | U21: =IFERROR(YEAR(A21),"") -> 2026 | V21: =IFERROR(O21*B21,0) -> 441236.71 | W21: =IFERROR(N21*B21,0) -> 10000 | X21: =IF(OR(ISNUMBER(SEARCH("live nation",L21)),ISNUMBER(SEARCH("ocesa",L21))),1,0) -> 0 | Y21: Asia / home markets
A22: 46129 | B22: 2 | C22: BTS | E22: Tokyo Dome | F22: Tokyo | H22: Japan | J22: Stadium | K22: Yen | L22: HYBE Co. Ltd. | M22: Asian Pop | N22: 48089 | O22: 9278360 | P22: 47589 | Q22: 1.01 | R22: 156.85 | S22: 282.33 | T22: 192.94 | U22: =IFERROR(YEAR(A22),"") -> 2026 | V22: =IFERROR(O22*B22,0) -> 18556720 | W22: =IFERROR(N22*B22,0) -> 96178 | X22: =IF(OR(ISNUMBER(SEARCH("live nation",L22)),ISNUMBER(SEARCH("ocesa",L22))),1,0) -> 0 | Y22: Asia / home markets
A23: 46129 | B23: 1 | C23: TWICE | E23: Moody Center | F23: Austin | G23: Texas | H23: United States | I23: Austin | J23: Arena | K23: US DOLLAR | L23: Live Nation | M23: Asian Pop | N23: 13362 | O23: 2146167 | P23: 13362 | Q23: 1 | R23: 33.5 | S23: 223.5 | T23: 160.62 | U23: =IFERROR(YEAR(A23),"") -> 2026 | V23: =IFERROR(O23*B23,0) -> 2146167 | W23: =IFERROR(N23*B23,0) -> 13362 | X23: =IF(OR(ISNUMBER(SEARCH("live nation",L23)),ISNUMBER(SEARCH("ocesa",L23))),1,0) -> 1 | Y23: Americas + Europe + ANZ
A24: 46129 | B24: 1 | C24: TV Anime 'Detective Conan' 30th Anniversary Special Concert 2026 | D24: Mai Kuraki | E24: K-Arena Yokohama | F24: Yokohama | H24: Japan | J24: Arena | K24: Yen | L24: Kyodo Tokyo | M24: Asian Pop | N24: 10000 | O24: 439181.26 | P24: 10000 | Q24: 1 | R24: 43.92 | S24: 43.92 | T24: 43.92 | U24: =IFERROR(YEAR(A24),"") -> 2026 | V24: =IFERROR(O24*B24,0) -> 439181.26 | W24: =IFERROR(N24*B24,0) -> 10000 | X24: =IF(OR(ISNUMBER(SEARCH("live nation",L24)),ISNUMBER(SEARCH("ocesa",L24))),1,0) -> 0 | Y24: Asia / home markets
A25: 46128 | B25: 1 | C25: Big Ocean | E25: Union Stage | F25: Washington | G25: District of Columbia | H25: United States | I25: Washington, D.C. (Hagerstown) | J25: Club | K25: US DOLLAR | L25: Union Stage Presents | M25: Asian Pop | N25: 359 | O25: 34975 | P25: 500 | Q25: 0.71 | R25: 40 | S25: 240 | T25: 97.42 | U25: =IFERROR(YEAR(A25),"") -> 2026 | V25: =IFERROR(O25*B25,0) -> 34975 | W25: =IFERROR(N25*B25,0) -> 359 | X25: =IF(OR(ISNUMBER(SEARCH("live nation",L25)),ISNUMBER(SEARCH("ocesa",L25))),1,0) -> 0 | Y25: Americas + Europe + ANZ
A26: 46124 | B26: 1 | C26: "The Performance" | D26: aoen, ALPHA DRIVE ONE, ATEEZ, NCT WISH, Xikers, The Jet Boy Bangerz, Hearts2Hearts, MYERA | E26: K-Arena Yokohama | F26: Yokohama | H26: Japan | J26: Arena | K26: Yen | L26: PIA Corporation | M26: Asian Pop | N26: 18951 | O26: 1666073.7 | P26: 18951 | Q26: 1 | R26: 87.91 | S26: 87.91 | T26: 87.91 | U26: =IFERROR(YEAR(A26),"") -> 2026 | V26: =IFERROR(O26*B26,0) -> 1666073.7 | W26: =IFERROR(N26*B26,0) -> 18951 | X26: =IF(OR(ISNUMBER(SEARCH("live nation",L26)),ISNUMBER(SEARCH("ocesa",L26))),1,0) -> 0 | Y26: Asia / home markets
A27: 46123 | B27: 1 | C27: "The Performance" | D27: EVNNE, ATEEZ, Verivery, Mazzel, RIIZE, ROIROM | E27: K-Arena Yokohama | F27: Yokohama | H27: Japan | J27: Arena | K27: Yen | L27: PIA Corporation | M27: Asian Pop | N27: 18951 | O27: 1665760.6 | P27: 18951 | Q27: 1 | R27: 87.9 | S27: 87.9 | T27: 87.9 | U27: =IFERROR(YEAR(A27),"") -> 2026 | V27: =IFERROR(O27*B27,0) -> 1665760.6 | W27: =IFERROR(N27*B27,0) -> 18951 | X27: =IF(OR(ISNUMBER(SEARCH("live nation",L27)),ISNUMBER(SEARCH("ocesa",L27))),1,0) -> 0 | Y27: Asia / home markets
A28: 46122 | B28: 1 | C28: Jackson Wang | E28: Barclays Center | F28: Brooklyn | G28: New York | H28: United States | I28: New York | J28: Arena | K28: US DOLLAR | L28: Live Nation | M28: Asian Pop | N28: 10344 | O28: 1481898 | P28: 10344 | Q28: 1 | R28: 22.45 | S28: 193.5 | T28: 143.26 | U28: =IFERROR(YEAR(A28),"") -> 2026 | V28: =IFERROR(O28*B28,0) -> 1481898 | W28: =IFERROR(N28*B28,0) -> 10344 | X28: =IF(OR(ISNUMBER(SEARCH("live nation",L28)),ISNUMBER(SEARCH("ocesa",L28))),1,0) -> 1 | Y28: Americas + Europe + ANZ
A29: 46122 | B29: 1 | C29: "The Performance" | D29: RIIZE, The Rampage | E29: K-Arena Yokohama | F29: Yokohama | H29: Japan | J29: Arena | K29: Yen | L29: PIA Corporation | M29: Asian Pop | N29: 12380 | O29: 1011311.9 | P29: 12380 | Q29: 1 | R29: 81.69 | S29: 81.69 | T29: 81.69 | U29: =IFERROR(YEAR(A29),"") -> 2026 | V29: =IFERROR(O29*B29,0) -> 1011311.9 | W29: =IFERROR(N29*B29,0) -> 12380 | X29: =IF(OR(ISNUMBER(SEARCH("live nation",L29)),ISNUMBER(SEARCH("ocesa",L29))),1,0) -> 0 | Y29: Asia / home markets
A30: 46121 | B30: 1 | C30: Nmixx | E30: YouTube Theater | F30: Inglewood | G30: California | H30: United States | I30: Los Angeles | J30: Auditorium / Theatre | K30: US DOLLAR | L30: Live Nation | M30: Asian Pop | N30: 5731 | O30: 580042.5 | P30: 5737 | Q30: 0.99 | R30: 69.5 | S30: 159.5 | T30: 101.21 | U30: =IFERROR(YEAR(A30),"") -> 2026 | V30: =IFERROR(O30*B30,0) -> 580042.5 | W30: =IFERROR(N30*B30,0) -> 5731 | X30: =IF(OR(ISNUMBER(SEARCH("live nation",L30)),ISNUMBER(SEARCH("ocesa",L30))),1,0) -> 1 | Y30: Americas + Europe + ANZ
A31: 46121 | B31: 3 | C31: BTS | E31: Goyang Stadium | F31: Goyang | H31: South Korea | J31: Stadium | K31: Won | L31: HYBE Co. Ltd. | M31: Asian Pop | N31: 42406 | O31: 5628730.8 | P31: 42528 | Q31: 0.99 | R31: 133.59 | S31: 178.13 | T31: 132.73 | U31: =IFERROR(YEAR(A31),"") -> 2026 | V31: =IFERROR(O31*B31,0) -> 16886193 | W31: =IFERROR(N31*B31,0) -> 127218 | X31: =IF(OR(ISNUMBER(SEARCH("live nation",L31)),ISNUMBER(SEARCH("ocesa",L31))),1,0) -> 0 | Y31: Asia / home markets
A32: 46120 | B32: 1 | C32: Jackson Wang | E32: Allstate Arena | F32: Rosemont | G32: Illinois | H32: United States | I32: Chicago | J32: Arena | K32: US DOLLAR | L32: Live Nation | M32: Asian Pop | N32: 5059 | O32: 633336 | P32: 5059 | Q32: 1 | R32: 59.5 | S32: 199.5 | T32: 125.19 | U32: =IFERROR(YEAR(A32),"") -> 2026 | V32: =IFERROR(O32*B32,0) -> 633336 | W32: =IFERROR(N32*B32,0) -> 5059 | X32: =IF(OR(ISNUMBER(SEARCH("live nation",L32)),ISNUMBER(SEARCH("ocesa",L32))),1,0) -> 1 | Y32: Americas + Europe + ANZ
A33: 46120 | B33: 1 | C33: Naniwa Danshi | E33: K-Arena Yokohama | F33: Yokohama | H33: Japan | J33: Arena | K33: Yen | L33: PIA Corporation | M33: Asian Pop | N33: 18951 | O33: 1315683.6 | P33: 18951 | Q33: 1 | R33: 69.43 | S33: 69.43 | T33: 69.43 | U33: =IFERROR(YEAR(A33),"") -> 2026 | V33: =IFERROR(O33*B33,0) -> 1315683.6 | W33: =IFERROR(N33*B33,0) -> 18951 | X33: =IF(OR(ISNUMBER(SEARCH("live nation",L33)),ISNUMBER(SEARCH("ocesa",L33))),1,0) -> 0 | Y33: Asia / home markets
A34: 46119 | B34: 1 | C34: Naniwa Danshi | E34: K-Arena Yokohama | F34: Yokohama | H34: Japan | J34: Arena | K34: Yen | L34: PIA Corporation | M34: Asian Pop | N34: 18951 | O34: 1304250.7 | P34: 18951 | Q34: 1 | R34: 68.82 | S34: 68.82 | T34: 68.82 | U34: =IFERROR(YEAR(A34),"") -> 2026 | V34: =IFERROR(O34*B34,0) -> 1304250.7 | W34: =IFERROR(N34*B34,0) -> 18951 | X34: =IF(OR(ISNUMBER(SEARCH("live nation",L34)),ISNUMBER(SEARCH("ocesa",L34))),1,0) -> 0 | Y34: Asia / home markets
A35: 46117 | B35: 1 | C35: "Central Music & Entertainment Festival" | D35: Chanmina, HANA, Yuuri, Murasaki Ima | E35: K-Arena Yokohama | F35: Yokohama | H35: Japan | J35: Arena | K35: Yen | L35: Sony Music Solutions | M35: Asian Pop | N35: 18123 | O35: 1362170.7 | P35: 18123 | Q35: 1 | R35: 75.16 | S35: 75.16 | T35: 75.16 | U35: =IFERROR(YEAR(A35),"") -> 2026 | V35: =IFERROR(O35*B35,0) -> 1362170.7 | W35: =IFERROR(N35*B35,0) -> 18123 | X35: =IF(OR(ISNUMBER(SEARCH("live nation",L35)),ISNUMBER(SEARCH("ocesa",L35))),1,0) -> 0 | Y35: Asia / home markets
A36: 46116 | B36: 1 | C36: "Central Music & Entertainment Festival" | D36: Amazarashi, Orange Range, Kessoku Band, Ling tosite sigure, Ling tosite sigure | E36: K-Arena Yokohama | F36: Yokohama | H36: Japan | J36: Arena | K36: Yen | L36: Sony Music Solutions | M36: Asian Pop | N36: 11544 | O36: 867676.33 | P36: 11544 | Q36: 1 | R36: 75.16 | S36: 75.16 | T36: 75.16 | U36: =IFERROR(YEAR(A36),"") -> 2026 | V36: =IFERROR(O36*B36,0) -> 867676.33 | W36: =IFERROR(N36*B36,0) -> 11544 | X36: =IF(OR(ISNUMBER(SEARCH("live nation",L36)),ISNUMBER(SEARCH("ocesa",L36))),1,0) -> 0 | Y36: Asia / home markets
A37: 46116 | B37: 2 | C37: SEVENTEEN | E37: Incheon Asiad Main Stadium | F37: Incheon | H37: South Korea | J37: Stadium | K37: Won | L37: HYBE Co. Ltd. | M37: Asian Pop | N37: 22650 | O37: 2155433.3 | P37: 25905 | Q37: 0.87 | R37: 131.11 | S37: 87.4 | T37: 95.16 | U37: =IFERROR(YEAR(A37),"") -> 2026 | V37: =IFERROR(O37*B37,0) -> 4310866.5 | W37: =IFERROR(N37*B37,0) -> 45300 | X37: =IF(OR(ISNUMBER(SEARCH("live nation",L37)),ISNUMBER(SEARCH("ocesa",L37))),1,0) -> 0 | Y37: Asia / home markets
A38: 46116 | B38: 1 | C38: "K-Pop Forever" | E38: Unipol Arena | F38: Bologna | H38: Italy | J38: Arena | K38: Euro | L38: Vivo Concerti | M38: Asian Pop, Tribute Acts | N38: 5493 | O38: 363359.13 | P38: 9193 | Q38: 0.59 | R38: 39.75 | S38: 108.64 | T38: 66.15 | U38: =IFERROR(YEAR(A38),"") -> 2026 | V38: =IFERROR(O38*B38,0) -> 363359.13 | W38: =IFERROR(N38*B38,0) -> 5493 | X38: =IF(OR(ISNUMBER(SEARCH("live nation",L38)),ISNUMBER(SEARCH("ocesa",L38))),1,0) -> 0 | Y38: Americas + Europe + ANZ
A39: 46115 | B39: 1 | C39: "Forever K-Pop" | E39: Mayo Performing Arts Center | F39: Morristown | G39: New Jersey | H39: United States | I39: New York | J39: Auditorium / Theatre | K39: US DOLLAR | L39: (In-House Promotion) | M39: Asian Pop, Tribute Acts | N39: 749 | O39: 43975.3 | P39: 1222 | Q39: 0.61 | R39: 35 | S39: 75 | T39: 58.71 | U39: =IFERROR(YEAR(A39),"") -> 2026 | V39: =IFERROR(O39*B39,0) -> 43975.3 | W39: =IFERROR(N39*B39,0) -> 749 | X39: =IF(OR(ISNUMBER(SEARCH("live nation",L39)),ISNUMBER(SEARCH("ocesa",L39))),1,0) -> 0 | Y39: Americas + Europe + ANZ
A40: 46115 | B40: 2 | C40: TWICE | E40: TD Garden | F40: Boston | G40: Massachusetts | H40: United States | I40: Boston (Manchester) | J40: Arena | K40: US DOLLAR | L40: Live Nation | M40: Asian Pop | N40: 14655 | O40: 2002366.5 | P40: 15248 | Q40: 0.96 | R40: 52.5 | S40: 222.5 | T40: 136.63 | U40: =IFERROR(YEAR(A40),"") -> 2026 | V40: =IFERROR(O40*B40,0) -> 4004733 | W40: =IFERROR(N40*B40,0) -> 29310 | X40: =IF(OR(ISNUMBER(SEARCH("live nation",L40)),ISNUMBER(SEARCH("ocesa",L40))),1,0) -> 1 | Y40: Americas + Europe + ANZ
A41: 46115 | B41: 1 | C41: "Central Music & Entertainment Festival" | D41: =LOVE, Nogizaka46, FRUITS ZIPPER, Morning Musume | E41: K-Arena Yokohama | F41: Yokohama | H41: Japan | J41: Arena | K41: Yen | L41: Sony Music Solutions | M41: Asian Pop | N41: 18123 | O41: 1362790.1 | P41: 18123 | Q41: 1 | R41: 75.2 | S41: 75.2 | T41: 75.2 | U41: =IFERROR(YEAR(A41),"") -> 2026 | V41: =IFERROR(O41*B41,0) -> 1362790.1 | W41: =IFERROR(N41*B41,0) -> 18123 | X41: =IF(OR(ISNUMBER(SEARCH("live nation",L41)),ISNUMBER(SEARCH("ocesa",L41))),1,0) -> 0 | Y41: Asia / home markets
A42: 46115 | B42: 1 | C42: "K-Pop Forever" | E42: Unipol Forum | F42: Assago | H42: Italy | J42: Arena | K42: Euro | L42: Vivo Concerti | M42: Asian Pop, Tribute Acts | N42: 9144 | O42: 572201.29 | P42: 10062 | Q42: 0.9 | R42: 39.8 | S42: 106.13 | T42: 62.58 | U42: =IFERROR(YEAR(A42),"") -> 2026 | V42: =IFERROR(O42*B42,0) -> 572201.29 | W42: =IFERROR(N42*B42,0) -> 9144 | X42: =IF(OR(ISNUMBER(SEARCH("live nation",L42)),ISNUMBER(SEARCH("ocesa",L42))),1,0) -> 0 | Y42: Americas + Europe + ANZ
A43: 46114 | B43: 1 | C43: Nmixx | E43: The Theater at MGM National Harbor | F43: Oxon Hill | G43: Maryland | H43: United States | I43: Washington, D.C. (Hagerstown) | J43: Auditorium / Theatre | K43: US DOLLAR | L43: Live Nation | M43: Asian Pop | N43: 2792 | O43: 322444 | P43: 2900 | Q43: 0.96 | R43: 69.5 | S43: 159.5 | T43: 115.49 | U43: =IFERROR(YEAR(A43),"") -> 2026 | V43: =IFERROR(O43*B43,0) -> 322444 | W43: =IFERROR(N43*B43,0) -> 2792 | X43: =IF(OR(ISNUMBER(SEARCH("live nation",L43)),ISNUMBER(SEARCH("ocesa",L43))),1,0) -> 1 | Y43: Americas + Europe + ANZ
A44: 46114 | B44: 1 | C44: Jackson Wang | E44: Oakland Arena | F44: Oakland | G44: California | H44: United States | I44: San Francisco-Oakland-San Jose | J44: Arena | K44: US DOLLAR | L44: Live Nation | M44: Asian Pop | N44: 7077 | O44: 730517 | P44: 7077 | Q44: 1 | R44: 19.7 | S44: 190 | T44: 103.22 | U44: =IFERROR(YEAR(A44),"") -> 2026 | V44: =IFERROR(O44*B44,0) -> 730517 | W44: =IFERROR(N44*B44,0) -> 7077 | X44: =IF(OR(ISNUMBER(SEARCH("live nation",L44)),ISNUMBER(SEARCH("ocesa",L44))),1,0) -> 1 | Y44: Americas + Europe + ANZ
A45: 46112 | B45: 1 | C45: TWICE | E45: Spectrum Center | F45: Charlotte | G45: North Carolina | H45: United States | I45: Charlotte | J45: Arena | K45: US DOLLAR | L45: Live Nation | M45: Asian Pop | N45: 16500 | O45: 2194530 | P45: 16500 | Q45: 1 | R45: 133 | S45: 133 | T45: 133 | U45: =IFERROR(YEAR(A45),"") -> 2026 | V45: =IFERROR(O45*B45,0) -> 2194530 | W45: =IFERROR(N45*B45,0) -> 16500 | X45: =IF(OR(ISNUMBER(SEARCH("live nation",L45)),ISNUMBER(SEARCH("ocesa",L45))),1,0) -> 1 | Y45: Americas + Europe + ANZ
A46: 46112 | B46: 1 | C46: "Forever K-Pop" | E46: Marcus Performing Arts Center | F46: Milwaukee | G46: Wisconsin | H46: United States | I46: Milwaukee | J46: Complex | K46: US DOLLAR | L46: Marcus Performing Arts Center | M46: Asian Pop, Tribute Acts | N46: 668 | O46: 36182.89 | P46: 2043 | Q46: 0.32 | R46: 20 | S46: 85 | T46: 54.17 | U46: =IFERROR(YEAR(A46),"") -> 2026 | V46: =IFERROR(O46*B46,0) -> 36182.89 | W46: =IFERROR(N46*B46,0) -> 668 | X46: =IF(OR(ISNUMBER(SEARCH("live nation",L46)),ISNUMBER(SEARCH("ocesa",L46))),1,0) -> 0 | Y46: Americas + Europe + ANZ
A47: 46110 | B47: 1 | C47: "Forever K-Pop" | E47: Midland Center for the Arts | F47: Midland | G47: Michigan | H47: United States | I47: Flint-Saginaw-Bay City | J47: Auditorium / Theatre | K47: US DOLLAR | L47: (In-House Promotion) | M47: Asian Pop, Tribute Acts | N47: 1379 | O47: 78725 | P47: 1430 | Q47: 0.96 | R47: 35 | S47: 95 | T47: 57.09 | U47: =IFERROR(YEAR(A47),"") -> 2026 | V47: =IFERROR(O47*B47,0) -> 78725 | W47: =IFERROR(N47*B47,0) -> 1379 | X47: =IF(OR(ISNUMBER(SEARCH("live nation",L47)),ISNUMBER(SEARCH("ocesa",L47))),1,0) -> 0 | Y47: Americas + Europe + ANZ
A48: 46110 | B48: 1 | C48: "GOLDEN: A K-Pop Party!" | E48: The Intersection / Elevation | F48: Grand Rapids | G48: Michigan | H48: United States | I48: Grand Rapids-Kalamazoo-Battle Creek | J48: Club | K48: US DOLLAR | L48: (In-House Promotion) | M48: Asian Pop, Dance / Electronic | N48: 600 | O48: 11750 | P48: 600 | Q48: 1 | R48: 15 | S48: 25 | T48: 19.58 | U48: =IFERROR(YEAR(A48),"") -> 2026 | V48: =IFERROR(O48*B48,0) -> 11750 | W48: =IFERROR(N48*B48,0) -> 600 | X48: =IF(OR(ISNUMBER(SEARCH("live nation",L48)),ISNUMBER(SEARCH("ocesa",L48))),1,0) -> 0 | Y48: Americas + Europe + ANZ
A49: 46110 | B49: 1 | C49: "GOLDEN: A K-Pop Party!" | E49: The Intersection / Elevation | F49: Grand Rapids | G49: Michigan | H49: United States | I49: Grand Rapids-Kalamazoo-Battle Creek | J49: Club | K49: US DOLLAR | L49: (In-House Promotion) | M49: Asian Pop, Dance / Electronic | N49: 600 | O49: 11750 | P49: 600 | Q49: 1 | R49: 15 | S49: 25 | T49: 19.58 | U49: =IFERROR(YEAR(A49),"") -> 2026 | V49: =IFERROR(O49*B49,0) -> 11750 | W49: =IFERROR(N49*B49,0) -> 600 | X49: =IF(OR(ISNUMBER(SEARCH("live nation",L49)),ISNUMBER(SEARCH("ocesa",L49))),1,0) -> 0 | Y49: Americas + Europe + ANZ
A50: 46110 | B50: 1 | C50: Jay Park, LNGSHOT, BIBI, Milli, AI, Kvi Baba | E50: Makuhari Messe | F50: Chiba | H50: Japan | J50: Complex | K50: Yen | L50: Creativeman Productions Co. | M50: Asian Pop, World | N50: 2102 | O50: 275393.5 | P50: 15000 | Q50: 0.14 | R50: 99.82 | S50: 162.21 | T50: 131.01 | U50: =IFERROR(YEAR(A50),"") -> 2026 | V50: =IFERROR(O50*B50,0) -> 275393.5 | W50: =IFERROR(N50*B50,0) -> 2102 | X50: =IF(OR(ISNUMBER(SEARCH("live nation",L50)),ISNUMBER(SEARCH("ocesa",L50))),1,0) -> 0 | Y50: Asia / home markets
A51: 46110 | B51: 1 | C51: "STPR Family Festival!!" | D51: Knight X, AMPTAKxCOLORS, Meteorites, SneakerStep Prod.STPR MUSIC | E51: K-Arena Yokohama | F51: Yokohama | H51: Japan | J51: Arena | K51: Yen | L51: Avex Live Creative Inc. | M51: Asian Pop | N51: 18274 | O51: 1128679.1 | P51: 18274 | Q51: 1 | R51: 61.76 | S51: 61.76 | T51: 61.76 | U51: =IFERROR(YEAR(A51),"") -> 2026 | V51: =IFERROR(O51*B51,0) -> 1128679.1 | W51: =IFERROR(N51*B51,0) -> 18274 | X51: =IF(OR(ISNUMBER(SEARCH("live nation",L51)),ISNUMBER(SEARCH("ocesa",L51))),1,0) -> 0 | Y51: Asia / home markets
A52: 46110 | B52: 1 | C52: "GOLDEN: A K-Pop Party!" | E52: The Orange Peel | F52: Asheville | G52: North Carolina | H52: United States | I52: Charlotte | J52: Club | K52: US DOLLAR | L52: (In-House Promotion) | M52: Asian Pop, Dance / Electronic | N52: 600 | O52: 10750 | P52: 750 | Q52: 0.8 | R52: 20 | S52: 25 | T52: 17.92 | U52: =IFERROR(YEAR(A52),"") -> 2026 | V52: =IFERROR(O52*B52,0) -> 10750 | W52: =IFERROR(N52*B52,0) -> 600 | X52: =IF(OR(ISNUMBER(SEARCH("live nation",L52)),ISNUMBER(SEARCH("ocesa",L52))),1,0) -> 0 | Y52: Americas + Europe + ANZ
A53: 46109 | B53: 1 | C53: "STPR Family Festival!!" | D53: Strawberry Prince, Knight X, AMPTAKxCOLORS, Meteorites, SneakerStep Prod.STPR MUSIC | E53: K-Arena Yokohama | F53: Yokohama | H53: Japan | J53: Arena | K53: Yen | L53: Avex Live Creative Inc. | M53: Asian Pop | N53: 18274 | O53: 1128594.7 | P53: 18274 | Q53: 1 | R53: 61.76 | S53: 61.76 | T53: 61.76 | U53: =IFERROR(YEAR(A53),"") -> 2026 | V53: =IFERROR(O53*B53,0) -> 1128594.7 | W53: =IFERROR(N53*B53,0) -> 18274 | X53: =IF(OR(ISNUMBER(SEARCH("live nation",L53)),ISNUMBER(SEARCH("ocesa",L53))),1,0) -> 0 | Y53: Asia / home markets
A54: 46108 | B54: 1 | C54: "CLUB K-POP" | E54: Union Stage | F54: Washington | G54: District of Columbia | H54: United States | I54: Washington, D.C. (Hagerstown) | J54: Club | K54: US DOLLAR | L54: Pauz Presents, Union Stage Presents | M54: Asian Pop, Dance / Electronic | N54: 299 | O54: 6225 | P54: 500 | Q54: 0.59 | R54: 15 | S54: 25 | T54: 20.82 | U54: =IFERROR(YEAR(A54),"") -> 2026 | V54: =IFERROR(O54*B54,0) -> 6225 | W54: =IFERROR(N54*B54,0) -> 299 | X54: =IF(OR(ISNUMBER(SEARCH("live nation",L54)),ISNUMBER(SEARCH("ocesa",L54))),1,0) -> 0 | Y54: Americas + Europe + ANZ
A55: 46108 | B55: 1 | C55: "K-Pop Night" | E55: 191 Toole | F55: Tucson | G55: Arizona | H55: United States | I55: Tucson (Sierra Vista) | J55: Club | K55: US DOLLAR | L55: Gate 52, Rialto Theatre | M55: Asian Pop | N55: 139 | O55: 2361 | P55: 500 | Q55: 0.27 | R55: 15 | S55: 21 | T55: 16.99 | U55: =IFERROR(YEAR(A55),"") -> 2026 | V55: =IFERROR(O55*B55,0) -> 2361 | W55: =IFERROR(N55*B55,0) -> 139 | X55: =IF(OR(ISNUMBER(SEARCH("live nation",L55)),ISNUMBER(SEARCH("ocesa",L55))),1,0) -> 0 | Y55: Americas + Europe + ANZ
A56: 46106 | B56: 1 | C56: "Forever K-Pop" | E56: Bloomington Center for the Perf. Arts | F56: Bloomington | G56: Illinois | H56: United States | I56: Peoria-Bloomington | J56: Auditorium / Theatre | K56: US DOLLAR | L56: (In-House Promotion) | M56: Asian Pop, Tribute Acts | N56: 883 | O56: 32826 | P56: 1166 | Q56: 0.75 | R56: 26 | S56: 86 | T56: 37.18 | U56: =IFERROR(YEAR(A56),"") -> 2026 | V56: =IFERROR(O56*B56,0) -> 32826 | W56: =IFERROR(N56*B56,0) -> 883 | X56: =IF(OR(ISNUMBER(SEARCH("live nation",L56)),ISNUMBER(SEARCH("ocesa",L56))),1,0) -> 0 | Y56: Americas + Europe + ANZ
A57: 46106 | B57: 2 | C57: Chanmina | E57: Ariake Arena | F57: Tokyo | H57: Japan | J57: Arena | K57: Yen | L57: Creativeman Productions Co. | M57: Asian Pop, Rap / HipHop | N57: 15000 | O57: 1142914.9 | P57: 15000 | Q57: 1 | R57: 76.19 | S57: 76.19 | T57: 76.19 | U57: =IFERROR(YEAR(A57),"") -> 2026 | V57: =IFERROR(O57*B57,0) -> 2285829.8 | W57: =IFERROR(N57*B57,0) -> 30000 | X57: =IF(OR(ISNUMBER(SEARCH("live nation",L57)),ISNUMBER(SEARCH("ocesa",L57))),1,0) -> 0 | Y57: Asia / home markets
A58: 46104 | B58: 1 | C58: Meteorites | E58: K-Arena Yokohama | F58: Yokohama | H58: Japan | J58: Arena | K58: Yen | L58: Avex Live Creative Inc. | M58: Asian Pop | N58: 8563 | O58: 472568.04 | P58: 8563 | Q58: 1 | R58: 55.19 | S58: 55.19 | T58: 55.19 | U58: =IFERROR(YEAR(A58),"") -> 2026 | V58: =IFERROR(O58*B58,0) -> 472568.04 | W58: =IFERROR(N58*B58,0) -> 8563 | X58: =IF(OR(ISNUMBER(SEARCH("live nation",L58)),ISNUMBER(SEARCH("ocesa",L58))),1,0) -> 0 | Y58: Asia / home markets
A59: 46103 | B59: 1 | C59: "GOLDEN: A K-Pop Party!" | E59: The Intersection / Elevation | F59: Grand Rapids | G59: Michigan | H59: United States | I59: Grand Rapids-Kalamazoo-Battle Creek | J59: Club | K59: US DOLLAR | L59: (In-House Promotion) | M59: Asian Pop, Dance / Electronic | N59: 600 | O59: 12000 | P59: 600 | Q59: 1 | R59: 20 | S59: 25 | T59: 20 | U59: =IFERROR(YEAR(A59),"") -> 2026 | V59: =IFERROR(O59*B59,0) -> 12000 | W59: =IFERROR(N59*B59,0) -> 600 | X59: =IF(OR(ISNUMBER(SEARCH("live nation",L59)),ISNUMBER(SEARCH("ocesa",L59))),1,0) -> 0 | Y59: Americas + Europe + ANZ
A60: 46103 | B60: 1 | C60: "GOLDEN: A K-Pop Party!" | E60: The Intersection / Elevation | F60: Grand Rapids | G60: Michigan | H60: United States | I60: Grand Rapids-Kalamazoo-Battle Creek | J60: Club | K60: US DOLLAR | L60: (In-House Promotion) | M60: Asian Pop, Dance / Electronic | N60: 465 | O60: 9405 | P60: 600 | Q60: 0.77 | R60: 20 | S60: 25 | T60: 20.23 | U60: =IFERROR(YEAR(A60),"") -> 2026 | V60: =IFERROR(O60*B60,0) -> 9405 | W60: =IFERROR(N60*B60,0) -> 465 | X60: =IF(OR(ISNUMBER(SEARCH("live nation",L60)),ISNUMBER(SEARCH("ocesa",L60))),1,0) -> 0 | Y60: Americas + Europe + ANZ
A61: 46103 | B61: 1 | C61: Meteorites | E61: K-Arena Yokohama | F61: Yokohama | H61: Japan | J61: Arena | K61: Yen | L61: Avex Live Creative Inc. | M61: Asian Pop | N61: 8563 | O61: 473227.51 | P61: 8563 | Q61: 1 | R61: 55.26 | S61: 55.26 | T61: 55.26 | U61: =IFERROR(YEAR(A61),"") -> 2026 | V61: =IFERROR(O61*B61,0) -> 473227.51 | W61: =IFERROR(N61*B61,0) -> 8563 | X61: =IF(OR(ISNUMBER(SEARCH("live nation",L61)),ISNUMBER(SEARCH("ocesa",L61))),1,0) -> 0 | Y61: Asia / home markets
A62: 46103 | B62: 1 | C62: BABYMETAL | E62: Brisbane Riverstage | F62: Brisbane | H62: Australia | J62: Amphitheatre | K62: Australian | L62: Destroy All Lines | M62: Asian Pop, Pop / Rock | N62: 3416 | O62: 371589.39 | P62: 8500 | Q62: 0.4 | R62: 108.78 | S62: 108.78 | T62: 108.78 | U62: =IFERROR(YEAR(A62),"") -> 2026 | V62: =IFERROR(O62*B62,0) -> 371589.39 | W62: =IFERROR(N62*B62,0) -> 3416 | X62: =IF(OR(ISNUMBER(SEARCH("live nation",L62)),ISNUMBER(SEARCH("ocesa",L62))),1,0) -> 0 | Y62: Americas + Europe + ANZ
A63: 46102 | B63: 1 | C63: "KRAZE KPOP" | E63: City Winery Pittsburgh | F63: Pittsburgh | G63: Pennsylvania | H63: United States | I63: Pittsburgh | J63: Club | K63: US DOLLAR | L63: (In-House Productions) / City Winery | M63: Asian Pop, Dance / Electronic | N63: 122 | O63: 2602 | P63: 220 | Q63: 0.55 | R63: 18 | S63: 35 | T63: 21.33 | U63: =IFERROR(YEAR(A63),"") -> 2026 | V63: =IFERROR(O63*B63,0) -> 2602 | W63: =IFERROR(N63*B63,0) -> 122 | X63: =IF(OR(ISNUMBER(SEARCH("live nation",L63)),ISNUMBER(SEARCH("ocesa",L63))),1,0) -> 0 | Y63: Americas + Europe + ANZ
A64: 46102 | B64: 1 | C64: SEVENTEEN | E64: Philippine Sports Stadium | F64: Bulacan | H64: Philippines | J64: Stadium | K64: Pesos | L64: HYBE Co. Ltd. | M64: Asian Pop | N64: 21887 | O64: 4983331.4 | P64: 22157 | Q64: 0.98 | R64: 91.68 | S64: 333.37 | T64: 227.68 | U64: =IFERROR(YEAR(A64),"") -> 2026 | V64: =IFERROR(O64*B64,0) -> 4983331.4 | W64: =IFERROR(N64*B64,0) -> 21887 | X64: =IF(OR(ISNUMBER(SEARCH("live nation",L64)),ISNUMBER(SEARCH("ocesa",L64))),1,0) -> 0 | Y64: Asia / home markets
A65: 46102 | B65: 1 | C65: AMPTAKxCOLORS | E65: K-Arena Yokohama | F65: Yokohama | H65: Japan | J65: Arena | K65: Yen | L65: Avex Live Creative Inc. | M65: Asian Pop | N65: 12409 | O65: 685773.71 | P65: 12409 | Q65: 1 | R65: 55.26 | S65: 55.26 | T65: 55.26 | U65: =IFERROR(YEAR(A65),"") -> 2026 | V65: =IFERROR(O65*B65,0) -> 685773.71 | W65: =IFERROR(N65*B65,0) -> 12409 | X65: =IF(OR(ISNUMBER(SEARCH("live nation",L65)),ISNUMBER(SEARCH("ocesa",L65))),1,0) -> 0 | Y65: Asia / home markets
A66: 46101 | B66: 1 | C66: MESTO | E66: The Grand | F66: Boston | G66: Massachusetts | H66: United States | I66: Boston (Manchester) | J66: Club | K66: US DOLLAR | L66: (In-House Promotion), Big Night Entertainment Group | M66: Asian Pop | N66: 134 | O66: 2360 | P66: 700 | Q66: 0.19 | R66: 15 | S66: 20 | T66: 17.61 | U66: =IFERROR(YEAR(A66),"") -> 2026 | V66: =IFERROR(O66*B66,0) -> 2360 | W66: =IFERROR(N66*B66,0) -> 134 | X66: =IF(OR(ISNUMBER(SEARCH("live nation",L66)),ISNUMBER(SEARCH("ocesa",L66))),1,0) -> 0 | Y66: Americas + Europe + ANZ
A67: 46101 | B67: 1 | C67: AMPTAKxCOLORS | E67: K-Arena Yokohama | F67: Yokohama | H67: Japan | J67: Arena | K67: Yen | L67: Avex Live Creative Inc. | M67: Asian Pop | N67: 12409 | O67: 689419.33 | P67: 12409 | Q67: 1 | R67: 55.56 | S67: 55.56 | T67: 55.56 | U67: =IFERROR(YEAR(A67),"") -> 2026 | V67: =IFERROR(O67*B67,0) -> 689419.33 | W67: =IFERROR(N67*B67,0) -> 12409 | X67: =IF(OR(ISNUMBER(SEARCH("live nation",L67)),ISNUMBER(SEARCH("ocesa",L67))),1,0) -> 0 | Y67: Asia / home markets
A68: 46101 | B68: 1 | C68: BABYMETAL | E68: Hordern Pavilion | F68: Moore Park | H68: Australia | J68: Arena | K68: Australian | L68: Destroy All Lines | M68: Asian Pop, Pop / Rock | N68: 3217 | O68: 351892.33 | P68: 5550 | Q68: 0.57 | R68: 109.39 | S68: 109.39 | T68: 109.39 | U68: =IFERROR(YEAR(A68),"") -> 2026 | V68: =IFERROR(O68*B68,0) -> 351892.33 | W68: =IFERROR(N68*B68,0) -> 3217 | X68: =IF(OR(ISNUMBER(SEARCH("live nation",L68)),ISNUMBER(SEARCH("ocesa",L68))),1,0) -> 0 | Y68: Americas + Europe + ANZ
A69: 46100 | B69: 10 | C69: ST?RISH | D69: QUARTET NIGHT, HE?VENS | E69: Makuhari Messe | F69: Chiba | H69: Japan | J69: Complex | K69: Yen | L69: Creativeman Productions Co. | M69: Asian Pop | N69: 5500 | O69: 513372.86 | P69: 5500 | Q69: 1 | R69: 61.39 | S69: 125.29 | T69: 93.34 | U69: =IFERROR(YEAR(A69),"") -> 2026 | V69: =IFERROR(O69*B69,0) -> 5133728.6 | W69: =IFERROR(N69*B69,0) -> 55000 | X69: =IF(OR(ISNUMBER(SEARCH("live nation",L69)),ISNUMBER(SEARCH("ocesa",L69))),1,0) -> 0 | Y69: Asia / home markets
A70: 46100 | B70: 1 | C70: BABYMETAL | E70: Hordern Pavilion | F70: Moore Park | H70: Australia | J70: Arena | K70: Australian | L70: Destroy All Lines | M70: Asian Pop, Pop / Rock | N70: 1469 | O70: 159869.45 | P70: 5550 | Q70: 0.26 | R70: 108.83 | S70: 108.83 | T70: 108.83 | U70: =IFERROR(YEAR(A70),"") -> 2026 | V70: =IFERROR(O70*B70,0) -> 159869.45 | W70: =IFERROR(N70*B70,0) -> 1469 | X70: =IF(OR(ISNUMBER(SEARCH("live nation",L70)),ISNUMBER(SEARCH("ocesa",L70))),1,0) -> 0 | Y70: Americas + Europe + ANZ
A71: 46098 | B71: 1 | C71: BABYMETAL | E71: John Cain Arena | F71: Melbourne | H71: Australia | J71: Arena | K71: Australian | L71: Destroy All Lines | M71: Asian Pop, Pop / Rock | N71: 5509 | O71: 200804.7 | P71: 9000 | Q71: 0.61 | R71: 109.13 | S71: 128.41 | T71: 36.45 | U71: =IFERROR(YEAR(A71),"") -> 2026 | V71: =IFERROR(O71*B71,0) -> 200804.7 | W71: =IFERROR(N71*B71,0) -> 5509 | X71: =IF(OR(ISNUMBER(SEARCH("live nation",L71)),ISNUMBER(SEARCH("ocesa",L71))),1,0) -> 0 | Y71: Americas + Europe + ANZ
A72: 46097 | B72: 1 | C72: D.U.N.K Showcase | D72: SB19, .ENDRECHERI, SkyHi, STARGLOW, Da-iCE, BE:FIRST, BMSG TRAINEE | E72: K-Arena Yokohama | F72: Yokohama | H72: Japan | J72: Arena | K72: Yen | L72: Sogo Tokyo Corporation | M72: Asian Pop | N72: 18200 | O72: 2168016 | P72: 18200 | Q72: 1 | R72: 119.12 | S72: 119.12 | T72: 119.12 | U72: =IFERROR(YEAR(A72),"") -> 2026 | V72: =IFERROR(O72*B72,0) -> 2168016 | W72: =IFERROR(N72*B72,0) -> 18200 | X72: =IF(OR(ISNUMBER(SEARCH("live nation",L72)),ISNUMBER(SEARCH("ocesa",L72))),1,0) -> 0 | Y72: Asia / home markets
A73: 46095 | B73: 2 | C73: SEVENTEEN | E73: Rajamangala National Stadium | F73: Bangkok | H73: Thailand | J73: Stadium | K73: Baht | L73: HYBE Co. Ltd. | M73: Asian Pop | N73: 13576 | O73: 2650417.6 | P73: 31569 | Q73: 0.43 | R73: 108.53 | S73: 288.38 | T73: 195.23 | U73: =IFERROR(YEAR(A73),"") -> 2026 | V73: =IFERROR(O73*B73,0) -> 5300835.3 | W73: =IFERROR(N73*B73,0) -> 27152 | X73: =IF(OR(ISNUMBER(SEARCH("live nation",L73)),ISNUMBER(SEARCH("ocesa",L73))),1,0) -> 0 | Y73: Asia / home markets
A74: 46095 | B74: 1 | C74: D.U.N.K Showcase | D74: INI, Ayumu Imazu, ShowMinorSavage, SkyHi, Bullet Train, BUS, BGYO, Mazzel, ONE N' ONLY, LDH SCREAM | E74: K-Arena Yokohama | F74: Yokohama | H74: Japan | J74: Arena | K74: Yen | L74: Sogo Tokyo Corporation | M74: Asian Pop | N74: 18200 | O74: 2164700 | P74: 18200 | Q74: 1 | R74: 118.94 | S74: 118.94 | T74: 118.94 | U74: =IFERROR(YEAR(A74),"") -> 2026 | V74: =IFERROR(O74*B74,0) -> 2164700 | W74: =IFERROR(N74*B74,0) -> 18200 | X74: =IF(OR(ISNUMBER(SEARCH("live nation",L74)),ISNUMBER(SEARCH("ocesa",L74))),1,0) -> 0 | Y74: Asia / home markets
A75: 46095 | B75: 2 | C75: ILLIT | E75: ticketLink Live Arena | F75: Seoul | H75: South Korea | J75: Arena | K75: Won | L75: HYBE Co. Ltd. | M75: Asian Pop | N75: 3176 | O75: 379129.65 | P75: 3150 | Q75: 1 | R75: 109.79 | S75: 146.39 | T75: 119.35 | U75: =IFERROR(YEAR(A75),"") -> 2026 | V75: =IFERROR(O75*B75,0) -> 758259.3 | W75: =IFERROR(N75*B75,0) -> 6352 | X75: =IF(OR(ISNUMBER(SEARCH("live nation",L75)),ISNUMBER(SEARCH("ocesa",L75))),1,0) -> 0 | Y75: Asia / home markets
A76: 46095 | B76: 1 | C76: Silence Wang | E76: Climate Pledge Arena | F76: Seattle | G76: Washington | H76: United States | I76: Seattle-Tacoma | J76: Arena | K76: US DOLLAR | L76: International Entertainment Marketing | M76: Asian Pop | N76: 9625 | O76: 2015329 | P76: 12594 | Q76: 0.76 | R76: 113.5 | S76: 403.5 | T76: 209.38 | U76: =IFERROR(YEAR(A76),"") -> 2026 | V76: =IFERROR(O76*B76,0) -> 2015329 | W76: =IFERROR(N76*B76,0) -> 9625 | X76: =IF(OR(ISNUMBER(SEARCH("live nation",L76)),ISNUMBER(SEARCH("ocesa",L76))),1,0) -> 0 | Y76: Americas + Europe + ANZ
A77: 46095 | B77: 1 | C77: BABYMETAL | E77: Adelaide Entertainment Centre Theatre | F77: Hindmarsh | H77: Australia | J77: Auditorium / Theatre | K77: Australian | L77: Destroy All Lines | M77: Asian Pop, Pop / Rock | N77: 2578 | O77: 278322.35 | P77: 3000 | Q77: 0.85 | R77: 107.96 | S77: 107.96 | T77: 107.96 | U77: =IFERROR(YEAR(A77),"") -> 2026 | V77: =IFERROR(O77*B77,0) -> 278322.35 | W77: =IFERROR(N77*B77,0) -> 2578 | X77: =IF(OR(ISNUMBER(SEARCH("live nation",L77)),ISNUMBER(SEARCH("ocesa",L77))),1,0) -> 0 | Y77: Americas + Europe + ANZ
A78: 46094 | B78: 1 | C78: Keung To | E78: OVO Arena Wembley | F78: London | H78: United Kingdom | J78: Arena | K78: Pound Sterling | L78: (In-House Promotion) | M78: Asian Pop | N78: 3217 | O78: 737332.67 | P78: 4253 | Q78: 0.75 | R78: 104.1 | S78: 304.29 | T78: 229.2 | U78: =IFERROR(YEAR(A78),"") -> 2026 | V78: =IFERROR(O78*B78,0) -> 737332.67 | W78: =IFERROR(N78*B78,0) -> 3217 | X78: =IF(OR(ISNUMBER(SEARCH("live nation",L78)),ISNUMBER(SEARCH("ocesa",L78))),1,0) -> 0 | Y78: Americas + Europe + ANZ
A79: 46094 | B79: 1 | C79: D.U.N.K Showcase | D79: INI, Cup Of Joe, CORTIS, s**t kingz, SkyHi, Da Pump, Tomohiro Kamiyama, CIRRA | E79: K-Arena Yokohama | F79: Yokohama | H79: Japan | J79: Arena | K79: Yen | L79: Sogo Tokyo Corporation | M79: Asian Pop | N79: 18200 | O79: 2169912.1 | P79: 18200 | Q79: 1 | R79: 119.23 | S79: 119.23 | T79: 119.23 | U79: =IFERROR(YEAR(A79),"") -> 2026 | V79: =IFERROR(O79*B79,0) -> 2169912.1 | W79: =IFERROR(N79*B79,0) -> 18200 | X79: =IF(OR(ISNUMBER(SEARCH("live nation",L79)),ISNUMBER(SEARCH("ocesa",L79))),1,0) -> 0 | Y79: Asia / home markets
A80: 46093 | B80: 1 | C80: BABYMETAL | D80: Bloodywood | E80: Perth HPC | F80: Mount Claremont | H80: Australia | J80: Stadium | K80: Australian | L80: Destroy All Lines | M80: Asian Pop, Pop / Rock | N80: 3253 | O80: 63612.66 | P80: 4500 | Q80: 0.72 | R80: 110.8 | S80: 130.37 | T80: 19.56 | U80: =IFERROR(YEAR(A80),"") -> 2026 | V80: =IFERROR(O80*B80,0) -> 63612.66 | W80: =IFERROR(N80*B80,0) -> 3253 | X80: =IF(OR(ISNUMBER(SEARCH("live nation",L80)),ISNUMBER(SEARCH("ocesa",L80))),1,0) -> 0 | Y80: Americas + Europe + ANZ
A81: 46089 | B81: 1 | C81: "CDTV Live! Live! | D81: &TEAM, M!LK, ATARASHII GAKKO!, Aina the End | E81: K-Arena Yokohama | F81: Yokohama | H81: Japan | J81: Arena | K81: Yen | L81: Disk Garage | M81: Asian Pop | N81: 19800 | O81: 1505846.6 | P81: 19800 | Q81: 1 | R81: 76.05 | S81: 76.05 | T81: 76.05 | U81: =IFERROR(YEAR(A81),"") -> 2026 | V81: =IFERROR(O81*B81,0) -> 1505846.6 | W81: =IFERROR(N81*B81,0) -> 19800 | X81: =IF(OR(ISNUMBER(SEARCH("live nation",L81)),ISNUMBER(SEARCH("ocesa",L81))),1,0) -> 0 | Y81: Asia / home markets
A82: 46088 | B82: 2 | C82: Silence Wang | E82: Barclays Center | F82: Brooklyn | G82: New York | H82: United States | I82: New York | J82: Arena | K82: US DOLLAR | L82: IEM Group | M82: Asian Pop | N82: 10207 | O82: 2273561.4 | P82: 10207 | Q82: 1 | R82: 98 | S82: 398 | T82: 222.75 | U82: =IFERROR(YEAR(A82),"") -> 2026 | V82: =IFERROR(O82*B82,0) -> 4547122.8 | W82: =IFERROR(N82*B82,0) -> 20414 | X82: =IF(OR(ISNUMBER(SEARCH("live nation",L82)),ISNUMBER(SEARCH("ocesa",L82))),1,0) -> 0 | Y82: Americas + Europe + ANZ
A83: 46088 | B83: 1 | C83: SEVENTEEN | E83: National Stadium | F83: Singapore | H83: Singapore | J83: Stadium | K83: Singapore | L83: HYBE Co. Ltd. | M83: Asian Pop | N83: 33649 | O83: 8596110.8 | P83: 34329 | Q83: 0.98 | R83: 155.61 | S83: 272.91 | T83: 255.46 | U83: =IFERROR(YEAR(A83),"") -> 2026 | V83: =IFERROR(O83*B83,0) -> 8596110.8 | W83: =IFERROR(N83*B83,0) -> 33649 | X83: =IF(OR(ISNUMBER(SEARCH("live nation",L83)),ISNUMBER(SEARCH("ocesa",L83))),1,0) -> 0 | Y83: Asia / home markets
A84: 46088 | B84: 1 | C84: "CDTV Live! Live! | D84: Bullet Train, BOYNEXTDOOR, Little Glee Monster, =LOVE | E84: K-Arena Yokohama | F84: Yokohama | H84: Japan | J84: Arena | K84: Yen | L84: Disk Garage | M84: Asian Pop | N84: 19800 | O84: 1505679.5 | P84: 19800 | Q84: 1 | R84: 76.04 | S84: 76.04 | T84: 76.04 | U84: =IFERROR(YEAR(A84),"") -> 2026 | V84: =IFERROR(O84*B84,0) -> 1505679.5 | W84: =IFERROR(N84*B84,0) -> 19800 | X84: =IF(OR(ISNUMBER(SEARCH("live nation",L84)),ISNUMBER(SEARCH("ocesa",L84))),1,0) -> 0 | Y84: Asia / home markets
A85: 46087 | B85: 2 | C85: TWICE | E85: TD Coliseum | F85: Hamilton | G85: Ontario | H85: Canada | J85: Arena | K85: Canadian | L85: Live Nation | M85: Asian Pop | N85: 15073 | O85: 1852267.1 | P85: 15700 | Q85: 0.96 | R85: 58.2 | S85: 204.6 | T85: 122.89 | U85: =IFERROR(YEAR(A85),"") -> 2026 | V85: =IFERROR(O85*B85,0) -> 3704534.2 | W85: =IFERROR(N85*B85,0) -> 30146 | X85: =IF(OR(ISNUMBER(SEARCH("live nation",L85)),ISNUMBER(SEARCH("ocesa",L85))),1,0) -> 1 | Y85: Americas + Europe + ANZ
A86: 46087 | B86: 2 | C86: ATEEZ | E86: Qudos Bank Arena | F86: Sydney | H86: Australia | J86: Arena | K86: Australian | L86: Frontier Touring | M86: Asian Pop | N86: 7547 | O86: 1306096.5 | P86: 8584 | Q86: 0.87 | R86: 70.22 | S86: 245.95 | T86: 173.05 | U86: =IFERROR(YEAR(A86),"") -> 2026 | V86: =IFERROR(O86*B86,0) -> 2612192.9 | W86: =IFERROR(N86*B86,0) -> 15094 | X86: =IF(OR(ISNUMBER(SEARCH("live nation",L86)),ISNUMBER(SEARCH("ocesa",L86))),1,0) -> 0 | Y86: Americas + Europe + ANZ
A87: 46084 | B87: 1 | C87: ATEEZ | E87: Rod Laver Arena | F87: Melbourne | H87: Australia | J87: Arena | K87: Australian | L87: Frontier Touring | M87: Asian Pop | N87: 8876 | O87: 1750596.4 | P87: 8876 | Q87: 1 | R87: 70.97 | S87: 248.58 | T87: 197.23 | U87: =IFERROR(YEAR(A87),"") -> 2026 | V87: =IFERROR(O87*B87,0) -> 1750596.4 | W87: =IFERROR(N87*B87,0) -> 8876 | X87: =IF(OR(ISNUMBER(SEARCH("live nation",L87)),ISNUMBER(SEARCH("ocesa",L87))),1,0) -> 0 | Y87: Americas + Europe + ANZ
A88: 46084 | B88: 1 | C88: TWICE | E88: Bell Centre | F88: Montreal | G88: Quebec | H88: Canada | J88: Arena | K88: Canadian | L88: (In-House Promotion), evenko, Live Nation | M88: Asian Pop | N88: 17885 | O88: 2083140.7 | P88: 17885 | Q88: 1 | R88: 58.15 | S88: 204.43 | T88: 116.47 | U88: =IFERROR(YEAR(A88),"") -> 2026 | V88: =IFERROR(O88*B88,0) -> 2083140.7 | W88: =IFERROR(N88*B88,0) -> 17885 | X88: =IF(OR(ISNUMBER(SEARCH("live nation",L88)),ISNUMBER(SEARCH("ocesa",L88))),1,0) -> 1 | Y88: Americas + Europe + ANZ
A89: 46083 | B89: 1 | C89: ATEEZ | E89: Rod Laver Arena | F89: Melbourne | H89: Australia | J89: Arena | K89: Australian | L89: Frontier Touring | M89: Asian Pop | N89: 4626 | O89: 845033.28 | P89: 4626 | Q89: 1 | R89: 70.87 | S89: 247.95 | T89: 182.67 | U89: =IFERROR(YEAR(A89),"") -> 2026 | V89: =IFERROR(O89*B89,0) -> 845033.28 | W89: =IFERROR(N89*B89,0) -> 4626 | X89: =IF(OR(ISNUMBER(SEARCH("live nation",L89)),ISNUMBER(SEARCH("ocesa",L89))),1,0) -> 0 | Y89: Americas + Europe + ANZ
A90: 46082 | B90: 1 | C90: "GOLDEN: A K-Pop Party!" | E90: Union Stage | F90: Washington | G90: District of Columbia | H90: United States | I90: Washington, D.C. (Hagerstown) | J90: Club | K90: US DOLLAR | L90: Union Stage Presents | M90: Asian Pop, Dance / Electronic | N90: 307 | O90: 4928 | P90: 500 | Q90: 0.61 | R90: 15 | S90: 22 | T90: 16.05 | U90: =IFERROR(YEAR(A90),"") -> 2026 | V90: =IFERROR(O90*B90,0) -> 4928 | W90: =IFERROR(N90*B90,0) -> 307 | X90: =IF(OR(ISNUMBER(SEARCH("live nation",L90)),ISNUMBER(SEARCH("ocesa",L90))),1,0) -> 0 | Y90: Americas + Europe + ANZ
A91: 46082 | B91: 1 | C91: MyGO!!!!! | D91: Ave Mujica, millsage, Ikka Dumb Rock! | E91: K-Arena Yokohama | F91: Yokohama | H91: Japan | J91: Arena | K91: Yen | L91: Creativeman Productions Co. | M91: Asian Pop | N91: 20000 | O91: 1268864.8 | P91: 20000 | Q91: 1 | R91: 63.44 | S91: 63.44 | T91: 63.44 | U91: =IFERROR(YEAR(A91),"") -> 2026 | V91: =IFERROR(O91*B91,0) -> 1268864.8 | W91: =IFERROR(N91*B91,0) -> 20000 | X91: =IF(OR(ISNUMBER(SEARCH("live nation",L91)),ISNUMBER(SEARCH("ocesa",L91))),1,0) -> 0 | Y91: Asia / home markets
A92: 46081 | B92: 1 | C92: "Mystic Nights", Dan Truong | D92: Quang Le, Trinh Lam | E92: The Theater at MGM National Harbor | F92: Oxon Hill | G92: Maryland | H92: United States | I92: Washington, D.C. (Hagerstown) | J92: Auditorium / Theatre | K92: US DOLLAR | L92: 5M Music | M92: Asian Pop, World | N92: 1974 | O92: 192928 | P92: 2900 | Q92: 0.68 | R92: 33.2 | S92: 148 | T92: 97.73 | U92: =IFERROR(YEAR(A92),"") -> 2026 | V92: =IFERROR(O92*B92,0) -> 192928 | W92: =IFERROR(N92*B92,0) -> 1974 | X92: =IF(OR(ISNUMBER(SEARCH("live nation",L92)),ISNUMBER(SEARCH("ocesa",L92))),1,0) -> 0 | Y92: Americas + Europe + ANZ
A93: 46081 | B93: 1 | C93: "GOLDEN: A K-Pop Party!" | E93: Jammin' Java | F93: Vienna | G93: Virginia | H93: United States | I93: Washington, D.C. (Hagerstown) | J93: Club | K93: US DOLLAR | L93: Union Stage Presents | M93: Asian Pop, Dance / Electronic | N93: 175 | O93: 4928 | P93: 180 | Q93: 0.97 | R93: 15 | S93: 22 | T93: 28.16 | U93: =IFERROR(YEAR(A93),"") -> 2026 | V93: =IFERROR(O93*B93,0) -> 4928 | W93: =IFERROR(N93*B93,0) -> 175 | X93: =IF(OR(ISNUMBER(SEARCH("live nation",L93)),ISNUMBER(SEARCH("ocesa",L93))),1,0) -> 0 | Y93: Americas + Europe + ANZ
A94: 46081 | B94: 1 | C94: BanG Dream! | D94: Poppin'Party, Afterglow, Pastel*Palettes, Roselia, Hello, Hello, Happy World!, Morfonica, RAISE A SUILEN, MyGO!!!!!, Ave Mujica, Mugendai Mewtype | E94: K-Arena Yokohama | F94: Yokohama | H94: Japan | J94: Arena | K94: Yen | L94: Creativeman Productions Co. | M94: Asian Pop | N94: 20000 | O94: 1281517.3 | P94: 20000 | Q94: 1 | R94: 64.08 | S94: 64.08 | T94: 64.08 | U94: =IFERROR(YEAR(A94),"") -> 2026 | V94: =IFERROR(O94*B94,0) -> 1281517.3 | W94: =IFERROR(N94*B94,0) -> 20000 | X94: =IF(OR(ISNUMBER(SEARCH("live nation",L94)),ISNUMBER(SEARCH("ocesa",L94))),1,0) -> 0 | Y94: Asia / home markets
A95: 46081 | B95: 2 | C95: SEVENTEEN | E95: Kai Tak Stadium | F95: Kowloon | H95: Hong Kong | J95: Stadium | K95: Hong Kong | L95: HYBE Co. Ltd. | M95: Asian Pop | N95: 36621 | O95: 8422939.3 | P95: 36584 | Q95: 1 | R95: 114.92 | S95: 370.57 | T95: 230 | U95: =IFERROR(YEAR(A95),"") -> 2026 | V95: =IFERROR(O95*B95,0) -> 16845879 | W95: =IFERROR(N95*B95,0) -> 73242 | X95: =IF(OR(ISNUMBER(SEARCH("live nation",L95)),ISNUMBER(SEARCH("ocesa",L95))),1,0) -> 0 | Y95: Asia / home markets
A96: 46080 | B96: 1 | C96: TWICE | E96: State Farm Arena | F96: Atlanta | G96: Georgia | H96: United States | I96: Atlanta | J96: Arena | K96: US DOLLAR | L96: Live Nation | M96: Asian Pop | N96: 15084 | O96: 2099562 | P96: 15084 | Q96: 1 | R96: 59.5 | S96: 229.5 | T96: 139.19 | U96: =IFERROR(YEAR(A96),"") -> 2026 | V96: =IFERROR(O96*B96,0) -> 2099562 | W96: =IFERROR(N96*B96,0) -> 15084 | X96: =IF(OR(ISNUMBER(SEARCH("live nation",L96)),ISNUMBER(SEARCH("ocesa",L96))),1,0) -> 1 | Y96: Americas + Europe + ANZ
A97: 46080 | B97: 1 | C97: HoYoFair Fan Concert | E97: Uber Eats Music Hall | F97: Berlin | H97: Germany | J97: Auditorium / Theatre | K97: Euro | L97: Semmel Concerts Entertainment GmbH | M97: Asian Pop | N97: 693 | O97: 66254.31 | P97: 1316 | Q97: 0.52 | R97: 59.05 | S97: 124.01 | T97: 95.61 | U97: =IFERROR(YEAR(A97),"") -> 2026 | V97: =IFERROR(O97*B97,0) -> 66254.31 | W97: =IFERROR(N97*B97,0) -> 693 | X97: =IF(OR(ISNUMBER(SEARCH("live nation",L97)),ISNUMBER(SEARCH("ocesa",L97))),1,0) -> 0 | Y97: Americas + Europe + ANZ
A98: 46076 | B98: 2 | C98: ?ME | E98: K-Arena Yokohama | F98: Yokohama | H98: Japan | J98: Arena | K98: Yen | L98: Disk Garage | M98: Asian Pop | N98: 6500 | O98: 833572.85 | P98: 11 | Q98: 590.9 | R98: 64.12 | S98: 64.12 | T98: 128.24 | U98: =IFERROR(YEAR(A98),"") -> 2026 | V98: =IFERROR(O98*B98,0) -> 1667145.7 | W98: =IFERROR(N98*B98,0) -> 13000 | X98: =IF(OR(ISNUMBER(SEARCH("live nation",L98)),ISNUMBER(SEARCH("ocesa",L98))),1,0) -> 0 | Y98: Asia / home markets
A99: 46074 | B99: 1 | C99: Hoshimachi Suisei | E99: K-Arena Yokohama | F99: Yokohama | H99: Japan | J99: Arena | K99: Yen | L99: Disk Garage | M99: Asian Pop | N99: 19800 | O99: 1060223.8 | P99: 19800 | Q99: 1 | R99: 53.55 | S99: 53.55 | T99: 53.55 | U99: =IFERROR(YEAR(A99),"") -> 2026 | V99: =IFERROR(O99*B99,0) -> 1060223.8 | W99: =IFERROR(N99*B99,0) -> 19800 | X99: =IF(OR(ISNUMBER(SEARCH("live nation",L99)),ISNUMBER(SEARCH("ocesa",L99))),1,0) -> 0 | Y99: Asia / home markets
A100: 46072 | B100: 1 | C100: ZEROBASEONE | E100: K-Arena Yokohama | F100: Yokohama | H100: Japan | J100: Arena | K100: Yen | L100: Disk Garage | M100: Asian Pop | N100: 18000 | O100: 2367839.2 | P100: 18000 | Q100: 1 | R100: 95.73 | S100: 95.73 | T100: 131.55 | U100: =IFERROR(YEAR(A100),"") -> 2026 | V100: =IFERROR(O100*B100,0) -> 2367839.2 | W100: =IFERROR(N100*B100,0) -> 18000 | X100: =IF(OR(ISNUMBER(SEARCH("live nation",L100)),ISNUMBER(SEARCH("ocesa",L100))),1,0) -> 0 | Y100: Asia / home markets
...
