Workbook

Sheet Cover
B2: TKO Group Holdings — Up-C Reconciliation
B3: Quantifying optical FCF leakage vs true Class A shareholder economics
B5: Prepared for: Ian Moore, VP & Research Analyst — Bernstein US Entertainment
B6: Date: May 11, 2026
B8: THESIS
B9: Bears argue OpCo tax distributions to Endeavor (~$475M FY26E) reduce reported FCF and therefore Class A shareholder economics. This is a flawed comparison. In a hypothetical C-Corp, the equivalent money would leave as corporate tax to the IRS — also gone. The relevant comparison is Up-C vs C-Corp, not Up-C vs Up-C-with-no-distributions. When properly compared, PubCo Class A FCF/share is ~117-123% of what it would be in a C-Corp with the same operating cash flows, driven by the 12.2% structural effective tax rate per 10-K Note 15.
B11: FILE STRUCTURE (5 tabs)
B12: 1. Cover — this page
B13: 2. Inputs — assumptions (blue = hardcoded primary-source value; green = linked to BERN_TKO.xlsx)
B14: 3. Walk — three FCF buildups side-by-side: Bear case, TRUE PubCo, C-Corp comparable
B15: 4. Output — final per-share table and publishable conclusion
B16: 5. Sensitivity — stress test on the two key variables (tax rate, distribution rate)
... B36: • Validation: Q1 2026 10-Q Note 12 (12.0% effective rate — confirms FY25 12.2% as run-rate)

Sheet Inputs
B2: INPUTS & ASSUMPTIONS
B4: STRUCTURAL ASSUMPTIONS
B5: Assumption | C5: Value | D5: Source
B6: PubCo (TKO Group) economic interest in OpCo | C6: 0.392 | D6: Q1 2026 10-Q Note 9 (74.96M Class A / 191.12M total OpCo units)
B7: Endeavor/Silver Lake economic interest (NCI) | C7: 0.608 | D7: Q1 2026 10-Q Note 9 (116.16M Class B / 191.12M total)
B8: Tax Distribution Rate (LLC Agreement) | C8: 0.526 | D8: LLC Agreement Sec 1.01: highest NYC/LA marginal individual rate net of SALT cap
B9: Hypothetical C-Corp effective tax rate | C9: 0.25 | D9: Standard analyst comparable; federal 21% + state ~4% blended
B10: TRA payment ratio (if exchanges occur) | C10: 0.85 | D10: Endeavor TRA dated April 28, 2021
B11: TRA payments through 12/31/25 | C11: 0 | D11: 10-K Note 15: zero TRA disclosure — confirmed dormant
B13: RATE OVERRIDE — PUBCO EFFECTIVE TAX RATE FOR FORECAST
B14: 10-K Note 15 shows FY25 actual = 12.2%, with 11.3pp from 'Partnership Income Not Subject to Tax' — structurally driven by Up-C and persists as long as Endeavor holds OpCo units. Bern model's FY27E/28E rates of ~20-21% are too punitive. Override to 12.5% for forecast.
B15: PubCo effective tax rate (override for FY26E-FY28E): | C15: 0.125
B16: FY24 effective rate (NM, loss year — use 0% for FCF calc) | C16: 0

Sheet Walk
B2: WALK — Three FCF/share calculations side by side
B3: Operating values linked from BERN_TKO.xlsx; per-share calcs use diluted shares (IS row 29)
B5: ($ in millions, except per-share) | C5: FY24 | D5: FY25 | E5: FY26E | F5: FY27E | G5: FY28E
B7: A. OPERATING DATA (LINKED FROM BERN_TKO.xlsx)
B8: Revenue | C8: ='[BERN_TKO.xlsx]IS'!BJ4 | D8: ='[BERN_TKO.xlsx]IS'!BK4 | E8: ='[BERN_TKO.xlsx]IS'!BL4 | F8: ='[BERN_TKO.xlsx]IS'!BM4 | G8: ='[BERN_TKO.xlsx]IS'!BN4
B9: EBIT | C9: ='[BERN_TKO.xlsx]IS'!BJ12 | D9: ='[BERN_TKO.xlsx]IS'!BK12 | E9: ='[BERN_TKO.xlsx]IS'!BL12 | F9: ='[BERN_TKO.xlsx]IS'!BM12 | G9: ='[BERN_TKO.xlsx]IS'!BN12
B10: Income before taxes (EBT) | C10: ='[BERN_TKO.xlsx]IS'!BJ15 | D10: ='[BERN_TKO.xlsx]IS'!BK15 | E10: ='[BERN_TKO.xlsx]IS'!BL15 | F10: ='[BERN_TKO.xlsx]IS'!BM15 | G10: ='[BERN_TKO.xlsx]IS'!BN15
B11: Income tax expense (Bern) | C11: ='[BERN_TKO.xlsx]IS'!BJ17 | D11: ='[BERN_TKO.xlsx]IS'!BK17 | E11: ='[BERN_TKO.xlsx]IS'!BL17 | F11: ='[BERN_TKO.xlsx]IS'!BM17 | G11: ='[BERN_TKO.xlsx]IS'!BN17
B12: Effective tax rate (Bern) | C12: ='[BERN_TKO.xlsx]IS'!BJ18 | D12: ='[BERN_TKO.xlsx]IS'!BK18 | E12: ='[BERN_TKO.xlsx]IS'!BL18 | F12: ='[BERN_TKO.xlsx]IS'!BM18 | G12: ='[BERN_TKO.xlsx]IS'!BN18
B13: Operating cash flow (OCF) | C13: ='[BERN_TKO.xlsx]CFS'!BJ23 | D13: ='[BERN_TKO.xlsx]CFS'!BK23 | E13: ='[BERN_TKO.xlsx]CFS'!BL23 | F13: ='[BERN_TKO.xlsx]CFS'!BM23 | G13: ='[BERN_TKO.xlsx]CFS'!BN23
B14: Capex | C14: ='[BERN_TKO.xlsx]CFS'!BJ27 | D14: ='[BERN_TKO.xlsx]CFS'!BK27 | E14: ='[BERN_TKO.xlsx]CFS'!BL27 | F14: ='[BERN_TKO.xlsx]CFS'!BM27 | G14: ='[BERN_TKO.xlsx]CFS'!BN27
B15: Bern reported Free Cash Flow | C15: ='[BERN_TKO.xlsx]CFS'!BJ56 | D15: ='[BERN_TKO.xlsx]CFS'!BK56 | E15: ='[BERN_TKO.xlsx]CFS'!BL56 | F15: ='[BERN_TKO.xlsx]CFS'!BM56 | G15: ='[BERN_TKO.xlsx]CFS'!BN56
B16: Distributions to Endeavor (NCI, CFS row 38) | C16: ='[BERN_TKO.xlsx]CFS'!BJ38 | D16: ='[BERN_TKO.xlsx]CFS'!BK38 | E16: ='[BERN_TKO.xlsx]CFS'!BL38 | F16: ='[BERN_TKO.xlsx]CFS'!BM38 | G16: ='[BERN_TKO.xlsx]CFS'!BN38
B17: Diluted shares (Class A + Class B/OpCo) | C17: ='[BERN_TKO.xlsx]IS'!BJ29 | D17: ='[BERN_TKO.xlsx]IS'!BK29 | E17: ='[BERN_TKO.xlsx]IS'!BL29 | F17: ='[BERN_TKO.xlsx]IS'!BM29 | G17: ='[BERN_TKO.xlsx]IS'!BN29
B19: B. BEAR CASE — Bern Reported FCF less Distributions (the wrong framing)
B20: Bern reported FCF (linked from CFS row 56) | C20: =C15 | D20: =D15 | E20: =E15 | F20: =F15 | G20: =G15
B21: Plus: Distributions to Endeavor (already negative in CFS) | C21: =C16 | D21: =D16 | E21: =E16 | F21: =F16 | G21: =G16
B22: =Bear case 'FCF after distributions' | C22: =C20+C21 | D22: =D20+D21 | E22: =E20+E21 | F22: =F20+F21 | G22: =G20+G21
B23: Bear FCF / diluted share | C23: =IFERROR(C22/C17,0) | D23: =IFERROR(D22/D17,0) | E23: =IFERROR(E22/E17,0) | F23: =IFERROR(F22/F17,0) | G23: =IFERROR(G22/G17,0)
B24: This is the bear's framing: 'Bern says FCF is X, but $475M leaks to Endeavor, so real FCF is X − $475M.' The framing is wrong — see Section C.
B26: C. TRUE PUBCO ECONOMIC FCF (what Class A shareholders actually own)
B27: Logic: PubCo owns 39.2% of OpCo. The distributions to Endeavor are NOT a loss to PubCo — they're Endeavor's economic share. PubCo's true claim = 39.2% × OpCo's after-tax FCF.
B28: PubCo effective tax rate (override for forecast) | C28: =Inputs!$C$16 | D28: =D12 | E28: =Inputs!$C$15 | F28: =Inputs!$C$15 | G28: =Inputs!$C$15
B29: OpCo pre-tax FCF (= Bern reported FCF + tax expense) | C29: =C15+C11 | D29: =D15+D11 | E29: =E15+E11 | F29: =F15+F11 | G29: =G15+G11
B30: × PubCo's 39.2% economic interest | C30: =C29*Inputs!$C$6 | D30: =D29*Inputs!$C$6 | E30: =E29*Inputs!$C$6 | F30: =F29*Inputs!$C$6 | G30: =G29*Inputs!$C$6
B31: Less: PubCo's federal tax (rate × 39.2% × EBT) | C31: =-C28*Inputs!$C$6*C10 | D31: =-D28*Inputs!$C$6*D10 | E31: =-E28*Inputs!$C$6*E10 | F31: =-F28*Inputs!$C$6*F10 | G31: =-G28*Inputs!$C$6*G10
B32: =TRUE PubCo economic FCF | C32: =C30+C31 | D32: =D30+D31 | E32: =E30+E31 | F32: =F30+F31 | G32: =G30+G31
B33: TRUE PubCo FCF / Class A basic share (PubCo's economic claim only) | C33: =IFERROR(C32/'[BERN_TKO.xlsx]IS'!BJ28,0) | D33: =IFERROR(D32/'[BERN_TKO.xlsx]IS'!BK28,0) | E33: =IFERROR(E32/'[BERN_TKO.xlsx]IS'!BL28,0) | F33: =IFERROR(F32/'[BERN_TKO.xlsx]IS'!BM28,0) | G33: =IFERROR(G32/'[BERN_TKO.xlsx]IS'!BN28,0)
B35: D. C-CORP COMPARABLE (apples-to-apples)
B36: In a C-Corp, all shareholders share equally (Class A + Class B convert to single class). FCF = EBT × (1 − 25%) − Capex. Per fully-diluted share.
B37: EBT × (1 − 25% C-Corp rate) | C37: =C10*(1-Inputs!$C$9) | D37: =D10*(1-Inputs!$C$9) | E37: =E10*(1-Inputs!$C$9) | F37: =F10*(1-Inputs!$C$9) | G37: =G10*(1-Inputs!$C$9)
B38: Plus: D&A and other non-cash (Bern FCF adjustment) | C38: =C29-C10 | D38: =D29-D10 | E38: =E29-E10 | F38: =F29-F10 | G38: =G29-G10
B39: =C-Corp FCF (available to ALL shareholders) | C39: =C37+C38 | D39: =D37+D38 | E39: =E37+E38 | F39: =F37+F38 | G39: =G37+G38
B40: C-Corp FCF / fully-diluted share | C40: =IFERROR(C39/C17,0) | D40: =IFERROR(D39/D17,0) | E40: =IFERROR(E39/E17,0) | F40: =IFERROR(F39/F17,0) | G40: =IFERROR(G39/G17,0)
B42: E. PER-SHARE COMPARISON
B43: (1) Bear's 'FCF after distributions' / diluted | C43: =C23 | D43: =D23 | E43: =E23 | F43: =F23 | G43: =G23
B44: (2) TRUE PubCo Class A economic FCF / Class A share | C44: =C33 | D44: =D33 | E44: =E33 | F44: =F33 | G44: =G33
B45: (3) C-Corp FCF / fully-diluted share | C45: =C40 | D45: =D40 | E45: =E40 | F45: =F40 | G45: =G40
B47: Up-C as % of C-Corp comparable | C47: =IFERROR(C44/C45,0) | D47: =IFERROR(D44/D45,0) | E47: =IFERROR(E44/E45,0) | F47: =IFERROR(F44/F45,0) | G47: =IFERROR(G44/G45,0)

Sheet Output
B2: OUTPUT — Final Comparison and Conclusion
B3: Headline table for the published note
B5: ($ in millions, except per-share) | C5: FY24 | D5: FY25 | E5: FY26E | F5: FY27E | G5: FY28E
B7: HEADLINE: FCF PER SHARE — THREE FRAMINGS
B8: (1) Bear case: 'FCF after distributions' / share | C8: =Walk!C23 | D8: =Walk!D23 | E8: =Walk!E23 | F8: =Walk!F23 | G8: =Walk!G23
B9: (2) TRUE PubCo Class A economic FCF / Class A share | C9: =Walk!C33 | D9: =Walk!D33 | E9: =Walk!E33 | F9: =Walk!F33 | G9: =Walk!G33
B10: (3) C-Corp comparable FCF / fully-diluted share | C10: =Walk!C40 | D10: =Walk!D40 | E10: =Walk!E40 | F10: =Walk!F40 | G10: =Walk!G40
B12: TRUE PubCo as % of C-Corp comparable | C12: =IFERROR(C9/C10,0) | D12: =IFERROR(D9/D10,0) | E12: =IFERROR(E9/E10,0) | F12: =IFERROR(F9/F10,0) | G12: =IFERROR(G9/G10,0)
B14: PUBLISHABLE CONCLUSION
B15: TKO's Up-C structure delivers PubCo Class A shareholders ~117-123% of the per-share FCF they would receive in a hypothetical C-Corp with the same operating cash flows, sustained through FY28E. The driver is the 12.2% structural PubCo effective tax rate vs. the 25% rate that would apply in a C-Corp. The bear thesis — that 'levered FCF leakage to Endeavor reduces Class A shareholder value' — conflates two things: consolidated cash flowing to NCI for tax purposes (gone, but the C-Corp equivalent would have gone to IRS) and PubCo's economic claim on remaining OpCo cash (retained, taxed at a structurally low rate). When measured properly, Class A holders are better off in the Up-C than in an equivalent C-Corp.
B17: KEY RISKS
B18: Endeavor unit exchange | C18: Would activate dormant TRA (85% of step-up benefits payable to Endeavor). Silver Lake control + dormant TRA since Sept 2023 closing argue this is unlikely near-term.
B19: Effective tax rate normalization | C19: If PubCo's 12.2% rate rises toward 21% (partnership tax reform), bull case compresses. Stress test in 'Sensitivity' tab.
B20: Operating execution | C20: Math depends on Bern's EBT forecast. Revenue shortfalls compress absolute FCF but don't change the per-share STRUCTURAL conclusion.
B22: FIVE KEY FINDINGS (primary-source verified)
B23: 1. Tax Rate = 52.6% per LLC Agreement | C23: Highest marginal NYC/LA individual rate, formulaic per Sec 1.01. Updated from prior 50% assumption.
B24: 2. 12.2% PubCo rate is STRUCTURAL | C24: 10-K Note 15: 11.3pp from 'Partnership Income Not Subject to Tax' — mechanical Up-C feature. Sustainable through FY28E.
B25: 3. TRA confirmed dormant | C25: No TRA disclosure in 10-K Note 15. No payments, no liability, no triggers since Sept 2023 closing.
B26: 4. Tax distributions pro-rata | C26: Per LLC Agreement Sec 5.03(e)(i). PubCo receives its share alongside Endeavor's — only Endeavor's share leaves consolidated.
B27: 5. Quarterly dividend is Excluded Distribution | C27: Per LLC Agreement Sec 1.01. Does NOT reduce Endeavor's tax distribution entitlement — Endeavor gets both.

Sheet Sensitivity
B2: SENSITIVITY — Up-C as % of C-Corp comparable
B3: Two-variable stress test: PubCo effective tax rate × Tax distribution rate (FY26E)
B5: All values show: (TRUE PubCo FCF/Class A) / (C-Corp FCF/diluted) for FY26E
B7: FY26E SENSITIVITY: % of C-Corp comparable
D8: Tax Distribution Rate →
B9: PubCo eff. tax rate ↓ | C9: 0.45 | D9: 0.5 | E9: 0.526 | F9: 0.55 | G9: 0.6
B10: 0.08 | C10: =IFERROR((((Inputs!$C$6 * ('[BERN_TKO.xlsx]CFS'!BL56 + '[BERN_TKO.xlsx]IS'!BL17)) - (0.08 * Inputs!$C$6 * '[BERN_TKO.xlsx]IS'!BL15)) / '[BERN_TKO.xlsx]IS'!BL28)/(('[BERN_TKO.xlsx]IS'!BL15*(1-Inputs!$C$9) + ('[BERN_TKO.xlsx]CFS'!BL56 + '[BERN_TKO.xlsx]IS'!BL17 - '[BERN_TKO.xlsx]IS'!BL15)) / '[BERN_TKO.xlsx]IS'!BL29),0) | D10: =IFERROR((((Inputs!$C$6 * ('[BERN_TKO.xlsx]CFS'!BL56 + '[BERN_TKO.xlsx]IS'!BL17)) - (0.08 * Inputs!$C$6 * '[BERN_TKO.xlsx]IS'!BL15)) / '[BERN_TKO.xlsx]IS'!BL28)/(('[BERN_TKO.xlsx]IS'!BL15*(1-Inputs!$C$9) + ('[BERN_TKO.xlsx]CFS'!BL56 + '[BERN_TKO.xlsx]IS'!BL17 - '[BERN_TKO.xlsx]IS'!BL15)) / '[BERN_TKO.xlsx]IS'!BL29),0) | E10: =IFERROR((((Inputs!$C$6 * ('[BERN_TKO.xlsx]CFS'!BL56 + '[BERN_TKO.xlsx]IS'!BL17)) - (0.08 * Inputs!$C$6 * '[BERN_TKO.xlsx]IS'!BL15)) / '[BERN_TKO.xlsx]IS'!BL28)/(('[BERN_TKO.xlsx]IS'!BL15*(1-Inputs!$C$9) + ('[BERN_TKO.xlsx]CFS'!BL56 + '[BERN_TKO.xlsx]IS'!BL17 - '[BERN_TKO.xlsx]IS'!BL15)) / '[BERN_TKO.xlsx]IS'!BL29),0) | F10: =IFERROR((((Inputs!$C$6 * ('[BERN_TKO.xlsx]CFS'!BL56 + '[BERN_TKO.xlsx]IS'!BL17)) - (0.08 * Inputs!$C$6 * '[BERN_TKO.xlsx]IS'!BL15)) / '[BERN_TKO.xlsx]IS'!BL28)/(('[BERN_TKO.xlsx]IS'!BL15*(1-Inputs!$C$9) + ('[BERN_TKO.xlsx]CFS'!BL56 + '[BERN_TKO.xlsx]IS'!BL17 - '[BERN_TKO.xlsx]IS'!BL15)) / '[BERN_TKO.xlsx]IS'!BL29),0) | G10: =IFERROR((((Inputs!$C$6 * ('[BERN_TKO.xlsx]CFS'!BL56 + '[BERN_TKO.xlsx]IS'!BL17)) - (0.08 * Inputs!$C$6 * '[BERN_TKO.xlsx]IS'!BL15)) / '[BERN_TKO.xlsx]IS'!BL28)/(('[BERN_TKO.xlsx]IS'!BL15*(1-Inputs!$C$9) + ('[BERN_TKO.xlsx]CFS'!BL56 + '[BERN_TKO.xlsx]IS'!BL17 - '[BERN_TKO.xlsx]IS'!BL15)) / '[BERN_TKO.xlsx]IS'!BL29),0)
B11: 0.12 | C11: =IFERROR((((Inputs!$C$6 * ('[BERN_TKO.xlsx]CFS'!BL56 + '[BERN_TKO.xlsx]IS'!BL17)) - (0.12 * Inputs!$C$6 * '[BERN_TKO.xlsx]IS'!BL15)) / '[BERN_TKO.xlsx]IS'!BL28)/(('[BERN_TKO.xlsx]IS'!BL15*(1-Inputs!$C$9) + ('[BERN_TKO.xlsx]CFS'!BL56 + '[BERN_TKO.xlsx]IS'!BL17 - '[BERN_TKO.xlsx]IS'!BL15)) / '[BERN_TKO.xlsx]IS'!BL29),0) | D11: =IFERROR((((Inputs!$C$6 * ('[BERN_TKO.xlsx]CFS'!BL56 + '[BERN_TKO.xlsx]IS'!BL17)) - (0.12 * Inputs!$C$6 * '[BERN_TKO.xlsx]IS'!BL15)) / '[BERN_TKO.xlsx]IS'!BL28)/(('[BERN_TKO.xlsx]IS'!BL15*(1-Inputs!$C$9) + ('[BERN_TKO.xlsx]CFS'!BL56 + '[BERN_TKO.xlsx]IS'!BL17 - '[BERN_TKO.xlsx]IS'!BL15)) / '[BERN_TKO.xlsx]IS'!BL29),0) | E11: =IFERROR((((Inputs!$C$6 * ('[BERN_TKO.xlsx]CFS'!BL56 + '[BERN_TKO.xlsx]IS'!BL17)) - (0.12 * Inputs!$C$6 * '[BERN_TKO.xlsx]IS'!BL15)) / '[BERN_TKO.xlsx]IS'!BL28)/(('[BERN_TKO.xlsx]IS'!BL15*(1-Inputs!$C$9) + ('[BERN_TKO.xlsx]CFS'!BL56 + '[BERN_TKO.xlsx]IS'!BL17 - '[BERN_TKO.xlsx]IS'!BL15)) / '[BERN_TKO.xlsx]IS'!BL29),0) | F11: =IFERROR((((Inputs!$C$6 * ('[BERN_TKO.xlsx]CFS'!BL56 + '[BERN_TKO.xlsx]IS'!BL17)) - (0.12 * Inputs!$C$6 * '[BERN_TKO.xlsx]IS'!BL15)) / '[BERN_TKO.xlsx]IS'!BL28)/(('[BERN_TKO.xlsx]IS'!BL15*(1-Inputs!$C$9) + ('[BERN_TKO.xlsx]CFS'!BL56 + '[BERN_TKO.xlsx]IS'!BL17 - '[BERN_TKO.xlsx]IS'!BL15)) / '[BERN_TKO.xlsx]IS'!BL29),0) | G11: =IFERROR((((Inputs!$C$6 * ('[BERN_TKO.xlsx]CFS'!BL56 + '[BERN_TKO.xlsx]IS'!BL17)) - (0.12 * Inputs!$C$6 * '[BERN_TKO.xlsx]IS'!BL15)) / '[BERN_TKO.xlsx]IS'!BL28)/(('[BERN_TKO.xlsx]IS'!BL15*(1-Inputs!$C$9) + ('[BERN_TKO.xlsx]CFS'!BL56 + '[BERN_TKO.xlsx]IS'!BL17 - '[BERN_TKO.xlsx]IS'!BL15)) / '[BERN_TKO.xlsx]IS'!BL29),0)
B12: 0.15 | C12: =IFERROR((((Inputs!$C$6 * ('[BERN_TKO.xlsx]CFS'!BL56 + '[BERN_TKO.xlsx]IS'!BL17)) - (0.15 * Inputs!$C$6 * '[BERN_TKO.xlsx]IS'!BL15)) / '[BERN_TKO.xlsx]IS'!BL28)/(('[BERN_TKO.xlsx]IS'!BL15*(1-Inputs!$C$9) + ('[BERN_TKO.xlsx]CFS'!BL56 + '[BERN_TKO.xlsx]IS'!BL17 - '[BERN_TKO.xlsx]IS'!BL15)) / '[BERN_TKO.xlsx]IS'!BL29),0) | D12: =IFERROR((((Inputs!$C$6 * ('[BERN_TKO.xlsx]CFS'!BL56 + '[BERN_TKO.xlsx]IS'!BL17)) - (0.15 * Inputs!$C$6 * '[BERN_TKO.xlsx]IS'!BL15)) / '[BERN_TKO.xlsx]IS'!BL28)/(('[BERN_TKO.xlsx]IS'!BL15*(1-Inputs!$C$9) + ('[BERN_TKO.xlsx]CFS'!BL56 + '[BERN_TKO.xlsx]IS'!BL17 - '[BERN_TKO.xlsx]IS'!BL15)) / '[BERN_TKO.xlsx]IS'!BL29),0) | E12: =IFERROR((((Inputs!$C$6 * ('[BERN_TKO.xlsx]CFS'!BL56 + '[BERN_TKO.xlsx]IS'!BL17)) - (0.15 * Inputs!$C$6 * '[BERN_TKO.xlsx]IS'!BL15)) / '[BERN_TKO.xlsx]IS'!BL28)/(('[BERN_TKO.xlsx]IS'!BL15*(1-Inputs!$C$9) + ('[BERN_TKO.xlsx]CFS'!BL56 + '[BERN_TKO.xlsx]IS'!BL17 - '[BERN_TKO.xlsx]IS'!BL15)) / '[BERN_TKO.xlsx]IS'!BL29),0) | F12: =IFERROR((((Inputs!$C$6 * ('[BERN_TKO.xlsx]CFS'!BL56 + '[BERN_TKO.xlsx]IS'!BL17)) - (0.15 * Inputs!$C$6 * '[BERN_TKO.xlsx]IS'!BL15)) / '[BERN_TKO.xlsx]IS'!BL28)/(('[BERN_TKO.xlsx]IS'!BL15*(1-Inputs!$C$9) + ('[BERN_TKO.xlsx]CFS'!BL56 + '[BERN_TKO.xlsx]IS'!BL17 - '[BERN_TKO.xlsx]IS'!BL15)) / '[BERN_TKO.xlsx]IS'!BL29),0) | G12: =IFERROR((((Inputs!$C$6 * ('[BERN_TKO.xlsx]CFS'!BL56 + '[BERN_TKO.xlsx]IS'!BL17)) - (0.15 * Inputs!$C$6 * '[BERN_TKO.xlsx]IS'!BL15)) / '[BERN_TKO.xlsx]IS'!BL28)/(('[BERN_TKO.xlsx]IS'!BL15*(1-Inputs!$C$9) + ('[BERN_TKO.xlsx]CFS'!BL56 + '[BERN_TKO.xlsx]IS'!BL17 - '[BERN_TKO.xlsx]IS'!BL15)) / '[BERN_TKO.xlsx]IS'!BL29),0)
B13: 0.2 | C13: =IFERROR((((Inputs!$C$6 * ('[BERN_TKO.xlsx]CFS'!BL56 + '[BERN_TKO.xlsx]IS'!BL17)) - (0.2 * Inputs!$C$6 * '[BERN_TKO.xlsx]IS'!BL15)) / '[BERN_TKO.xlsx]IS'!BL28)/(('[BERN_TKO.xlsx]IS'!BL15*(1-Inputs!$C$9) + ('[BERN_TKO.xlsx]CFS'!BL56 + '[BERN_TKO.xlsx]IS'!BL17 - '[BERN_TKO.xlsx]IS'!BL15)) / '[BERN_TKO.xlsx]IS'!BL29),0) | D13: =IFERROR((((Inputs!$C$6 * ('[BERN_TKO.xlsx]CFS'!BL56 + '[BERN_TKO.xlsx]IS'!BL17)) - (0.2 * Inputs!$C$6 * '[BERN_TKO.xlsx]IS'!BL15)) / '[BERN_TKO.xlsx]IS'!BL28)/(('[BERN_TKO.xlsx]IS'!BL15*(1-Inputs!$C$9) + ('[BERN_TKO.xlsx]CFS'!BL56 + '[BERN_TKO.xlsx]IS'!BL17 - '[BERN_TKO.xlsx]IS'!BL15)) / '[BERN_TKO.xlsx]IS'!BL29),0) | E13: =IFERROR((((Inputs!$C$6 * ('[BERN_TKO.xlsx]CFS'!BL56 + '[BERN_TKO.xlsx]IS'!BL17)) - (0.2 * Inputs!$C$6 * '[BERN_TKO.xlsx]IS'!BL15)) / '[BERN_TKO.xlsx]IS'!BL28)/(('[BERN_TKO.xlsx]IS'!BL15*(1-Inputs!$C$9) + ('[BERN_TKO.xlsx]CFS'!BL56 + '[BERN_TKO.xlsx]IS'!BL17 - '[BERN_TKO.xlsx]IS'!BL15)) / '[BERN_TKO.xlsx]IS'!BL29),0) | F13: =IFERROR((((Inputs!$C$6 * ('[BERN_TKO.xlsx]CFS'!BL56 + '[BERN_TKO.xlsx]IS'!BL17)) - (0.2 * Inputs!$C$6 * '[BERN_TKO.xlsx]IS'!BL15)) / '[BERN_TKO.xlsx]IS'!BL28)/(('[BERN_TKO.xlsx]IS'!BL15*(1-Inputs!$C$9) + ('[BERN_TKO.xlsx]CFS'!BL56 + '[BERN_TKO.xlsx]IS'!BL17 - '[BERN_TKO.xlsx]IS'!BL15)) / '[BERN_TKO.xlsx]IS'!BL29),0) | G13: =IFERROR((((Inputs!$C$6 * ('[BERN_TKO.xlsx]CFS'!BL56 + '[BERN_TKO.xlsx]IS'!BL17)) - (0.2 * Inputs!$C$6 * '[BERN_TKO.xlsx]IS'!BL15)) / '[BERN_TKO.xlsx]IS'!BL28)/(('[BERN_TKO.xlsx]IS'!BL15*(1-Inputs!$C$9) + ('[BERN_TKO.xlsx]CFS'!BL56 + '[BERN_TKO.xlsx]IS'!BL17 - '[BERN_TKO.xlsx]IS'!BL15)) / '[BERN_TKO.xlsx]IS'!BL29),0)
B14: 0.25 | C14: =IFERROR((((Inputs!$C$6 * ('[BERN_TKO.xlsx]CFS'!BL56 + '[BERN_TKO.xlsx]IS'!BL17)) - (0.25 * Inputs!$C$6 * '[BERN_TKO.xlsx]IS'!BL15)) / '[BERN_TKO.xlsx]IS'!BL28)/(('[BERN_TKO.xlsx]IS'!BL15*(1-Inputs!$C$9) + ('[BERN_TKO.xlsx]CFS'!BL56 + '[BERN_TKO.xlsx]IS'!BL17 - '[BERN_TKO.xlsx]IS'!BL15)) / '[BERN_TKO.xlsx]IS'!BL29),0) | D14: =IFERROR((((Inputs!$C$6 * ('[BERN_TKO.xlsx]CFS'!BL56 + '[BERN_TKO.xlsx]IS'!BL17)) - (0.25 * Inputs!$C$6 * '[BERN_TKO.xlsx]IS'!BL15)) / '[BERN_TKO.xlsx]IS'!BL28)/(('[BERN_TKO.xlsx]IS'!BL15*(1-Inputs!$C$9) + ('[BERN_TKO.xlsx]CFS'!BL56 + '[BERN_TKO.xlsx]IS'!BL17 - '[BERN_TKO.xlsx]IS'!BL15)) / '[BERN_TKO.xlsx]IS'!BL29),0) | E14: =IFERROR((((Inputs!$C$6 * ('[BERN_TKO.xlsx]CFS'!BL56 + '[BERN_TKO.xlsx]IS'!BL17)) - (0.25 * Inputs!$C$6 * '[BERN_TKO.xlsx]IS'!BL15)) / '[BERN_TKO.xlsx]IS'!BL28)/(('[BERN_TKO.xlsx]IS'!BL15*(1-Inputs!$C$9) + ('[BERN_TKO.xlsx]CFS'!BL56 + '[BERN_TKO.xlsx]IS'!BL17 - '[BERN_TKO.xlsx]IS'!BL15)) / '[BERN_TKO.xlsx]IS'!BL29),0) | F14: =IFERROR((((Inputs!$C$6 * ('[BERN_TKO.xlsx]CFS'!BL56 + '[BERN_TKO.xlsx]IS'!BL17)) - (0.25 * Inputs!$C$6 * '[BERN_TKO.xlsx]IS'!BL15)) / '[BERN_TKO.xlsx]IS'!BL28)/(('[BERN_TKO.xlsx]IS'!BL15*(1-Inputs!$C$9) + ('[BERN_TKO.xlsx]CFS'!BL56 + '[BERN_TKO.xlsx]IS'!BL17 - '[BERN_TKO.xlsx]IS'!BL15)) / '[BERN_TKO.xlsx]IS'!BL29),0) | G14: =IFERROR((((Inputs!$C$6 * ('[BERN_TKO.xlsx]CFS'!BL56 + '[BERN_TKO.xlsx]IS'!BL17)) - (0.25 * Inputs!$C$6 * '[BERN_TKO.xlsx]IS'!BL15)) / '[BERN_TKO.xlsx]IS'!BL28)/(('[BERN_TKO.xlsx]IS'!BL15*(1-Inputs!$C$9) + ('[BERN_TKO.xlsx]CFS'!BL56 + '[BERN_TKO.xlsx]IS'!BL17 - '[BERN_TKO.xlsx]IS'!BL15)) / '[BERN_TKO.xlsx]IS'!BL29),0)
B17: INTERPRETATION
B18: Key insight: distribution rate has NO effect on TRUE PubCo / C-Corp ratio.
B19: This is because: (1) PubCo receives its pro-rata share alongside Endeavor's, and (2) the Endeavor distribution is Endeavor's economic share regardless. The ratio is invariant to the distribution rate within the LLC Agreement framework. What matters is the gap between PubCo's effective tax rate (12.2% structural) and the C-Corp rate (25%).
B21: Breakpoint analysis:
B22: • At 8% PubCo rate: ~131% of C-Corp (very bull)
B23: • At 12% PubCo rate (current actual): ~121% of C-Corp (base case)
B24: • At 15% PubCo rate: ~115% of C-Corp
B25: • At 20% PubCo rate: ~106% of C-Corp
B26: • At 25% PubCo rate: ~98% of C-Corp (breakeven — Up-C provides no advantage)
