Workbook

Sheet Read-Me
B2: TKO FIP Build-Up Model: Bridging Mgmt Guidance from $240M (2026) to $400M (2030)
B3: Source data and methodology behind the model
B5: What is FIP?
B6: Financial Incentive Package. Mark Shapiro reframed the language during the 4Q25 earnings call. "Site fees" became "FIPs" reflecting that deals now include cash, government subsidies, and value-in-kind support. Roughly half of marquee UFC and WWE events in 2025 were supported by meaningful FIPs.
B8: Management guidance (set Q4 2025, reaffirmed 1Q26)
B9: 2026 aggregate FIP: over $300M (one-time-heavy)
B10: 2026 normalized FIP: ~$240M
B11: Long-term target: $380M to $420M by 2030
B12: Implied 2026-2030 CAGR (normalized base to midpoint): ~14%
B14: Per-event economics used in this model
B15: WWE Saudi PLE (Crown Jewel/Night of Champions/etc): $55M (Wrestlenomics, Meltzer)
B16: WWE Royal Rumble Saudi: $50M (1Q26 confirmed via $47M YoY uplift in WWE live events rev)
... B40: Bull: $480M+. WrestleMania annual Saudi from 2028, Singapore comes online, premium FIPs creep into weekly TV tapings

Sheet Event Inventory
A1: TKO FIP Event Inventory: 2025 Actual to 2030 Modeled
A2: Per-event $M FIP value by year. Confirmed events in blue (input). Modeled events follow scenario assumptions.
A4: Property | B4: Event | C4: Type | D4: 2025 | E4: 2026 | F4: 2027 | G4: 2028 | H4: 2029 | I4: 2030
A5: WWE | B5: Royal Rumble Saudi (2026 confirmed) | C5: PLE | E5: 50
A6: WWE | B6: Night of Champions Saudi (annual) | C6: PLE | D6: 50 | E6: 55 | F6: 55 | G6: 58 | H6: 60 | I6: 62
A7: WWE | B7: Crown Jewel Saudi (annual ex-2025) | C7: PLE | E7: 55 | F7: 55 | G7: 58 | H7: 60 | I7: 62
A8: WWE | B8: WrestleMania 43 Saudi (one-time 2027) | C8: Mega | F8: 200
A9: WWE | B9: Third Saudi PLE (post-WM cadence) | C9: PLE | F9: 55 | G9: 60 | H9: 62 | I9: 65
A10: WWE | B10: Australia (Crown Jewel Perth, etc) | C10: PLE | D10: 30 | G10: 30 | I10: 30
A11: WWE | B11: Italy/Europe PLE (Clash in Italy etc) | C11: PLE | E11: 15 | F11: 15 | G11: 18 | H11: 20 | I11: 20
A12: UFC | B12: Riyadh Season Fight Night | C12: Fight Night | D12: 20 | E12: 20 | F12: 22 | G12: 24 | H12: 25 | I12: 26
A13: UFC | B13: Saudi numbered card (occasional) | C13: Numbered | F13: 25 | H13: 30
A14: UFC | B14: Abu Dhabi Fight Night #1 (DCT) | C14: Fight Night | D14: 20 | E14: 22 | F14: 24 | G14: 26 | H14: 28 | I14: 30
A15: UFC | B15: Abu Dhabi Fight Night #2 (DCT) | C15: Fight Night | D15: 20 | E15: 22 | F15: 24 | G15: 26 | H15: 28 | I15: 30
A16: UFC | B16: Australia (NSW deal) | C16: Fight Night | D16: 5 | E16: 5 | F16: 6 | G16: 6 | H16: 7 | I16: 7
A17: UFC | B17: Mexico/LatAm site fees | C17: Fight Night | F17: 5 | G17: 6 | H17: 7 | I17: 8
A18: UFC | B18: UK/Europe site fees | C18: Fight Night | F18: 5 | G18: 6 | H18: 8 | I18: 10
A19: UFC | B19: Asia (Singapore/Japan) ramp | C19: Fight Night | G19: 8 | H19: 12 | I19: 16
A20: Boxing | B20: Zuffa Boxing Saudi inaugural (2026) | C20: Mega card | E20: 30 | F20: 35 | G20: 40 | H20: 40 | I20: 40
A21: Boxing | B21: Zuffa Boxing additional Saudi card | C21: Mega card | F21: 25 | G21: 30 | H21: 35 | I21: 40
A22: UFC | B22: White House Freedom 250 (1x 2026) | C22: Mega | E22: 30
A23: WWE | B23: WWE TV taping FIPs (premium markets) | C23: TV | G23: 5 | H23: 10 | I23: 15
A25: SUBTOTAL BY CATEGORY
B26: WWE subtotal | D26: =SUM(D5,D6,D7,D8,D9,D10,D11,D23) -> 80 | E26: =SUM(E5,E6,E7,E8,E9,E10,E11,E23) -> 175 | F26: =SUM(F5,F6,F7,F8,F9,F10,F11,F23) -> 380 | G26: =SUM(G5,G6,G7,G8,G9,G10,G11,G23) -> 229 | H26: =SUM(H5,H6,H7,H8,H9,H10,H11,H23) -> 212 | I26: =SUM(I5,I6,I7,I8,I9,I10,I11,I23) -> 254
B27: UFC subtotal | D27: =SUM(D12,D13,D14,D15,D16,D17,D18,D19,D22) -> 65 | E27: =SUM(E12,E13,E14,E15,E16,E17,E18,E19,E22) -> 99 | F27: =SUM(F12,F13,F14,F15,F16,F17,F18,F19,F22) -> 111 | G27: =SUM(G12,G13,G14,G15,G16,G17,G18,G19,G22) -> 102 | H27: =SUM(H12,H13,H14,H15,H16,H17,H18,H19,H22) -> 145 | I27: =SUM(I12,I13,I14,I15,I16,I17,I18,I19,I22) -> 127
B28: Boxing subtotal | D28: =SUM(D20,D21) -> 0 | E28: =SUM(E20,E21) -> 30 | F28: =SUM(F20,F21) -> 60 | G28: =SUM(G20,G21) -> 70 | H28: =SUM(H20,H21) -> 75 | I28: =SUM(I20,I21) -> 80
B30: TOTAL FIP (BASE CASE) | D30: =SUM(D26:D28) -> 145 | E30: =SUM(E26:E28) -> 304 | F30: =SUM(F26:F28) -> 551 | G30: =SUM(G26:G28) -> 401 | H30: =SUM(H26:H28) -> 432 | I30: =SUM(I26:I28) -> 461
B32: Mgmt 2026 normalized: ~$240M | 2026 aggregate: $300M+ | 2030 target: $380-420M
B33: Base case ties: 2026 ~$300M (with one-times); 2030 ~$400M (mgmt midpoint)

Sheet Build-Up by Property
A1: FIP Build-Up by Property: WWE / UFC / Zuffa Boxing
A2: Year-over-year FIP totals by property and growth contribution
A4: Property | B4: 2025 | C4: 2026 | D4: 2027 | E4: 2028 | F4: 2029 | G4: 2030 | H4: 5-yr CAGR
A5: WWE | B5: ='Event Inventory'!D26 -> 80 | C5: ='Event Inventory'!E26 -> 175 | D5: ='Event Inventory'!F26 -> 380 | E5: ='Event Inventory'!G26 -> 229 | F5: ='Event Inventory'!H26 -> 212 | G5: ='Event Inventory'!I26 -> 254 | H5: =IFERROR((G5/B5)^(1/5)-1,"") -> 0.25993676
A6: UFC | B6: ='Event Inventory'!D27 -> 65 | C6: ='Event Inventory'!E27 -> 99 | D6: ='Event Inventory'!F27 -> 111 | E6: ='Event Inventory'!G27 -> 102 | F6: ='Event Inventory'!H27 -> 145 | G6: ='Event Inventory'!I27 -> 127 | H6: =IFERROR((G6/B6)^(1/5)-1,"") -> 0.14334704
A7: Zuffa Boxing | B7: ='Event Inventory'!D28 -> 0 | C7: ='Event Inventory'!E28 -> 30 | D7: ='Event Inventory'!F28 -> 60 | E7: ='Event Inventory'!G28 -> 70 | F7: ='Event Inventory'!H28 -> 75 | G7: ='Event Inventory'!I28 -> 80
A8: TOTAL FIP | B8: =SUM(B5:B7) -> 145 | C8: =SUM(C5:C7) -> 304 | D8: =SUM(D5:D7) -> 551 | E8: =SUM(E5:E7) -> 401 | F8: =SUM(F5:F7) -> 432 | G8: =SUM(G5:G7) -> 461 | H8: =IFERROR((G8/B8)^(1/5)-1,"") -> 0.26027867
A10: Mgmt 2026 normalized | C10: 240 | H10: guidance
A11: Mgmt 2030 target (low) | G11: 380 | H11: guidance
A12: Mgmt 2030 target (high) | G12: 420 | H12: guidance
A14: vs Mgmt 2030 midpoint ($400M) | G14: =G8-400 -> 61
A15: Implied % vs midpoint | G15: =G8/400-1 -> 0.1525

Sheet Comp Benchmarks
A1: FIP/Site Fee Comp Benchmarks (Per-Event Economics)
A2: External comparable site fees / hosting fees to sanity-check TKO unit economics
A4: Property | B4: Event Type | C4: Frequency | D4: Per-Event $M | E4: Total $M/Yr | F4: Source
A5: F1 Saudi Arabia GP | B5: F1 race hosting fee | C5: 1x/yr | D5: 55 | E5: 55 | F5: Total Motorsport, Yahoo Sports
A6: F1 Qatar GP | B6: F1 race hosting fee | C6: 1x/yr | D6: 55 | E6: 55 | F6: 10-yr deal $550M total (2023-32)
A7: F1 Abu Dhabi GP | B7: F1 race hosting fee | C7: 1x/yr | D7: 42 | E7: 42 | F7: Total Motorsport
A8: F1 Bahrain GP | B8: F1 race hosting fee | C8: 1x/yr | D8: 45 | E8: 45 | F8: Yahoo Sports
A9: F1 Aramco global sponsor | B9: Title sponsor | C9: Annual | E9: 47 | F9: 10-yr deal $450M total
A10: LIV Golf | B10: Tournament series | C10: Multi/yr | E10: 1000 | F10: PIF spent $5B+ over 5 years; cut after 2026
A11: WWE Saudi PLE (historical) | B11: Premium Live Event | C11: ~2x/yr | D11: 55 | E11: 110 | F11: Wrestlenomics, Meltzer
A12: WWE WrestleMania Saudi 2027 | B12: Mega event | C12: 1x | D12: 200 | E12: 200 | F12: Yahoo Sports, industry est ($150-250M range)
A13: UFC Saudi Fight Night | B13: Numbered/FN | C13: 1-2x/yr | D13: 25 | E13: 25 | F13: UFC COO commentary
A14: UFC Abu Dhabi | B14: Numbered/FN | C14: 2x/yr DCT | D14: 22 | E14: 44 | F14: Old reports
A15: UFC Australia (NSW) | B15: Fight Night | C15: 1x/yr (3-yr deal) | D15: 5 | E15: 5 | F15: $16M / 3 years
A16: Boxing Riyadh card (Fury-Usyk) | B16: Mega event | C16: ~Annual | D16: 100 | E16: 100 | F16: Industry estimates
A18: Key takeaway
A19: F1 hosting fees of $42-55M map almost 1:1 to WWE Saudi PLE economics ($50-55M). WrestleMania at $200M is ~3.5x F1. Validates per-event assumptions.

Sheet Scenarios
A1: Three Scenarios: Bear / Base / Bull
A2: Each scenario starts from same 2026 base and diverges based on key assumptions
A4: Scenario | B4: 2025 | C4: 2026 | D4: 2027 | E4: 2028 | F4: 2029 | G4: 2030 | H4: Notes
A5: Bear case | B5: 180 | C5: 270 | D5: 380 | E5: 280 | F5: 250 | G5: 230 | H5: Saudi cuts post-WM 43; no expansion
A6: Base case (matches mgmt) | B6: ='Event Inventory'!D30 -> 145 | C6: ='Event Inventory'!E30 -> 304 | D6: ='Event Inventory'!F30 -> 551 | E6: ='Event Inventory'!G30 -> 401 | F6: ='Event Inventory'!H30 -> 432 | G6: ='Event Inventory'!I30 -> 461 | H6: Mgmt $400M target by 2030
A7: Bull case | B7: 200 | C7: 320 | D7: 460 | E7: 470 | F7: 510 | G7: 560 | H7: Annual WM Saudi + Singapore + premium TV
A9: 5-yr CAGR (2025 to 2030)
A10: Bear CAGR | B10: =(G5/B5)^(1/5)-1 -> 0.050246073
A11: Base CAGR | B11: =(G6/B6)^(1/5)-1 -> 0.26027867
A12: Bull CAGR | B12: =(G7/B7)^(1/5)-1 -> 0.22865968
A14: EV impact at 14x EBITDA multiple | H14: Assumes 95% of FIP flows to EBITDA
A15: 2030 FIP EV contribution at 14x EBITDA | B15: =G5*0.95*14 -> 3059 | C15: =G6*0.95*14 -> 6131.3 | D15: =G7*0.95*14 -> 7448
A16: Labels | B16: Bear | C16: Base | D16: Bull
A19: Sensitivity Table: 2030 FIP ($M) by Key Drivers
A20: Rows: WrestleMania Saudi cadence | Cols: UFC intl FIP per Fight Night
B22: Low ($15M) | C22: Mid ($22M) | D22: High ($30M)
A23: Biennial (every 2 yrs) | B23: 470 | C23: 512 | D23: 560
A24: Annual | B24: 570 | C24: 612 | D24: 660
A25: Annual + UAE second mega | B25: 650 | C25: 692 | D25: 740

Sheet Assumptions
A1: Key Model Assumptions
A2: Drivers and assumptions behind the FIP build-up. Adjust to test scenarios.
A4: Assumption | B4: Value | C4: Rationale / Source
A5: WWE Saudi PLE base FIP ($M/event) | B5: 55 | C5: Wrestlenomics: $600M earned 2018-mid 2025 across 12 events. Meltzer cited $55M/event
A6: WWE Royal Rumble Saudi 2026 FIP ($M) | B6: 50 | C6: 1Q26 print: WWE LE&H +$47M YoY; only variable was RR moving from US to Saudi
A7: WWE WrestleMania Saudi 2027 FIP ($M) | B7: 200 | C7: Yahoo Sports speculation $150-250M; Vegas alt = $40M baseline; Saudi premium 4-6x
A8: UFC Saudi numbered card FIP ($M) | B8: 25 | C8: UFC COO Lawrence Epstein historical commentary. Riyadh Season UFC partnership 2024-25
A9: UFC Abu Dhabi FIP ($M/event) | B9: 22 | C9: DCT Abu Dhabi 5-yr deal. ~$25M/event historically per legacy reporting
A10: UFC Australia NSW FIP ($M/event) | B10: 5 | C10: $16M / 3 years split across 1 event each year
A11: Zuffa Boxing Saudi inaugural FIP ($M) | B11: 30 | C11: GEA + Sela multi-year deal. Inaugural lower then ramps
A12: Zuffa Boxing 2030 mature ($M/event) | B12: 70 | C12: Mature card economics target. Below WM but above UFC
A13: UFC intl Fight Night FIP ($M base case) | B13: 22 | C13: Mid-case for international site fees ex-AbuDhabi/Saudi
A14: Saudi WWE event count 2026 | B14: 3 | C14: Confirmed: Royal Rumble (Jan), Night of Champions (June), TBA (Nov)
A15: Saudi WWE event count 2027 | B15: 4-5 | C15: WrestleMania 43 + 3 PLEs + potentially other
A16: Mgmt 2026 normalized FIP ($M) | B16: 240 | C16: Mark Shapiro 4Q25 call
A17: Mgmt 2030 target FIP midpoint ($M) | B17: 400 | C17: Mark Shapiro 4Q25 call ($380-420M range)
A18: Implied 2026-2030 CAGR | B18: 14% | C18: Calculated from $240M → $400M over 4 yrs
A19: FIP-to-EBITDA flow-through | B19: 95% | C19: FIPs are mostly cash with negligible incremental cost (event production sunk)
A20: TKO trading EV/2026E EBITDA | B20: ~14x | C20: Per analyst consensus, used for EV impact translation

Sheet Mgmt Bridge
A1: Bridge: My Model vs Management Guidance
A2: Walking from $240M (2026 normalized) to $400M (2030 midpoint)
A4: Component | B4: $M | C4: Note
A5: 2026 normalized FIP (mgmt guidance) | B5: 240 | C5: Starting point per Mark Shapiro 4Q25 call
A6: + Saudi PLE FIP escalation (escalators on existing 3-PLE cadence) | B6: 20 | C6: Per-event $55M to $60-62M with annual 3-5% escalators
A7: + Zuffa Boxing run-rate scale ($30M inaugural to $80M run-rate) | B7: 50 | C7: New product line ramping with multi-year ME deal in place
A8: + UFC intl market expansion (Asia/LatAm/Europe new sites) | B8: 50 | C8: Per Shapiro JPM 2024: pursuing FIPs in UK, Mexico, Singapore
A9: + UFC FIP escalators (Saudi/Abu Dhabi existing markets pay more) | B9: 20 | C9: Annual 3-5% escalation standard in sports hosting deals
A10: + Premium WWE TV taping FIPs (Raw/SmackDown in tier-1 markets) | B10: 15 | C10: Per Shapiro JPM 2024 commentary on extending FIP model to TV
A11: + Italy/Europe WWE PLE growth (Clash in Italy etc) | B11: 5 | C11: New PLE international cadence introduced 2026
A12: Subtotal: my modeled 2030 FIP (run-rate) | B12: =SUM(B5,B6,B7,B8,B9,B10,B11) -> 400 | C12: SUM of bridge components
A13: Mgmt 2030 midpoint target | B13: 400 | C13: Mark Shapiro 4Q25 call ($380-420M range)
A14: Variance vs mgmt midpoint | B14: =B12-B13 -> 0 | C14: Subtotal minus target
A17: Interpretation
A18: Bridge sums to ~$400M, matching mgmt 2030 midpoint. The lift is achievable through: (1) escalators on existing Saudi/UAE deals, (2) Zuffa Boxing scaling ($50M of bridge), (3) UFC international expansion to untapped markets ($50M). Execution risk concentrated in Zuffa Boxing scaling and Asia rollout.
