Workbook

Sheet Read Me
B2: Vail Resorts (NYSE: MTN) - Estimated Revenue & EBITDA by Resort [v8]
B3: Geographically anchored: Whistler pinned to reported Canada revenue; US residual allocated via NSAA engine
B5: What v8 changes
B6: Skier-visit assumptions are now documented and grounded. Vail does not disclose per-resort visits, so: the North American total is calibrated to Vail's reported ~16.9mm FY2025 skier visits (US + Whistler); flagship resorts are cross-checked against public figures (caution: Whistler's ~2.0mm is WINTER skier visits, not the ~3mm total-visitor figure that includes summer); and the rest are grounded on NSAA Table 1 region x size averages, scaled up because Vail owns the larger areas in each region. A 'Visit Basis' column and a skier-visit reconciliation document every number.
B8: Why it matters
B9: Whistler is the largest single estimate in the model; pinning it to reported data removes that guesswork. It confirms Whistler as the #1 gross-revenue resort (~$320mm) but, after the 25% Nippon Cable interest, still behind Breckenridge and Vail Mountain on revenue attributable to Vail.
B11: Logic recap
B12: Total revenue: anchored resorts take their anchor; the rest share (Total Mountain - anchors) by visits x NSAA annual yield/visit by size x Yield Index. Lift vs non-lift split by NSAA size mix. EBITDA = revenue x NSAA size all-in margin, rescaled to Vail's Mountain EBITDA. 'To Vail' = x ownership %.
B14: Inputs (blue/yellow)
B15: Resort Model: Size (D), Visits (F), Yield Index (G), Anchor Rev (K), Ownership % (W).
B16: Assumptions: Vail revenue by stream, Mountain EBITDA, and the geographic anchors (Canada revenue + BC lodging carve-out).
B18: Caveats
... B26: NSAA Economic Analysis of U.S. Ski Areas, 2024/25 (user-provided): Table 2 (rev/visit by size), Table 3 (region x size EBITDA margins), Table 8.

Sheet Assumptions
A1: ASSUMPTIONS
A2: Fiscal year: | B2: FY2025 | D2: Ended July 31, 2025.
A4: MOUNTAIN SEGMENT REVENUE ($mm) | C4: % total | D4: Source / note
A5: Lift (pass + non-pass) | B5: 1503.2 | C5: =B5/$B$10 -> 0.57158067 | D5: Vail FY2025 8-K: $1,503.2mm.
A6: Ski school | B6: 317 | C6: =B6/$B$10 -> 0.1205369 | D6: Derived +1.7% YoY.
A7: Dining | B7: 239 | C7: =B7/$B$10 -> 0.09087798 | D7: Derived +5.9% YoY.
A8: Retail / rental | B8: 290 | C8: =B8/$B$10 -> 0.11027035 | D8: Estimated FY2025.
A9: Other mountain | B9: 280.7 | C9: =B9/$B$10 -> 0.1067341 | D9: Balancing plug; ties Mountain to reported $2,629.9mm.
A10: Total Mountain revenue | B10: =SUM(B5:B9) -> 2629.9 | C10: =B10/$B$10 -> 1 | D10: Ties to reported FY2025 Mountain net revenue $2,629.9mm.
A11: Non-lift revenue | B11: =SUM(B6:B9) -> 1126.7 | C11: =B11/$B$10 -> 0.42841933
A12: Lift rescale (to tie lift) | B12: =B5/SUMPRODUCT('Resort Model'!$L$4:$L$43,'Resort Model'!$H$4:$H$43/('Resort Model'!$H$4:$H$43+'Resort Model'!$I$4:$I$43)) -> 1.0632849 | D12: Scales the size-mix lift split so total lift ties to reported.
A13: PROFITABILITY
A14: Vail Mountain Reported EBITDA ($mm) | B14: 821.3 | D14: Reported FY2025 Mountain EBITDA (10-K segment table).
A15: Pre-scale modeled EBITDA ($mm) | B15: =SUMPRODUCT('Resort Model'!$L$4:$L$43,'Resort Model'!$T$4:$T$43) -> 888.63762
A16: EBITDA scaling factor | B16: =B14/B15 -> 0.92422376
A18: GEOGRAPHIC ANCHORS ($mm, FY2025 10-K)
A19: Total net revenue (all segments) | B19: 2964.3 | D19: 10-K geographic note.
A20: U.S. net revenue | B20: 2423.2
A21: International net revenue | B21: 541.1
A22: Canada (Whistler) net revenue | B22: 335.3 | D22: All-segment; Whistler is the only Canadian resort.
A23: Intl ex-Canada (AUS + EUR) | B23: =B21-B22 -> 205.8 | D23: Validation target for Australia + Europe.
A24: BC lodging carve-out (est) | B24: 15 | D24: Non-Mountain Canada revenue removed from the Whistler anchor.
A25: Whistler Mountain anchor | B25: =B22-B24 -> 320.3 | D25: Canada revenue less BC lodging. Pinned in the model.

Sheet NSAA Benchmarks
A1: NSAA BENCHMARKS
A2: Economic Analysis of U.S. Ski Areas, 2024/25 (per skier visit).
A4: Table 2C - Revenue per skier visit by SIZE ($) <-- drives revenue weights
A5: Size category | B5: VTF/hr range | C5: Annual rev/visit | D5: Ticket yield | E5: Non-ticket/visit | F5: # areas
A6: Small | B6: 0 - 5,000 | C6: 110.84 | D6: 48.88 | E6: 61.96 | F6: 47
A7: Medium | B7: 5,001 - 9,500 | C7: 116.43 | D7: 59.56 | E7: 57.37 | F7: 32
A8: Large | B8: 9,501 - 20,000 | C8: 119.5 | D8: 66.74 | E8: 52.76 | F8: 36
A9: Extra Large | B9: 20,001 + | C9: 171.89 | D9: 94.3 | E9: 77.59 | F9: 30
A11: Whistler's yield is set by its Canada anchor, not these US benchmarks (NSAA excludes Canada).
A13: Table 1 - Avg downhill visits per ski area by REGION x SIZE band (2024/25)
A14: Region | B14: Size band (VTF/hr 000s) | C14: Avg visits/area | D14: # areas
A15: Rocky Mountain | B15: 0 - 9,500 | C15: 132747 | D15: 13
A16: Rocky Mountain | B16: 9,501 - 20,000 | C16: 379829 | D16: 14
A17: Rocky Mountain | B17: 20,000 + | C17: 994914 | D17: 16
A18: Pacific Southwest | B18: 9,501 - 20,000 | C18: 230387 | D18: 6
A19: Pacific Southwest | B19: 20,001 + | C19: 968100 | D19: 5
A20: Pacific South & NW | B20: 0 - 9,500 | C20: 166903 | D20: 9
A21: Pacific Northwest | B21: 9,501 + | C21: 490792 | D21: 4
A22: Northeast | B22: 0 - 7,500 | C22: 149640 | D22: 6
A23: Northeast | B23: 7,501 - 10,000 | C23: 112966 | D23: 9
A24: Northeast | B24: 10,001 - 20,000 | C24: 224092 | D24: 9
A25: Northeast | B25: 20,001 + | C25: 488626 | D25: 7
A26: Southeast | B26: 0 - 5,000 | C26: 103499 | D26: 13
... A29: Midwest | B29: 3,501 + | C29: 100621 | D29: 11
A31: Vail's resorts sit ABOVE these regional averages (Vail owns the larger areas in each region). Per-resort visits are estimates: flagships cross-checked vs public figures; the rest grounded on these averages; the North American total calibrated to Vail's reported ~16.9mm skier visits.

Sheet NSAA Margins
A1: NSAA EBITDA MARGINS
A2: NSAA 2024/25 Table 3, EBITDA margin by region x size. Drives the EBITDA layer.
A4: EBITDA margin by REGION x SIZE <-- drives EBITDA (relative; portfolio rescales to reported total)
A5: Region | B5: Small | C5: Medium | D5: Large | E5: Extra Large | F5: Basis / note
A6: Rocky Mountain | B6: 0.229 | C6: 0.229 | D6: 0.317 | E6: 0.419 | F6: 0-9.5k / 9.5-20k / 20k+ bands
A7: Pacific Southwest | B7: 0.227 | C7: 0.227 | D7: 0.18 | E7: 0.294 | F7: Tahoe; Large approx (Kirkwood)
A8: Pacific Northwest | B8: 0.233 | C8: 0.233 | D8: 0.233 | E8: 0.233 | F8: 9,501+ band only
A9: Northeast | B9: 0.199 | C9: 0.199 | D9: 0.235 | E9: 0.291 | F9: 0-7.5k / 7.5-10k / 10-20k / 20k+
A10: Southeast | B10: 0.253 | C10: 0.253 | D10: 0.253 | E10: 0.253 | F10: Mid-Atlantic; both bands ~25.3%
A11: Midwest | B11: 0.278 | C11: 0.25 | D11: 0.25 | E11: 0.25 | F11: 0-3,500 band; larger approx
A12: Canada | B12: 0.335 | C12: 0.335 | D12: 0.335 | E12: 0.335 | F12: No NSAA; Whistler blended-XL (editable)
A13: Europe | B13: 0.24 | C13: 0.24 | D13: 0.24 | E13: 0.24 | F13: No NSAA; fallback (editable)
A14: Australia | B14: 0.24 | C14: 0.24 | D14: 0.24 | E14: 0.24 | F14: No NSAA; fallback (editable)
A16: Reference: NSAA Table 3 region x size EBITDA margins are full-entity (after all operating costs, before D&A/interest/tax) - the same concept as Vail's Reported Mountain EBITDA. Values are relative weights; the portfolio is rescaled so total EBITDA equals Vail's reported $821.3mm.

Sheet Resort Model
A1: RESORT MODEL - estimated revenue & EBITDA by resort ($mm, FY2025)
A2: Inputs (blue/yellow): Size (D), Visits (F), Yield Index (G), Anchor Rev (K), Ownership % (W). Orange = to Vail.
A3: Resort | B3: Region | C3: Country | D3: Size Category | E3: Skiable Acres | F3: Est. Skier Visits (000s) | G3: Yield Index | H3: NSAA Ticket Yield ($) | I3: NSAA Non- Ticket ($) | J3: Weight | K3: Anchor Rev ($mm) | L3: Total Rev ($mm) | M3: Lift Rev ($mm) | N3: Non-lift Rev ($mm) | O3: Ski School ($mm) | P3: Dining ($mm) | Q3: Retail/Rent ($mm) | R3: Other ($mm) | S3: Rev/Visit ($) | T3: NSAA Size Margin | U3: Est. EBITDA ($mm) | V3: EBITDA Margin | W3: Owner- ship % | X3: Rev to Vail ($mm) | Y3: EBITDA to Vail ($mm) | Z3: Visit Basis / source
A4: Whistler Blackcomb | B4: Canada | C4: Canada | D4: Extra Large | E4: 8171 | F4: 2050 | G4: 1 | H4: =VLOOKUP(D4,'NSAA Benchmarks'!$A$6:$F$9,4,FALSE()) -> 94.3 | I4: =VLOOKUP(D4,'NSAA Benchmarks'!$A$6:$F$9,5,FALSE()) -> 77.59 | J4: =F4*(H4+I4)*G4 -> 352374.5 | K4: =Assumptions!$B$25 -> 320.3 | L4: =IF(K4>0,K4,J4/SUMIF($K$4:$K$43,0,$J$4:$J$43)*(Assumptions!$B$10-SUM($K$4:$K$43))) -> 320.3 | M4: =L4*H4/(H4+I4)*Assumptions!$B$12 -> 186.83905 | N4: =L4-M4 -> 133.46095 | O4: =N4*Assumptions!$B$6/Assumptions!$B$11 -> 37.549589 | P4: =N4*Assumptions!$B$7/Assumptions!$B$11 -> 28.310258 | Q4: =N4*Assumptions!$B$8/Assumptions!$B$11 -> 34.351359 | R4: =N4*Assumptions!$B$9/Assumptions!$B$11 -> 33.249746 | S4: =IF(F4=0,0,L4*1000/F4) -> 156.2439 | T4: =INDEX('NSAA Margins'!$B$6:$E$14,MATCH(B4,'NSAA Margins'!$A$6:$A$14,0),MATCH(D4,'NSAA Margins'!$B$5:$E$5,0)) -> 0.335 | U4: =L4*T4*Assumptions!$B$16 -> 99.169671 | V4: =IF(L4=0,0,U4/L4) -> 0.30961496 | W4: 0.75 | X4: =L4*W4 -> 240.225 | Y4: =U4*W4 -> 74.377254 | Z4: Public est. (winter skier visits, excl. summer)
A5: Breckenridge | B5: Rocky Mountain | C5: USA | D5: Extra Large | E5: 2908 | F5: 1750 | G5: 1 | H5: =VLOOKUP(D5,'NSAA Benchmarks'!$A$6:$F$9,4,FALSE()) -> 94.3 | I5: =VLOOKUP(D5,'NSAA Benchmarks'!$A$6:$F$9,5,FALSE()) -> 77.59 | J5: =F5*(H5+I5)*G5 -> 300807.5 | K5: 0 | L5: =IF(K5>0,K5,J5/SUMIF($K$4:$K$43,0,$J$4:$J$43)*(Assumptions!$B$10-SUM($K$4:$K$43))) -> 288.56856 | M5: =L5*H5/(H5+I5)*Assumptions!$B$12 -> 168.3293 | N5: =L5-M5 -> 120.23926 | O5: =N5*Assumptions!$B$6/Assumptions!$B$11 -> 33.829631 | P5: =N5*Assumptions!$B$7/Assumptions!$B$11 -> 25.505621 | Q5: =N5*Assumptions!$B$8/Assumptions!$B$11 -> 30.948243 | R5: =N5*Assumptions!$B$9/Assumptions!$B$11 -> 29.955765 | S5: =IF(F5=0,0,L5*1000/F5) -> 164.89632 | T5: =INDEX('NSAA Margins'!$B$6:$E$14,MATCH(B5,'NSAA Margins'!$A$6:$A$14,0),MATCH(D5,'NSAA Margins'!$B$5:$E$5,0)) -> 0.419 | U5: =L5*T5*Assumptions!$B$16 -> 111.7481 | V5: =IF(L5=0,0,U5/L5) -> 0.38724975 | W5: 1 | X5: =L5*W5 -> 288.56856 | Y5: =U5*W5 -> 111.7481 | Z5: Public est. (busiest US resort)
A6: Vail Mountain | B6: Rocky Mountain | C6: USA | D6: Extra Large | E6: 5317 | F6: 1650 | G6: 1 | H6: =VLOOKUP(D6,'NSAA Benchmarks'!$A$6:$F$9,4,FALSE()) -> 94.3 | I6: =VLOOKUP(D6,'NSAA Benchmarks'!$A$6:$F$9,5,FALSE()) -> 77.59 | J6: =F6*(H6+I6)*G6 -> 283618.5 | K6: 0 | L6: =IF(K6>0,K6,J6/SUMIF($K$4:$K$43,0,$J$4:$J$43)*(Assumptions!$B$10-SUM($K$4:$K$43))) -> 272.07893 | M6: =L6*H6/(H6+I6)*Assumptions!$B$12 -> 158.71049 | N6: =L6-M6 -> 113.36844 | O6: =N6*Assumptions!$B$6/Assumptions!$B$11 -> 31.896509 | P6: =N6*Assumptions!$B$7/Assumptions!$B$11 -> 24.048157 | Q6: =N6*Assumptions!$B$8/Assumptions!$B$11 -> 29.179772 | R6: =N6*Assumptions!$B$9/Assumptions!$B$11 -> 28.244007 | S6: =IF(F6=0,0,L6*1000/F6) -> 164.89632 | T6: =INDEX('NSAA Margins'!$B$6:$E$14,MATCH(B6,'NSAA Margins'!$A$6:$A$14,0),MATCH(D6,'NSAA Margins'!$B$5:$E$5,0)) -> 0.419 | U6: =L6*T6*Assumptions!$B$16 -> 105.3625 | V6: =IF(L6=0,0,U6/L6) -> 0.38724975 | W6: 1 | X6: =L6*W6 -> 272.07893 | Y6: =U6*W6 -> 105.3625 | Z6: Public est.
A7: Park City Mountain | B7: Rocky Mountain | C7: USA | D7: Extra Large | E7: 7300 | F7: 1550 | G7: 1 | H7: =VLOOKUP(D7,'NSAA Benchmarks'!$A$6:$F$9,4,FALSE()) -> 94.3 | I7: =VLOOKUP(D7,'NSAA Benchmarks'!$A$6:$F$9,5,FALSE()) -> 77.59 | J7: =F7*(H7+I7)*G7 -> 266429.5 | K7: 0 | L7: =IF(K7>0,K7,J7/SUMIF($K$4:$K$43,0,$J$4:$J$43)*(Assumptions!$B$10-SUM($K$4:$K$43))) -> 255.5893 | M7: =L7*H7/(H7+I7)*Assumptions!$B$12 -> 149.09167 | N7: =L7-M7 -> 106.49763 | O7: =N7*Assumptions!$B$6/Assumptions!$B$11 -> 29.963388 | P7: =N7*Assumptions!$B$7/Assumptions!$B$11 -> 22.590693 | Q7: =N7*Assumptions!$B$8/Assumptions!$B$11 -> 27.411301 | R7: =N7*Assumptions!$B$9/Assumptions!$B$11 -> 26.532249 | S7: =IF(F7=0,0,L7*1000/F7) -> 164.89632 | T7: =INDEX('NSAA Margins'!$B$6:$E$14,MATCH(B7,'NSAA Margins'!$A$6:$A$14,0),MATCH(D7,'NSAA Margins'!$B$5:$E$5,0)) -> 0.419 | U7: =L7*T7*Assumptions!$B$16 -> 98.976893 | V7: =IF(L7=0,0,U7/L7) -> 0.38724975 | W7: 1 | X7: =L7*W7 -> 255.5893 | Y7: =U7*W7 -> 98.976893 | Z7: Public est. (largest US by acreage)
A8: Keystone | B8: Rocky Mountain | C8: USA | D8: Extra Large | E8: 3149 | F8: 1200 | G8: 1 | H8: =VLOOKUP(D8,'NSAA Benchmarks'!$A$6:$F$9,4,FALSE()) -> 94.3 | I8: =VLOOKUP(D8,'NSAA Benchmarks'!$A$6:$F$9,5,FALSE()) -> 77.59 | J8: =F8*(H8+I8)*G8 -> 206268 | K8: 0 | L8: =IF(K8>0,K8,J8/SUMIF($K$4:$K$43,0,$J$4:$J$43)*(Assumptions!$B$10-SUM($K$4:$K$43))) -> 197.87559 | M8: =L8*H8/(H8+I8)*Assumptions!$B$12 -> 115.42581 | N8: =L8-M8 -> 82.449778 | O8: =N8*Assumptions!$B$6/Assumptions!$B$11 -> 23.197461 | P8: =N8*Assumptions!$B$7/Assumptions!$B$11 -> 17.489569 | Q8: =N8*Assumptions!$B$8/Assumptions!$B$11 -> 21.221652 | R8: =N8*Assumptions!$B$9/Assumptions!$B$11 -> 20.541096 | S8: =IF(F8=0,0,L8*1000/F8) -> 164.89632 | T8: =INDEX('NSAA Margins'!$B$6:$E$14,MATCH(B8,'NSAA Margins'!$A$6:$A$14,0),MATCH(D8,'NSAA Margins'!$B$5:$E$5,0)) -> 0.419 | U8: =L8*T8*Assumptions!$B$16 -> 76.627272 | V8: =IF(L8=0,0,U8/L8) -> 0.38724975 | W8: 1 | X8: =L8*W8 -> 197.87559 | Y8: =U8*W8 -> 76.627272 | Z8: Public est.
A9: Beaver Creek | B9: Rocky Mountain | C9: USA | D9: Extra Large | E9: 2082 | F9: 1000 | G9: 1 | H9: =VLOOKUP(D9,'NSAA Benchmarks'!$A$6:$F$9,4,FALSE()) -> 94.3 | I9: =VLOOKUP(D9,'NSAA Benchmarks'!$A$6:$F$9,5,FALSE()) -> 77.59 | J9: =F9*(H9+I9)*G9 -> 171890 | K9: 0 | L9: =IF(K9>0,K9,J9/SUMIF($K$4:$K$43,0,$J$4:$J$43)*(Assumptions!$B$10-SUM($K$4:$K$43))) -> 164.89632 | M9: =L9*H9/(H9+I9)*Assumptions!$B$12 -> 96.188173 | N9: =L9-M9 -> 68.708148 | O9: =N9*Assumptions!$B$6/Assumptions!$B$11 -> 19.331218 | P9: =N9*Assumptions!$B$7/Assumptions!$B$11 -> 14.574641 | Q9: =N9*Assumptions!$B$8/Assumptions!$B$11 -> 17.68471 | R9: =N9*Assumptions!$B$9/Assumptions!$B$11 -> 17.11758 | S9: =IF(F9=0,0,L9*1000/F9) -> 164.89632 | T9: =INDEX('NSAA Margins'!$B$6:$E$14,MATCH(B9,'NSAA Margins'!$A$6:$A$14,0),MATCH(D9,'NSAA Margins'!$B$5:$E$5,0)) -> 0.419 | U9: =L9*T9*Assumptions!$B$16 -> 63.85606 | V9: =IF(L9=0,0,U9/L9) -> 0.38724975 | W9: 1 | X9: =L9*W9 -> 164.89632 | Y9: =U9*W9 -> 63.85606 | Z9: Public est.
A10: Heavenly | B10: Pacific Southwest | C10: USA | D10: Extra Large | E10: 4800 | F10: 870 | G10: 1 | H10: =VLOOKUP(D10,'NSAA Benchmarks'!$A$6:$F$9,4,FALSE()) -> 94.3 | I10: =VLOOKUP(D10,'NSAA Benchmarks'!$A$6:$F$9,5,FALSE()) -> 77.59 | J10: =F10*(H10+I10)*G10 -> 149544.3 | K10: 0 | L10: =IF(K10>0,K10,J10/SUMIF($K$4:$K$43,0,$J$4:$J$43)*(Assumptions!$B$10-SUM($K$4:$K$43))) -> 143.4598 | M10: =L10*H10/(H10+I10)*Assumptions!$B$12 -> 83.68371 | N10: =L10-M10 -> 59.776089 | O10: =N10*Assumptions!$B$6/Assumptions!$B$11 -> 16.818159 | P10: =N10*Assumptions!$B$7/Assumptions!$B$11 -> 12.679937 | Q10: =N10*Assumptions!$B$8/Assumptions!$B$11 -> 15.385698 | R10: =N10*Assumptions!$B$9/Assumptions!$B$11 -> 14.892294 | S10: =IF(F10=0,0,L10*1000/F10) -> 164.89632 | T10: =INDEX('NSAA Margins'!$B$6:$E$14,MATCH(B10,'NSAA Margins'!$A$6:$A$14,0),MATCH(D10,'NSAA Margins'!$B$5:$E$5,0)) -> 0.294 | U10: =L10*T10*Assumptions!$B$16 -> 38.981153 | V10: =IF(L10=0,0,U10/L10) -> 0.27172179 | W10: 1 | X10: =L10*W10 -> 143.4598 | Y10: =U10*W10 -> 38.981153 | Z10: Public est.
A11: Northstar | B11: Pacific Southwest | C11: USA | D11: Extra Large | E11: 3170 | F11: 680 | G11: 1 | H11: =VLOOKUP(D11,'NSAA Benchmarks'!$A$6:$F$9,4,FALSE()) -> 94.3 | I11: =VLOOKUP(D11,'NSAA Benchmarks'!$A$6:$F$9,5,FALSE()) -> 77.59 | J11: =F11*(H11+I11)*G11 -> 116885.2 | K11: 0 | L11: =IF(K11>0,K11,J11/SUMIF($K$4:$K$43,0,$J$4:$J$43)*(Assumptions!$B$10-SUM($K$4:$K$43))) -> 112.1295 | M11: =L11*H11/(H11+I11)*Assumptions!$B$12 -> 65.407958 | N11: =L11-M11 -> 46.721541 | O11: =N11*Assumptions!$B$6/Assumptions!$B$11 -> 13.145228 | P11: =N11*Assumptions!$B$7/Assumptions!$B$11 -> 9.9107555 | Q11: =N11*Assumptions!$B$8/Assumptions!$B$11 -> 12.025603 | R11: =N11*Assumptions!$B$9/Assumptions!$B$11 -> 11.639954 | S11: =IF(F11=0,0,L11*1000/F11) -> 164.89632 | T11: =INDEX('NSAA Margins'!$B$6:$E$14,MATCH(B11,'NSAA Margins'!$A$6:$A$14,0),MATCH(D11,'NSAA Margins'!$B$5:$E$5,0)) -> 0.294 | U11: =L11*T11*Assumptions!$B$16 -> 30.468027 | V11: =IF(L11=0,0,U11/L11) -> 0.27172179 | W11: 1 | X11: =L11*W11 -> 112.1295 | Y11: =U11*W11 -> 30.468027 | Z11: Public est.
A12: Crested Butte | B12: Rocky Mountain | C12: USA | D12: Large | E12: 1547 | F12: 470 | G12: 1 | H12: =VLOOKUP(D12,'NSAA Benchmarks'!$A$6:$F$9,4,FALSE()) -> 66.74 | I12: =VLOOKUP(D12,'NSAA Benchmarks'!$A$6:$F$9,5,FALSE()) -> 52.76 | J12: =F12*(H12+I12)*G12 -> 56165 | K12: 0 | L12: =IF(K12>0,K12,J12/SUMIF($K$4:$K$43,0,$J$4:$J$43)*(Assumptions!$B$10-SUM($K$4:$K$43))) -> 53.879818 | M12: =L12*H12/(H12+I12)*Assumptions!$B$12 -> 31.995879 | N12: =L12-M12 -> 21.883939 | O12: =N12*Assumptions!$B$6/Assumptions!$B$11 -> 6.1571036 | P12: =N12*Assumptions!$B$7/Assumptions!$B$11 -> 4.6421065 | Q12: =N12*Assumptions!$B$8/Assumptions!$B$11 -> 5.6326816 | R12: =N12*Assumptions!$B$9/Assumptions!$B$11 -> 5.4520473 | S12: =IF(F12=0,0,L12*1000/F12) -> 114.63791 | T12: =INDEX('NSAA Margins'!$B$6:$E$14,MATCH(B12,'NSAA Margins'!$A$6:$A$14,0),MATCH(D12,'NSAA Margins'!$B$5:$E$5,0)) -> 0.317 | U12: =L12*T12*Assumptions!$B$16 -> 15.785651 | V12: =IF(L12=0,0,U12/L12) -> 0.29297893 | W12: 1 | X12: =L12*W12 -> 53.879818 | Y12: =U12*W12 -> 15.785651 | Z12: NSAA RM-Large avg, scaled
A13: Kirkwood | B13: Pacific Southwest | C13: USA | D13: Large | E13: 2300 | F13: 310 | G13: 1 | H13: =VLOOKUP(D13,'NSAA Benchmarks'!$A$6:$F$9,4,FALSE()) -> 66.74 | I13: =VLOOKUP(D13,'NSAA Benchmarks'!$A$6:$F$9,5,FALSE()) -> 52.76 | J13: =F13*(H13+I13)*G13 -> 37045 | K13: 0 | L13: =IF(K13>0,K13,J13/SUMIF($K$4:$K$43,0,$J$4:$J$43)*(Assumptions!$B$10-SUM($K$4:$K$43))) -> 35.537752 | M13: =L13*H13/(H13+I13)*Assumptions!$B$12 -> 21.103665 | N13: =L13-M13 -> 14.434087 | O13: =N13*Assumptions!$B$6/Assumptions!$B$11 -> 4.0610684 | P13: =N13*Assumptions!$B$7/Assumptions!$B$11 -> 3.0618149 | Q13: =N13*Assumptions!$B$8/Assumptions!$B$11 -> 3.7151729 | R13: =N13*Assumptions!$B$9/Assumptions!$B$11 -> 3.5960312 | S13: =IF(F13=0,0,L13*1000/F13) -> 114.63791 | T13: =INDEX('NSAA Margins'!$B$6:$E$14,MATCH(B13,'NSAA Margins'!$A$6:$A$14,0),MATCH(D13,'NSAA Margins'!$B$5:$E$5,0)) -> 0.18 | U13: =L13*T13*Assumptions!$B$16 -> 5.9120703 | V13: =IF(L13=0,0,U13/L13) -> 0.16636028 | W13: 1 | X13: =L13*W13 -> 35.537752 | Y13: =U13*W13 -> 5.9120703 | Z13: NSAA PSW-Large avg
A14: Stowe | B14: Northeast | C14: USA | D14: Large | E14: 485 | F14: 560 | G14: 1 | H14: =VLOOKUP(D14,'NSAA Benchmarks'!$A$6:$F$9,4,FALSE()) -> 66.74 | I14: =VLOOKUP(D14,'NSAA Benchmarks'!$A$6:$F$9,5,FALSE()) -> 52.76 | J14: =F14*(H14+I14)*G14 -> 66920 | K14: 0 | L14: =IF(K14>0,K14,J14/SUMIF($K$4:$K$43,0,$J$4:$J$43)*(Assumptions!$B$10-SUM($K$4:$K$43))) -> 64.19723 | M14: =L14*H14/(H14+I14)*Assumptions!$B$12 -> 38.122749 | N14: =L14-M14 -> 26.074481 | O14: =N14*Assumptions!$B$6/Assumptions!$B$11 -> 7.3361235 | P14: =N14*Assumptions!$B$7/Assumptions!$B$11 -> 5.5310205 | Q14: =N14*Assumptions!$B$8/Assumptions!$B$11 -> 6.7112802 | R14: =N14*Assumptions!$B$9/Assumptions!$B$11 -> 6.4960564 | S14: =IF(F14=0,0,L14*1000/F14) -> 114.63791 | T14: =INDEX('NSAA Margins'!$B$6:$E$14,MATCH(B14,'NSAA Margins'!$A$6:$A$14,0),MATCH(D14,'NSAA Margins'!$B$5:$E$5,0)) -> 0.235 | U14: =L14*T14*Assumptions!$B$16 -> 13.943162 | V14: =IF(L14=0,0,U14/L14) -> 0.21719258 | W14: 1 | X14: =L14*W14 -> 64.19723 | Y14: =U14*W14 -> 13.943162 | Z14: NSAA NE-Large, top-tier scale
A15: Okemo | B15: Northeast | C15: USA | D15: Large | E15: 667 | F15: 510 | G15: 1 | H15: =VLOOKUP(D15,'NSAA Benchmarks'!$A$6:$F$9,4,FALSE()) -> 66.74 | I15: =VLOOKUP(D15,'NSAA Benchmarks'!$A$6:$F$9,5,FALSE()) -> 52.76 | J15: =F15*(H15+I15)*G15 -> 60945 | K15: 0 | L15: =IF(K15>0,K15,J15/SUMIF($K$4:$K$43,0,$J$4:$J$43)*(Assumptions!$B$10-SUM($K$4:$K$43))) -> 58.465334 | M15: =L15*H15/(H15+I15)*Assumptions!$B$12 -> 34.718932 | N15: =L15-M15 -> 23.746402 | O15: =N15*Assumptions!$B$6/Assumptions!$B$11 -> 6.6811125 | P15: =N15*Assumptions!$B$7/Assumptions!$B$11 -> 5.0371794 | Q15: =N15*Assumptions!$B$8/Assumptions!$B$11 -> 6.1120587 | R15: =N15*Assumptions!$B$9/Assumptions!$B$11 -> 5.9160513 | S15: =IF(F15=0,0,L15*1000/F15) -> 114.63791 | T15: =INDEX('NSAA Margins'!$B$6:$E$14,MATCH(B15,'NSAA Margins'!$A$6:$A$14,0),MATCH(D15,'NSAA Margins'!$B$5:$E$5,0)) -> 0.235 | U15: =L15*T15*Assumptions!$B$16 -> 12.698237 | V15: =IF(L15=0,0,U15/L15) -> 0.21719258 | W15: 1 | X15: =L15*W15 -> 58.465334 | Y15: =U15*W15 -> 12.698237 | Z15: NSAA NE-Large, scaled
A16: Mount Snow | B16: Northeast | C16: USA | D16: Large | E16: 588 | F16: 470 | G16: 1 | H16: =VLOOKUP(D16,'NSAA Benchmarks'!$A$6:$F$9,4,FALSE()) -> 66.74 | I16: =VLOOKUP(D16,'NSAA Benchmarks'!$A$6:$F$9,5,FALSE()) -> 52.76 | J16: =F16*(H16+I16)*G16 -> 56165 | K16: 0 | L16: =IF(K16>0,K16,J16/SUMIF($K$4:$K$43,0,$J$4:$J$43)*(Assumptions!$B$10-SUM($K$4:$K$43))) -> 53.879818 | M16: =L16*H16/(H16+I16)*Assumptions!$B$12 -> 31.995879 | N16: =L16-M16 -> 21.883939 | O16: =N16*Assumptions!$B$6/Assumptions!$B$11 -> 6.1571036 | P16: =N16*Assumptions!$B$7/Assumptions!$B$11 -> 4.6421065 | Q16: =N16*Assumptions!$B$8/Assumptions!$B$11 -> 5.6326816 | R16: =N16*Assumptions!$B$9/Assumptions!$B$11 -> 5.4520473 | S16: =IF(F16=0,0,L16*1000/F16) -> 114.63791 | T16: =INDEX('NSAA Margins'!$B$6:$E$14,MATCH(B16,'NSAA Margins'!$A$6:$A$14,0),MATCH(D16,'NSAA Margins'!$B$5:$E$5,0)) -> 0.235 | U16: =L16*T16*Assumptions!$B$16 -> 11.702297 | V16: =IF(L16=0,0,U16/L16) -> 0.21719258 | W16: 1 | X16: =L16*W16 -> 53.879818 | Y16: =U16*W16 -> 11.702297 | Z16: NSAA NE-Large, scaled
... A43: Laurel Mountain | B43: Southeast | C43: USA | D43: Small | E43: 70 | F43: 70 | G43: 1 | H43: =VLOOKUP(D43,'NSAA Benchmarks'!$A$6:$F$9,4,FALSE()) -> 48.88 | I43: =VLOOKUP(D43,'NSAA Benchmarks'!$A$6:$F$9,5,FALSE()) -> 61.96 | J43: =F43*(H43+I43)*G43 -> 7758.8 | K43: 0 | L43: =IF(K43>0,K43,J43/SUMIF($K$4:$K$43,0,$J$4:$J$43)*(Assumptions!$B$10-SUM($K$4:$K$43))) -> 7.4431181 | M43: =L43*H43/(H43+I43)*Assumptions!$B$12 -> 3.4901108 | N43: =L43-M43 -> 3.9530073 | O43: =N43*Assumptions!$B$6/Assumptions!$B$11 -> 1.112189 | P43: =N43*Assumptions!$B$7/Assumptions!$B$11 -> 0.83852733 | Q43: =N43*Assumptions!$B$8/Assumptions!$B$11 -> 1.0174599 | R43: =N43*Assumptions!$B$9/Assumptions!$B$11 -> 0.98483105 | S43: =IF(F43=0,0,L43*1000/F43) -> 106.33026 | T43: =INDEX('NSAA Margins'!$B$6:$E$14,MATCH(B43,'NSAA Margins'!$A$6:$A$14,0),MATCH(D43,'NSAA Margins'!$B$5:$E$5,0)) -> 0.253 | U43: =L43*T43*Assumptions!$B$16 -> 1.740414 | V43: =IF(L43=0,0,U43/L43) -> 0.23382861 | W43: 1 | X43: =L43*W43 -> 7.4431181 | Y43: =U43*W43 -> 1.740414 | Z43: NSAA SE-Small avg
A44: TOTAL / PORTFOLIO | E44: =SUM(E4:E43) -> 59493 | F44: =SUM(F4:F43) -> 18585 | J44: =SUM(J4:J43) -> 2759930.6 | K44: =SUM(K4:K43) -> 320.3 | L44: =SUM(L4:L43) -> 2629.9 | M44: =SUM(M4:M43) -> 1503.2 | N44: =SUM(N4:N43) -> 1126.7 | O44: =SUM(O4:O43) -> 317 | P44: =SUM(P4:P43) -> 239 | Q44: =SUM(Q4:Q43) -> 290 | R44: =SUM(R4:R43) -> 280.7 | S44: =L44*1000/F44 -> 141.50659 | T44: =U44/L44 -> 0.31229324 | U44: =SUM(U4:U43) -> 821.3 | V44: =U44/L44 -> 0.31229324 | X44: =SUM(X4:X43) -> 2549.825 | Y44: =SUM(Y4:Y43) -> 796.50758

Sheet Summary
A1: SUMMARY
A3: RECONCILIATION CHECKS ($mm)
A4: Line | B4: Reported/Target | C4: Model | D4: Diff
A5: Total Mountain revenue | B5: =Assumptions!$B$10 -> 2629.9 | C5: =SUM('Resort Model'!L4:L43) -> 2629.9 | D5: =C5-B5 -> 0
A6: Mountain EBITDA | B6: =Assumptions!$B$14 -> 821.3 | C6: =SUM('Resort Model'!U4:U43) -> 821.3 | D6: =C6-B6 -> 0
A7: Lift revenue (approx) | B7: =Assumptions!$B$5 -> 1503.2 | C7: =SUM('Resort Model'!M4:M43) -> 1503.2 | D7: =C7-B7 -> 0
A8: (Total revenue & EBITDA tie exactly; lift is approximate as it is derived from size mix.)
A10: GEOGRAPHIC RECONCILIATION ($mm)
A11: Geography | B11: Model Mountain | C11: 10-K (all-seg) | D11: Note
A12: U.S. | B12: =SUMIF('Resort Model'!$C$4:$C$43,"USA",'Resort Model'!$L$4:$L$43) -> 2115.9483 | C12: =Assumptions!$B$20 -> 2423.2 | D12: Mountain only vs all-segment
A13: Canada (Whistler) | B13: =SUMIF('Resort Model'!$C$4:$C$43,"Canada",'Resort Model'!$L$4:$L$43) -> 320.3 | C13: =Assumptions!$B$22 -> 335.3 | D13: Anchored (less BC lodging)
A14: Australia | B14: =SUMIF('Resort Model'!$C$4:$C$43,"Australia",'Resort Model'!$L$4:$L$43) -> 119.13709 | D14: part of Intl ex-Canada
A15: Europe (Switzerland) | B15: =SUMIF('Resort Model'!$C$4:$C$43,"Switzerland",'Resort Model'!$L$4:$L$43) -> 74.514642 | D15: part of Intl ex-Canada
A16: Intl ex-Canada (model) | B16: =B14+B15 -> 193.65173 | C16: =Assumptions!$B$23 -> 205.8 | D16: validation: model vs 10-K
A18: SKIER-VISIT CHECK (000s)
A19: North America (US + Whistler) | B19: =SUMIF('Resort Model'!$C$4:$C$43,"USA",'Resort Model'!$F$4:$F$43)+SUMIF('Resort Model'!$C$4:$C$43,"Canada",'Resort Model'!$F$4:$F$43) -> 16885 | C19: 16900 | D19: model vs Vail reported FY2025 NA visits
A20: Intl (AUS+EUR, excl. from NA metric) | B20: =SUM('Resort Model'!$F$4:$F$43)-B19 -> 1700 | D20: not in Vail's NA skier-visit disclosure
A22: TOP 8: GROSS REVENUE vs REVENUE TO VAIL
A23: Rank | B23: By gross rev | C23: Gross ($mm) | D23: By rev to Vail | E23: To Vail ($mm)
A24: 1 | B24: =INDEX('Resort Model'!$A$4:$A$43,MATCH(LARGE('Resort Model'!$L$4:$L$43,1),'Resort Model'!$L$4:$L$43,0)) -> Whistler Blackcomb | C24: =LARGE('Resort Model'!$L$4:$L$43,1) -> 320.3 | D24: =INDEX('Resort Model'!$A$4:$A$43,MATCH(LARGE('Resort Model'!$X$4:$X$43,1),'Resort Model'!$X$4:$X$43,0)) -> Breckenridge | E24: =LARGE('Resort Model'!$X$4:$X$43,1) -> 288.56856
A25: 2 | B25: =INDEX('Resort Model'!$A$4:$A$43,MATCH(LARGE('Resort Model'!$L$4:$L$43,2),'Resort Model'!$L$4:$L$43,0)) -> Breckenridge | C25: =LARGE('Resort Model'!$L$4:$L$43,2) -> 288.56856 | D25: =INDEX('Resort Model'!$A$4:$A$43,MATCH(LARGE('Resort Model'!$X$4:$X$43,2),'Resort Model'!$X$4:$X$43,0)) -> Vail Mountain | E25: =LARGE('Resort Model'!$X$4:$X$43,2) -> 272.07893
A26: 3 | B26: =INDEX('Resort Model'!$A$4:$A$43,MATCH(LARGE('Resort Model'!$L$4:$L$43,3),'Resort Model'!$L$4:$L$43,0)) -> Vail Mountain | C26: =LARGE('Resort Model'!$L$4:$L$43,3) -> 272.07893 | D26: =INDEX('Resort Model'!$A$4:$A$43,MATCH(LARGE('Resort Model'!$X$4:$X$43,3),'Resort Model'!$X$4:$X$43,0)) -> Park City Mountain | E26: =LARGE('Resort Model'!$X$4:$X$43,3) -> 255.5893
A27: 4 | B27: =INDEX('Resort Model'!$A$4:$A$43,MATCH(LARGE('Resort Model'!$L$4:$L$43,4),'Resort Model'!$L$4:$L$43,0)) -> Park City Mountain | C27: =LARGE('Resort Model'!$L$4:$L$43,4) -> 255.5893 | D27: =INDEX('Resort Model'!$A$4:$A$43,MATCH(LARGE('Resort Model'!$X$4:$X$43,4),'Resort Model'!$X$4:$X$43,0)) -> Whistler Blackcomb | E27: =LARGE('Resort Model'!$X$4:$X$43,4) -> 240.225
A28: 5 | B28: =INDEX('Resort Model'!$A$4:$A$43,MATCH(LARGE('Resort Model'!$L$4:$L$43,5),'Resort Model'!$L$4:$L$43,0)) -> Keystone | C28: =LARGE('Resort Model'!$L$4:$L$43,5) -> 197.87559 | D28: =INDEX('Resort Model'!$A$4:$A$43,MATCH(LARGE('Resort Model'!$X$4:$X$43,5),'Resort Model'!$X$4:$X$43,0)) -> Keystone | E28: =LARGE('Resort Model'!$X$4:$X$43,5) -> 197.87559
A29: 6 | B29: =INDEX('Resort Model'!$A$4:$A$43,MATCH(LARGE('Resort Model'!$L$4:$L$43,6),'Resort Model'!$L$4:$L$43,0)) -> Beaver Creek | C29: =LARGE('Resort Model'!$L$4:$L$43,6) -> 164.89632 | D29: =INDEX('Resort Model'!$A$4:$A$43,MATCH(LARGE('Resort Model'!$X$4:$X$43,6),'Resort Model'!$X$4:$X$43,0)) -> Beaver Creek | E29: =LARGE('Resort Model'!$X$4:$X$43,6) -> 164.89632
A30: 7 | B30: =INDEX('Resort Model'!$A$4:$A$43,MATCH(LARGE('Resort Model'!$L$4:$L$43,7),'Resort Model'!$L$4:$L$43,0)) -> Heavenly | C30: =LARGE('Resort Model'!$L$4:$L$43,7) -> 143.4598 | D30: =INDEX('Resort Model'!$A$4:$A$43,MATCH(LARGE('Resort Model'!$X$4:$X$43,7),'Resort Model'!$X$4:$X$43,0)) -> Heavenly | E30: =LARGE('Resort Model'!$X$4:$X$43,7) -> 143.4598
A31: 8 | B31: =INDEX('Resort Model'!$A$4:$A$43,MATCH(LARGE('Resort Model'!$L$4:$L$43,8),'Resort Model'!$L$4:$L$43,0)) -> Northstar | C31: =LARGE('Resort Model'!$L$4:$L$43,8) -> 112.1295 | D31: =INDEX('Resort Model'!$A$4:$A$43,MATCH(LARGE('Resort Model'!$X$4:$X$43,8),'Resort Model'!$X$4:$X$43,0)) -> Northstar | E31: =LARGE('Resort Model'!$X$4:$X$43,8) -> 112.1295
