Workbook

Sheet Summary
B2: 2026 World Cup: Incremental OSB Handle
B3: Uplift to US online sports betting handle. Observed through 28 Jun 2026.
B5: KEY RESULTS | K5: chart data
B6: Metric | C6: Value | D6: Basis | K6: NY scaled (upper) | L6: =National!C15 -> 5.3343896
B7: Observed: NY handle uplift, 3 World Cup weeks | C7: =National!C6 -> 0.53703003 | D7: Hard data (NY State Gaming Commission). Plus 48% vs counterfactual. | K7: Adjusted (central) | L7: =National!C16 -> 3.2006337
B8: Observed: NY uplift, percent | C8: ='Uplift Calc'!I11 -> 0.48191013 | D8: Vs a seasonally and growth adjusted counterfactual. | K8: Third party (central) | L8: =National!C19 -> 3.284
B9: Estimated: national uplift to date | C9: =National!C10 -> 2.0429577 | D9: NY scaled to US and representativeness adjusted (central).
B10: Estimated: national, full tournament | C10: =National!C16 -> 3.2006337 | D10: Projection to 19 Jul. Adjusted central.
B11: Cross check: third party central | C11: =National!C19 -> 3.284 | D11: Independent bottom up (EK, H2, DB, Bookies).
B13: VERDICT
B14: A '3B plus incremental handle' call is well supported and, for legal states, arguably conservative. The observed NY lift is large and clean. Scaled and reconciled to independent estimates, the national full tournament uplift lands at roughly 3.0 to 3.5B.
B16: See the Method tab for the full approach, definitions, limitations and sources.

Sheet Method
B2: Method, Definitions and Limitations
B3: How the uplift is measured and why it is defensible.
B5: APPROACH
B6: Each 2026 World Cup week is compared to the same ISO week in 2025 (a no tournament year), grown by organic year on year growth. This isolates the World Cup by controlling for two things at once: the summer seasonal trough, and underlying market growth. Uplift equals actual minus counterfactual.
B7: Organic growth is measured, not assumed. It is taken from a clean pre tournament window (ISO weeks 10 to 21, mid March to late May) of 2026 vs 2025. NY was about minus 2 percent (flat to down), so the tournament week jump is cleanly attributable to the World Cup rather than to a trend.
B8: The model measures handle (amount wagered), not revenue, so sport outcome and hold volatility do not distort the result.
B9: The national figure scales NY by its share of US handle (15.8 percent), then applies a representativeness factor because NY over indexes on the World Cup. The result is cross checked against four independent bottom up estimates.
B11: DEFINITIONS
B12: Handle: total amount wagered. Counterfactual: 2025 same ISO week times (1 plus organic growth), that is, expected 2026 handle with no World Cup. Uplift: actual 2026 handle minus counterfactual. Representativeness factor: adjustment for NY being more World Cup sensitive than the national average.
B14: KEY LIMITATIONS
B15: 1. Partial tournament. Data covers 3 of about 5.6 tournament weeks. Full tournament figures are projections, labelled as such.
B16: 2. NY is not the nation. NY over indexes on soccer, and the three largest soccer states (California, Texas, Florida, holding 52 percent of US Hispanics) have no legal OSB, so they add nothing to national OSB handle. The naive NY scale up is therefore an upper bound. A representativeness factor of about 0.6, which is also what the third party reconciliation implies, gives the central figure.
... B23: Estimates for analytical purposes, not investment advice.

Sheet Inputs
B2: Inputs
B3: Blue = you can change it. Yellow = key judgement. Black = derived.
B4: MODEL INPUTS
B5: Organic YoY growth (NY, pre tournament) | C5: =SUM('NY Data'!D15:D26)/SUM('NY Data'!C15:C26)-1 -> -0.021485797 | D5: % | E5: Derived from NY Data, ISO weeks 10 to 21 (2026 vs 2025).
B6: NY 2025 handle | C6: 26.33 | D6: $B | E6: Source: AGA / RG.org, FY2025.
B7: US 2025 handle | C7: 166.94 | D7: $B | E7: Source: AGA, FY2025.
B8: NY share of US OSB handle | C8: =C6/C7 -> 0.15772134 | D8: % | E8: Derived: NY divided by US 2025 handle.
B9: World Cup kickoff | C9: 2026-06-11 | D9: date | E9: Source: FIFA.
B10: World Cup final | C10: 2026-07-19 | D10: date | E10: Source: FIFA.
B11: Full tournament length | C11: =(DATE(2026,7,19)-DATE(2026,6,11))/7 -> 5.4285714 | D11: wks | E11: Derived: (final minus kickoff) / 7.
B12: Observed tournament weeks (data) | C12: 3 | D12: wks | E12: ISO weeks 24 to 26, through 28 Jun 2026.
B13: Representativeness factor | C13: 0.6 | D13: x | E13: Judgement. NY over indexes on soccer; CA, TX, FL have no OSB. 1.0 means NY representative (upper bound). Third party reconciliation implies about 0.6.
B14: Remaining week pace vs to date | C14: 0.7 | D14: x | E14: Judgement. USMNT eliminated 6 Jul; knockout interest partly offsets loss of US matches.
B16: THIRD PARTY FULL TOURNAMENT US WORLD CUP HANDLE ($B)
B17: Eilers & Krejcik, low | C17: 2.82 | D17: $B | E17: Source: firm World Cup preview notes, Jun 2026 (match handle, full tournament).
B18: Eilers & Krejcik, high | C18: 4.3 | D18: $B | E18: Source: firm World Cup preview notes, Jun 2026 (match handle, full tournament).
B19: H2 Gambling Capital | C19: 2.9 | D19: $B | E19: Source: firm World Cup preview notes, Jun 2026 (match handle, full tournament).
B20: Deutsche Bank | C20: 3.3 | D20: $B | E20: Source: firm World Cup preview notes, Jun 2026 (match handle, full tournament).
B21: Bookies.com | C21: 3.1 | D21: $B | E21: Source: firm World Cup preview notes, Jun 2026 (match handle, full tournament).
B22: Third party central (average) | C22: =AVERAGE(C17:C21) -> 3.284 | D22: $B | E22: Independent national anchor for the cross check.

Sheet NY Data
B2: NY Weekly OSB Handle: Raw Data
B3: By ISO week, all operators, online. Feeds the growth calc and the uplift engine.
B4: WEEKLY HANDLE ($M)
B5: ISO week | C5: 2025 | D5: 2026 | E5: Note
B6: 1 | C6: 600.838 | D6: 575.862
B7: 2 | C7: 561.041 | D7: 549.592
B8: 3 | C8: 593.664 | D8: 545.143
B9: 4 | C9: 541.118 | D9: 552.471
B10: 5 | C10: 518.991 | D10: 510.012
B11: 6 | C11: 557.879 | D11: 572.48
B12: 7 | C12: 434.077 | D12: 459.448
B13: 8 | C13: 428.242 | D13: 475.323
B14: 9 | C14: 549.865 | D14: 494.613
B15: 10 | C15: 562.183 | D15: 526.526 | E15: growth window start
B16: 11 | C16: 550.832 | D16: 549.272
B17: 12 | C17: 555.343 | D17: 554.68
B18: 13 | C18: 522.371 | D18: 492.134
B19: 14 | C19: 562.485 | D19: 511.436
B20: 15 | C20: 474.43 | D20: 492.053
B21: 16 | C21: 462.115 | D21: 484.512
B22: 17 | C22: 526.167 | D22: 535.534
B23: 18 | C23: 480.252 | D23: 493.585
B24: 19 | C24: 521.083 | D24: 513.47
B25: 20 | C25: 500.833 | D25: 423.404
B26: 21 | C26: 478.232 | D26: 486.587 | E26: growth window end
B27: 22 | C27: 493.314 | D27: 482.926
B28: 23 | C28: 400.206 | D28: 448.604 | E28: week before kickoff (reference)
B29: 24 | C29: 390.831 | D29: 587.58 | E29: World Cup week (kickoff 11 Jun, ISO 24)
B30: 25 | C30: 398.34 | D30: 551.32 | E30: World Cup week (kickoff 11 Jun, ISO 24)
B31: 26 | C31: 349.676 | D31: 512.508 | E31: World Cup week (kickoff 11 Jun, ISO 24)
B33: Source: NY State Gaming Commission weekly operator reports, ISO week aligned across years.

Sheet Uplift Calc
B2: New York World Cup Uplift
B3: Observed, using an ISO week counterfactual. This is the measured anchor.
B4: A. UPLIFT ENGINE
B6: ISO wk | C6: Wk ending | D6: 2026 Actual | E6: 2025 Base | F6: Organic gth | G6: Counterfactual | H6: Uplift ($M) | I6: Uplift %
B7: 23 | C7: 2026-06-07 | D7: ='NY Data'!D28 -> 448.604 | E7: ='NY Data'!C28 -> 400.206 | F7: =Inputs!C5 -> -0.021485797 | G7: =E7*(1+F7) -> 391.60726 | H7: =D7-G7 -> 56.996745 | I7: =D7/G7-1 -> 0.14554568 | J7: pre kickoff reference, excluded from totals
B8: 24 | C8: 2026-06-14 | D8: ='NY Data'!D29 -> 587.58 | E8: ='NY Data'!C29 -> 390.831 | F8: =Inputs!C5 -> -0.021485797 | G8: =E8*(1+F8) -> 382.43368 | H8: =D8-G8 -> 205.14632 | I8: =D8/G8-1 -> 0.53642324
B9: 25 | C9: 2026-06-21 | D9: ='NY Data'!D30 -> 551.32 | E9: ='NY Data'!C30 -> 398.34 | F9: =Inputs!C5 -> -0.021485797 | G9: =E9*(1+F9) -> 389.78135 | H9: =D9-G9 -> 161.53865 | I9: =D9/G9-1 -> 0.41443402
B10: 26 | C10: 2026-06-28 | D10: ='NY Data'!D31 -> 512.508 | E10: ='NY Data'!C31 -> 349.676 | F10: =Inputs!C5 -> -0.021485797 | G10: =E10*(1+F10) -> 342.16293 | H10: =D10-G10 -> 170.34507 | I10: =D10/G10-1 -> 0.49784781
B11: Total, WC wks 24 to 26 | D11: =SUM(D8:D10) -> 1651.408 | E11: =SUM(E8:E10) -> 1138.847 | G11: =SUM(G8:G10) -> 1114.378 | H11: =SUM(H8:H10) -> 537.03003 | I11: =D11/G11-1 -> 0.48191013
B13: Read: over the three World Cup weeks NY handle ran well above a counterfactual that already controls for the summer trough and for organic growth. The lift is large (about plus 48 percent) and robust; even at an implausibly high plus 15 percent growth assumption it stays about plus 30 percent (see Sensitivity).
B15: B. EVIDENCE CHART DATA (ISO wks 18 to 26)
B16: ISO wk | C16: Actual 2026 | D16: Counterfactual
B17: 18 | C17: ='NY Data'!D23 -> 493.585 | D17: ='NY Data'!C23*(1+Inputs!C5) -> 469.9334
B18: 19 | C18: ='NY Data'!D24 -> 513.47 | D18: ='NY Data'!C24*(1+Inputs!C5) -> 509.88712
B19: 20 | C19: ='NY Data'!D25 -> 423.404 | D19: ='NY Data'!C25*(1+Inputs!C5) -> 490.0722
B20: 21 | C20: ='NY Data'!D26 -> 486.587 | D20: ='NY Data'!C26*(1+Inputs!C5) -> 467.9568
B21: 22 | C21: ='NY Data'!D27 -> 482.926 | D21: ='NY Data'!C27*(1+Inputs!C5) -> 482.71476
B22: 23 | C22: ='NY Data'!D28 -> 448.604 | D22: ='NY Data'!C28*(1+Inputs!C5) -> 391.60726
B23: 24 | C23: ='NY Data'!D29 -> 587.58 | D23: ='NY Data'!C29*(1+Inputs!C5) -> 382.43368
B24: 25 | C24: ='NY Data'!D30 -> 551.32 | D24: ='NY Data'!C30*(1+Inputs!C5) -> 389.78135
B25: 26 | C25: ='NY Data'!D31 -> 512.508 | D25: ='NY Data'!C31*(1+Inputs!C5) -> 342.16293

Sheet National
B2: National Estimate and Cross Check
B3: Scale NY to the US, project the full tournament, and reconcile with independent estimates.
B4: A. OBSERVED TO DATE (hard)
B6: NY uplift, 3 World Cup weeks | C6: ='Uplift Calc'!H11/1000 -> 0.53703003 | D6: $B | E6: From Uplift Calc. Equals plus 48 percent vs counterfactual.
B7: NY share of US OSB handle | C7: =Inputs!C8 -> 0.15772134 | D7: % | E7: From Inputs.
B8: National to date, upper bound | C8: =C6/C7 -> 3.4049295 | D8: $B | E8: NY uplift divided by share. Assumes NY representative, so upper bound.
B9: Representativeness factor | C9: =Inputs!C13 -> 0.6 | D9: x | E9: From Inputs (judgement; about 0.6 implied by cross check).
B10: National to date, adjusted (central) | C10: =C8*C9 -> 2.0429577 | D10: $B | E10: Upper bound times representativeness factor.
B12: B. FULL TOURNAMENT PROJECTION (estimate)
B13: Full tournament / observed weeks | C13: =ROUND(Inputs!C11,1)&" / "&Inputs!C12 -> 5.4 / 3 | D13: wks | E13: FIFA calendar / ISO 24 to 26.
B14: Projected remaining uplift (NY) | C14: =('Uplift Calc'!H11/Inputs!C12)*(Inputs!C11-Inputs!C12)*Inputs!C14/1000 -> 0.30431702 | D14: $B | E14: NY weekly uplift times remaining weeks times pace.
B15: National full tournament, upper bound | C15: =(C6+C14)/C7 -> 5.3343896 | D15: $B | E15: (NY to date plus projected remaining) divided by share.
B16: National full tournament, adjusted (central) | C16: =C15*C9 -> 3.2006337 | D16: $B | E16: Upper bound times representativeness factor.
B18: C. CROSS CHECK vs INDEPENDENT BOTTOM UP
B19: Third party central (full tournament) | C19: =Inputs!C22 -> 3.284 | D19: $B | E19: Average of EK, H2, DB, Bookies (match handle).
B20: Third party range | C20: ="$"&Inputs!C17&" to $"&Inputs!C18 -> $2.82 to $4.3 | D20: $B | E20: Eilers and Krejcik low and high.
B21: Implied representativeness factor | C21: =C19/C15 -> 0.61562808 | D21: x | E21: Third party central divided by NY upper bound. About 0.6 implies NY runs about 1.6x national average lift.
B23: Read: the adjusted central figures in B agree with the independent bottom up in C. The two methods reconcile at roughly 3.0 to 3.5B; the naive NY scale up (about 5.3B) is an upper bound.

Sheet Sensitivity
B2: Sensitivity: National Full Tournament Uplift ($B)
B3: Rows = organic growth. Columns = representativeness factor.
B4: HEATMAP
C6: 0.5 | D6: 0.6 | E6: 0.7 | F6: 0.85 | G6: 1
B7: -0.02 | C7: =((SUM('NY Data'!D29:D31)-SUM('NY Data'!C29:C31)*(1+$B7))*(1+((Inputs!C11-Inputs!C12)/Inputs!C12)*Inputs!C14))/Inputs!C8*C$6/1000 -> 2.6587909 | D7: =((SUM('NY Data'!D29:D31)-SUM('NY Data'!C29:C31)*(1+$B7))*(1+((Inputs!C11-Inputs!C12)/Inputs!C12)*Inputs!C14))/Inputs!C8*D$6/1000 -> 3.1905491 | E7: =((SUM('NY Data'!D29:D31)-SUM('NY Data'!C29:C31)*(1+$B7))*(1+((Inputs!C11-Inputs!C12)/Inputs!C12)*Inputs!C14))/Inputs!C8*E$6/1000 -> 3.7223072 | F7: =((SUM('NY Data'!D29:D31)-SUM('NY Data'!C29:C31)*(1+$B7))*(1+((Inputs!C11-Inputs!C12)/Inputs!C12)*Inputs!C14))/Inputs!C8*F$6/1000 -> 4.5199445 | G7: =((SUM('NY Data'!D29:D31)-SUM('NY Data'!C29:C31)*(1+$B7))*(1+((Inputs!C11-Inputs!C12)/Inputs!C12)*Inputs!C14))/Inputs!C8*G$6/1000 -> 5.3175818
B8: 0 | C8: =((SUM('NY Data'!D29:D31)-SUM('NY Data'!C29:C31)*(1+$B8))*(1+((Inputs!C11-Inputs!C12)/Inputs!C12)*Inputs!C14))/Inputs!C8*C$6/1000 -> 2.5456677 | D8: =((SUM('NY Data'!D29:D31)-SUM('NY Data'!C29:C31)*(1+$B8))*(1+((Inputs!C11-Inputs!C12)/Inputs!C12)*Inputs!C14))/Inputs!C8*D$6/1000 -> 3.0548013 | E8: =((SUM('NY Data'!D29:D31)-SUM('NY Data'!C29:C31)*(1+$B8))*(1+((Inputs!C11-Inputs!C12)/Inputs!C12)*Inputs!C14))/Inputs!C8*E$6/1000 -> 3.5639348 | F8: =((SUM('NY Data'!D29:D31)-SUM('NY Data'!C29:C31)*(1+$B8))*(1+((Inputs!C11-Inputs!C12)/Inputs!C12)*Inputs!C14))/Inputs!C8*F$6/1000 -> 4.3276351 | G8: =((SUM('NY Data'!D29:D31)-SUM('NY Data'!C29:C31)*(1+$B8))*(1+((Inputs!C11-Inputs!C12)/Inputs!C12)*Inputs!C14))/Inputs!C8*G$6/1000 -> 5.0913354
B9: 0.05 | C9: =((SUM('NY Data'!D29:D31)-SUM('NY Data'!C29:C31)*(1+$B9))*(1+((Inputs!C11-Inputs!C12)/Inputs!C12)*Inputs!C14))/Inputs!C8*C$6/1000 -> 2.2628598 | D9: =((SUM('NY Data'!D29:D31)-SUM('NY Data'!C29:C31)*(1+$B9))*(1+((Inputs!C11-Inputs!C12)/Inputs!C12)*Inputs!C14))/Inputs!C8*D$6/1000 -> 2.7154318 | E9: =((SUM('NY Data'!D29:D31)-SUM('NY Data'!C29:C31)*(1+$B9))*(1+((Inputs!C11-Inputs!C12)/Inputs!C12)*Inputs!C14))/Inputs!C8*E$6/1000 -> 3.1680037 | F9: =((SUM('NY Data'!D29:D31)-SUM('NY Data'!C29:C31)*(1+$B9))*(1+((Inputs!C11-Inputs!C12)/Inputs!C12)*Inputs!C14))/Inputs!C8*F$6/1000 -> 3.8468617 | G9: =((SUM('NY Data'!D29:D31)-SUM('NY Data'!C29:C31)*(1+$B9))*(1+((Inputs!C11-Inputs!C12)/Inputs!C12)*Inputs!C14))/Inputs!C8*G$6/1000 -> 4.5257196
B10: 0.1 | C10: =((SUM('NY Data'!D29:D31)-SUM('NY Data'!C29:C31)*(1+$B10))*(1+((Inputs!C11-Inputs!C12)/Inputs!C12)*Inputs!C14))/Inputs!C8*C$6/1000 -> 1.9800519 | D10: =((SUM('NY Data'!D29:D31)-SUM('NY Data'!C29:C31)*(1+$B10))*(1+((Inputs!C11-Inputs!C12)/Inputs!C12)*Inputs!C14))/Inputs!C8*D$6/1000 -> 2.3760623 | E10: =((SUM('NY Data'!D29:D31)-SUM('NY Data'!C29:C31)*(1+$B10))*(1+((Inputs!C11-Inputs!C12)/Inputs!C12)*Inputs!C14))/Inputs!C8*E$6/1000 -> 2.7720727 | F10: =((SUM('NY Data'!D29:D31)-SUM('NY Data'!C29:C31)*(1+$B10))*(1+((Inputs!C11-Inputs!C12)/Inputs!C12)*Inputs!C14))/Inputs!C8*F$6/1000 -> 3.3660883 | G10: =((SUM('NY Data'!D29:D31)-SUM('NY Data'!C29:C31)*(1+$B10))*(1+((Inputs!C11-Inputs!C12)/Inputs!C12)*Inputs!C14))/Inputs!C8*G$6/1000 -> 3.9601038
B11: 0.15 | C11: =((SUM('NY Data'!D29:D31)-SUM('NY Data'!C29:C31)*(1+$B11))*(1+((Inputs!C11-Inputs!C12)/Inputs!C12)*Inputs!C14))/Inputs!C8*C$6/1000 -> 1.697244 | D11: =((SUM('NY Data'!D29:D31)-SUM('NY Data'!C29:C31)*(1+$B11))*(1+((Inputs!C11-Inputs!C12)/Inputs!C12)*Inputs!C14))/Inputs!C8*D$6/1000 -> 2.0366928 | E11: =((SUM('NY Data'!D29:D31)-SUM('NY Data'!C29:C31)*(1+$B11))*(1+((Inputs!C11-Inputs!C12)/Inputs!C12)*Inputs!C14))/Inputs!C8*E$6/1000 -> 2.3761416 | F11: =((SUM('NY Data'!D29:D31)-SUM('NY Data'!C29:C31)*(1+$B11))*(1+((Inputs!C11-Inputs!C12)/Inputs!C12)*Inputs!C14))/Inputs!C8*F$6/1000 -> 2.8853148 | G11: =((SUM('NY Data'!D29:D31)-SUM('NY Data'!C29:C31)*(1+$B11))*(1+((Inputs!C11-Inputs!C12)/Inputs!C12)*Inputs!C14))/Inputs!C8*G$6/1000 -> 3.394488
B13: Base case (organic minus 2 percent, representativeness 0.60) and third party central (about 3.1B) sit in the mid grid.
B15: The existence and rough scale of the uplift is robust to the growth assumption. The level of the national figure is most sensitive to the representativeness factor, the softest input.
