Workbook

Sheet Annual Summary
A1: WWE Live Event Box Office | Annual Summary
A2: Source: Pollstar Data Cloud, Boxoffice. Promoter: World Wrestling Entertainment. USD. Calendar years 2023 to 2026.
A4: Year | B4: Events | C4: Shows | D4: Total Gross (USD) | E4: Avg. Gross / Show (USD) | F4: Avg. Gross / Event (USD) | G4: Avg. Ticket (USD) | H4: Capacity Sold % | I4: Total Gross YoY % | J4: Avg. Gross/Show YoY % | K4: Avg. Ticket YoY %
A5: 2023 | B5: =COUNTIFS('Raw Data'!$B:$B,$A5) -> 84 | C5: =SUMIFS('Raw Data'!$E:$E,'Raw Data'!$B:$B,$A5) -> 85 | D5: =SUMIFS('Raw Data'!$N:$N,'Raw Data'!$B:$B,$A5) -> 64315187 | E5: =IF(C5=0,"",D5/C5) -> 756649.26 | F5: =IF(B5=0,"",D5/B5) -> 765656.99 | G5: =AVERAGEIFS('Raw Data'!$S:$S,'Raw Data'!$B:$B,$A5) -> 58.827024 | H5: =AVERAGEIFS('Raw Data'!$P:$P,'Raw Data'!$B:$B,$A5) -> 0.86595238 | I5: n/a | J5: n/a | K5: n/a
A6: 2024 | B6: =COUNTIFS('Raw Data'!$B:$B,$A6) -> 70 | C6: =SUMIFS('Raw Data'!$E:$E,'Raw Data'!$B:$B,$A6) -> 74 | D6: =SUMIFS('Raw Data'!$N:$N,'Raw Data'!$B:$B,$A6) -> 60018065 | E6: =IF(C6=0,"",D6/C6) -> 811054.93 | F6: =IF(B6=0,"",D6/B6) -> 857400.92 | G6: =AVERAGEIFS('Raw Data'!$S:$S,'Raw Data'!$B:$B,$A6) -> 74.969571 | H6: =AVERAGEIFS('Raw Data'!$P:$P,'Raw Data'!$B:$B,$A6) -> 0.88514286 | I6: =D6/D5-1 -> -0.06681349 | J6: =E6/E5-1 -> 0.071903423 | K6: =G6/G5-1 -> 0.27440701
A7: 2025 | B7: =COUNTIFS('Raw Data'!$B:$B,$A7) -> 51 | C7: =SUMIFS('Raw Data'!$E:$E,'Raw Data'!$B:$B,$A7) -> 52 | D7: =SUMIFS('Raw Data'!$N:$N,'Raw Data'!$B:$B,$A7) -> 87276181 | E7: =IF(C7=0,"",D7/C7) -> 1678388.1 | F7: =IF(B7=0,"",D7/B7) -> 1711297.7 | G7: =AVERAGEIFS('Raw Data'!$S:$S,'Raw Data'!$B:$B,$A7) -> 131.38882 | H7: =AVERAGEIFS('Raw Data'!$P:$P,'Raw Data'!$B:$B,$A7) -> 0.92117647 | I7: =D7/D6-1 -> 0.4541652 | J7: =E7/E6-1 -> 1.0693889 | K7: =G7/G6-1 -> 0.75256202
A8: 2026 | B8: =COUNTIFS('Raw Data'!$B:$B,$A8) -> 22 | C8: =SUMIFS('Raw Data'!$E:$E,'Raw Data'!$B:$B,$A8) -> 22 | D8: =SUMIFS('Raw Data'!$N:$N,'Raw Data'!$B:$B,$A8) -> 24423182 | E8: =IF(C8=0,"",D8/C8) -> 1110144.6 | F8: =IF(B8=0,"",D8/B8) -> 1110144.6 | G8: =AVERAGEIFS('Raw Data'!$S:$S,'Raw Data'!$B:$B,$A8) -> 112.54 | H8: =AVERAGEIFS('Raw Data'!$P:$P,'Raw Data'!$B:$B,$A8) -> 0.89636364 | I8: =D8/D7-1 -> -0.72016211 | J8: =E8/E7-1 -> -0.33856499 | K8: =G8/G7-1 -> -0.14345835
A10: Notes: 2023 YoY is not available because pre-2023 data is excluded per scope. 2026 covers Q1 to Q2 only, so its YoY figures compare a partial year against a full year and are not like-for-like.

Sheet Quarterly Summary
A1: WWE Live Event Box Office | Quarterly Summary
A2: Source: Pollstar Data Cloud, Boxoffice. USD. YoY compares each quarter to the same quarter one year earlier.
A4: Year-Qtr | B4: Events | C4: Shows | D4: Total Gross (USD) | E4: Avg. Gross / Show (USD) | F4: Avg. Ticket (USD) | G4: Capacity Sold % | H4: Total Gross YoY % | I4: Avg. Gross/Show YoY %
A5: 2023 Q1 | B5: =COUNTIFS('Raw Data'!$D:$D,$A5) -> 26 | C5: =SUMIFS('Raw Data'!$E:$E,'Raw Data'!$D:$D,$A5) -> 26 | D5: =SUMIFS('Raw Data'!$N:$N,'Raw Data'!$D:$D,$A5) -> 13643659 | E5: =IF(C5=0,"",D5/C5) -> 524756.1 | F5: =AVERAGEIFS('Raw Data'!$S:$S,'Raw Data'!$D:$D,$A5) -> 54.328846 | G5: =AVERAGEIFS('Raw Data'!$P:$P,'Raw Data'!$D:$D,$A5) -> 0.855 | H5: n/a | I5: n/a
A6: 2023 Q2 | B6: =COUNTIFS('Raw Data'!$D:$D,$A6) -> 16 | C6: =SUMIFS('Raw Data'!$E:$E,'Raw Data'!$D:$D,$A6) -> 17 | D6: =SUMIFS('Raw Data'!$N:$N,'Raw Data'!$D:$D,$A6) -> 26762178 | E6: =IF(C6=0,"",D6/C6) -> 1574245.8 | F6: =AVERAGEIFS('Raw Data'!$S:$S,'Raw Data'!$D:$D,$A6) -> 58.7575 | G6: =AVERAGEIFS('Raw Data'!$P:$P,'Raw Data'!$D:$D,$A6) -> 0.87625 | H6: n/a | I6: n/a
A7: 2023 Q3 | B7: =COUNTIFS('Raw Data'!$D:$D,$A7) -> 16 | C7: =SUMIFS('Raw Data'!$E:$E,'Raw Data'!$D:$D,$A7) -> 16 | D7: =SUMIFS('Raw Data'!$N:$N,'Raw Data'!$D:$D,$A7) -> 7888629.5 | E7: =IF(C7=0,"",D7/C7) -> 493039.34 | F7: =AVERAGEIFS('Raw Data'!$S:$S,'Raw Data'!$D:$D,$A7) -> 56.060625 | G7: =AVERAGEIFS('Raw Data'!$P:$P,'Raw Data'!$D:$D,$A7) -> 0.9 | H7: n/a | I7: n/a
A8: 2023 Q4 | B8: =COUNTIFS('Raw Data'!$D:$D,$A8) -> 26 | C8: =SUMIFS('Raw Data'!$E:$E,'Raw Data'!$D:$D,$A8) -> 26 | D8: =SUMIFS('Raw Data'!$N:$N,'Raw Data'!$D:$D,$A8) -> 16020720 | E8: =IF(C8=0,"",D8/C8) -> 616181.55 | F8: =AVERAGEIFS('Raw Data'!$S:$S,'Raw Data'!$D:$D,$A8) -> 65.070385 | G8: =AVERAGEIFS('Raw Data'!$P:$P,'Raw Data'!$D:$D,$A8) -> 0.84961538 | H8: n/a | I8: n/a
A9: 2024 Q1 | B9: =COUNTIFS('Raw Data'!$D:$D,$A9) -> 20 | C9: =SUMIFS('Raw Data'!$E:$E,'Raw Data'!$D:$D,$A9) -> 20 | D9: =SUMIFS('Raw Data'!$N:$N,'Raw Data'!$D:$D,$A9) -> 10721668 | E9: =IF(C9=0,"",D9/C9) -> 536083.42 | F9: =AVERAGEIFS('Raw Data'!$S:$S,'Raw Data'!$D:$D,$A9) -> 58.95 | G9: =AVERAGEIFS('Raw Data'!$P:$P,'Raw Data'!$D:$D,$A9) -> 0.889 | H9: =D9/D5-1 -> -0.21416471 | I9: =E9/E5-1 -> 0.021585876
A10: 2024 Q2 | B10: =COUNTIFS('Raw Data'!$D:$D,$A10) -> 14 | C10: =SUMIFS('Raw Data'!$E:$E,'Raw Data'!$D:$D,$A10) -> 18 | D10: =SUMIFS('Raw Data'!$N:$N,'Raw Data'!$D:$D,$A10) -> 21894394 | E10: =IF(C10=0,"",D10/C10) -> 1216355.2 | F10: =AVERAGEIFS('Raw Data'!$S:$S,'Raw Data'!$D:$D,$A10) -> 96.139286 | G10: =AVERAGEIFS('Raw Data'!$P:$P,'Raw Data'!$D:$D,$A10) -> 0.93928571 | H10: =D10/D6-1 -> -0.18189044 | I10: =E10/E6-1 -> -0.22734097
A11: 2024 Q3 | B11: =COUNTIFS('Raw Data'!$D:$D,$A11) -> 16 | C11: =SUMIFS('Raw Data'!$E:$E,'Raw Data'!$D:$D,$A11) -> 16 | D11: =SUMIFS('Raw Data'!$N:$N,'Raw Data'!$D:$D,$A11) -> 11138944 | E11: =IF(C11=0,"",D11/C11) -> 696184 | F11: =AVERAGEIFS('Raw Data'!$S:$S,'Raw Data'!$D:$D,$A11) -> 70.989375 | G11: =AVERAGEIFS('Raw Data'!$P:$P,'Raw Data'!$D:$D,$A11) -> 0.863125 | H11: =D11/D7-1 -> 0.41202525 | I11: =E11/E7-1 -> 0.41202525
A12: 2024 Q4 | B12: =COUNTIFS('Raw Data'!$D:$D,$A12) -> 20 | C12: =SUMIFS('Raw Data'!$E:$E,'Raw Data'!$D:$D,$A12) -> 20 | D12: =SUMIFS('Raw Data'!$N:$N,'Raw Data'!$D:$D,$A12) -> 16263058 | E12: =IF(C12=0,"",D12/C12) -> 813152.91 | F12: =AVERAGEIFS('Raw Data'!$S:$S,'Raw Data'!$D:$D,$A12) -> 79.3545 | G12: =AVERAGEIFS('Raw Data'!$P:$P,'Raw Data'!$D:$D,$A12) -> 0.861 | H12: =D12/D8-1 -> 0.015126528 | I12: =E12/E8-1 -> 0.31966449
A13: 2025 Q1 | B13: =COUNTIFS('Raw Data'!$D:$D,$A13) -> 14 | C13: =SUMIFS('Raw Data'!$E:$E,'Raw Data'!$D:$D,$A13) -> 14 | D13: =SUMIFS('Raw Data'!$N:$N,'Raw Data'!$D:$D,$A13) -> 20953480 | E13: =IF(C13=0,"",D13/C13) -> 1496677.2 | F13: =AVERAGEIFS('Raw Data'!$S:$S,'Raw Data'!$D:$D,$A13) -> 112.83286 | G13: =AVERAGEIFS('Raw Data'!$P:$P,'Raw Data'!$D:$D,$A13) -> 0.96071429 | H13: =D13/D9-1 -> 0.95431156 | I13: =E13/E9-1 -> 1.7918737
A14: 2025 Q2 | B14: =COUNTIFS('Raw Data'!$D:$D,$A14) -> 13 | C14: =SUMIFS('Raw Data'!$E:$E,'Raw Data'!$D:$D,$A14) -> 13 | D14: =SUMIFS('Raw Data'!$N:$N,'Raw Data'!$D:$D,$A14) -> 23617202 | E14: =IF(C14=0,"",D14/C14) -> 1816707.8 | F14: =AVERAGEIFS('Raw Data'!$S:$S,'Raw Data'!$D:$D,$A14) -> 138.63692 | G14: =AVERAGEIFS('Raw Data'!$P:$P,'Raw Data'!$D:$D,$A14) -> 0.90923077 | H14: =D14/D10-1 -> 0.078687142 | I14: =E14/E10-1 -> 0.49356681
A15: 2025 Q3 | B15: =COUNTIFS('Raw Data'!$D:$D,$A15) -> 15 | C15: =SUMIFS('Raw Data'!$E:$E,'Raw Data'!$D:$D,$A15) -> 16 | D15: =SUMIFS('Raw Data'!$N:$N,'Raw Data'!$D:$D,$A15) -> 23319938 | E15: =IF(C15=0,"",D15/C15) -> 1457496.1 | F15: =AVERAGEIFS('Raw Data'!$S:$S,'Raw Data'!$D:$D,$A15) -> 126.41533 | G15: =AVERAGEIFS('Raw Data'!$P:$P,'Raw Data'!$D:$D,$A15) -> 0.918 | H15: =D15/D11-1 -> 1.0935502 | I15: =E15/E11-1 -> 1.0935502
A16: 2025 Q4 | B16: =COUNTIFS('Raw Data'!$D:$D,$A16) -> 9 | C16: =SUMIFS('Raw Data'!$E:$E,'Raw Data'!$D:$D,$A16) -> 9 | D16: =SUMIFS('Raw Data'!$N:$N,'Raw Data'!$D:$D,$A16) -> 19385561 | E16: =IF(C16=0,"",D16/C16) -> 2153951.2 | F16: =AVERAGEIFS('Raw Data'!$S:$S,'Raw Data'!$D:$D,$A16) -> 158.07333 | G16: =AVERAGEIFS('Raw Data'!$P:$P,'Raw Data'!$D:$D,$A16) -> 0.88222222 | H16: =D16/D12-1 -> 0.19199974 | I16: =E16/E12-1 -> 1.6488883
A17: 2026 Q1 | B17: =COUNTIFS('Raw Data'!$D:$D,$A17) -> 13 | C17: =SUMIFS('Raw Data'!$E:$E,'Raw Data'!$D:$D,$A17) -> 13 | D17: =SUMIFS('Raw Data'!$N:$N,'Raw Data'!$D:$D,$A17) -> 14032828 | E17: =IF(C17=0,"",D17/C17) -> 1079448.3 | F17: =AVERAGEIFS('Raw Data'!$S:$S,'Raw Data'!$D:$D,$A17) -> 104.37077 | G17: =AVERAGEIFS('Raw Data'!$P:$P,'Raw Data'!$D:$D,$A17) -> 0.90692308 | H17: =D17/D13-1 -> -0.33028656 | I17: =E17/E13-1 -> -0.27877014
A18: 2026 Q2 | B18: =COUNTIFS('Raw Data'!$D:$D,$A18) -> 9 | C18: =SUMIFS('Raw Data'!$E:$E,'Raw Data'!$D:$D,$A18) -> 9 | D18: =SUMIFS('Raw Data'!$N:$N,'Raw Data'!$D:$D,$A18) -> 10390354 | E18: =IF(C18=0,"",D18/C18) -> 1154483.8 | F18: =AVERAGEIFS('Raw Data'!$S:$S,'Raw Data'!$D:$D,$A18) -> 124.34 | G18: =AVERAGEIFS('Raw Data'!$P:$P,'Raw Data'!$D:$D,$A18) -> 0.88111111 | H18: =D18/D14-1 -> -0.56005141 | I18: =E18/E14-1 -> -0.36451871
A20: Notes: YoY is blank for all 2023 quarters (no 2022 comparison in scope). Total Gross = Avg. Gross per Show multiplied by Number of Shows, summed across engagements.

Sheet Exhibit 4 - Like-for-Like
A1: Exhibit 4 | Like-for-Like Same-Venue Pricing, 2025 to 2026
A2: Latest year-over-year cut. Each venue is compared to itself in the same quarter (Q1 or Q2), 2025 vs 2026. Same venue, same quarter, one year apart, so the comparison is fully like-for-like.
A4: Venue | B4: City | C4: Qtr | D4: Window | E4: Gap | F4: First Avg Tkt | G4: Latest Avg Tkt | H4: Avg Tkt Δ | I4: First Top Tkt | J4: Latest Top Tkt | K4: Top Tkt Δ | L4: First Gross/Show | M4: Latest Gross/Show | N4: Gross/Show Δ
A5: KeyBank Center | B5: Buffalo | C5: Q1 | D5: 2025–2026 | E5: 1y | F5: 90.91 | G5: 120.93 | H5: =G5/F5-1 -> 0.3302167 | I5: 400 | J5: 400 | K5: =J5/I5-1 -> 0 | L5: 1170770 | M5: 902970 | N5: =M5/L5-1 -> -0.22873835
A6: CHI Health Center Omaha | B6: Omaha | C6: Q2 | D6: 2025–2026 | E6: 1y | F6: 81.04 | G6: 100.23 | H6: =G6/F6-1 -> 0.23679664 | I6: 250 | J6: 400 | K6: =J6/I6-1 -> 0.6 | L6: 881850 | M6: 846384.17 | N6: =M6/L6-1 -> -0.040217531
A7: Spectrum Center | B7: Charlotte | C7: Q1 | D7: 2025–2026 | E7: 1y | F7: 88.45 | G7: 100.77 | H7: =G7/F7-1 -> 0.13928773 | I7: 303.5 | J7: 100.77 | K7: =J7/I7-1 -> -0.66797364 | L7: 1213566 | M7: 893495.6 | N7: =M7/L7-1 -> -0.26374371
A8: Frost Bank Center | B8: San Antonio | C8: Q1 | D8: 2025–2026 | E8: 1y | F8: 105.4 | G8: 117.83 | H8: =G8/F8-1 -> 0.11793169 | I8: 35 | J8: 500 | K8: =J8/I8-1 -> 13.285714 | L8: 1615820 | M8: 1665318 | N8: =M8/L8-1 -> 0.030633363
A9: American Airlines Center | B9: Dallas | C9: Q1 | D9: 2025–2026 | E9: 1y | F9: 109.7 | G9: 117.43 | H9: =G9/F9-1 -> 0.070464904 | I9: 400 | J9: 800 | K9: =J9/I9-1 -> 1 | L9: 1440685 | M9: 1190420 | N9: =M9/L9-1 -> -0.1737125
A10: Golden 1 Center | B10: Sacramento | C10: Q2 | D10: 2025–2026 | E10: 1y | F10: 126.32 | G10: 135.07 | H10: =G10/F10-1 -> 0.069268524 | I10: 500 | J10: 800 | K10: =J10/I10-1 -> 0.6 | L10: 1697100 | M10: 1484719 | N10: =M10/L10-1 -> -0.12514347
A11: State Farm Arena | B11: Atlanta | C11: Q1 | D11: 2025–2026 | E11: 1y | F11: 101.23 | G11: 105.42 | H11: =G11/F11-1 -> 0.041390892 | I11: 250 | J11: 750 | K11: =J11/I11-1 -> 2 | L11: 1299337.5 | M11: 1280370 | N11: =M11/L11-1 -> -0.014597824
A12: BOK Center | B12: Tulsa | C12: Q2 | D12: 2025–2026 | E12: 1y | F12: 94.5 | G12: 92.15 | H12: =G12/F12-1 -> -0.024867725 | I12: 300 | J12: 400 | K12: =J12/I12-1 -> 0.33333333 | L12: 780180 | M12: 518620.98 | N12: =M12/L12-1 -> -0.33525471
A13: Dickies Arena | B13: Fort Worth | C13: Q2 | D13: 2025–2026 | E13: 1y | F13: 130.31 | G13: 107.98 | H13: =G13/F13-1 -> -0.1713606 | I13: 554 | J13: 619 | K13: =J13/I13-1 -> 0.11732852 | L13: 1493662 | M13: 1069191 | N13: =M13/L13-1 -> -0.28418143
A14: T-Mobile Arena | B14: Las Vegas | C14: Q2 | D14: 2025–2026 | E14: 1y | F14: 207.92 | G14: 140.35 | H14: =G14/F14-1 -> -0.32498076 | I14: 1368.5 | J14: 1641 | K14: =J14/I14-1 -> 0.19912313 | L14: 3480131 | M14: 1963923 | N14: =M14/L14-1 -> -0.43567555
A15: MEDIAN | H15: =MEDIAN(H5:H14) -> 0.069866714 | K15: =MEDIAN(K5:K14) -> 0.46666667 | N15: =MEDIAN(N5:N14) -> -0.20122543
A16: SHARE POSITIVE | H16: =COUNTIF(H5:H14,">0")/COUNT(H5:H14) -> 0.7 | K16: =COUNTIF(K5:K14,">0")/COUNT(K5:K14) -> 0.8 | N16: =COUNTIF(N5:N14,">0")/COUNT(N5:N14) -> 0.1
A18: Takeaway: on the latest 2025 to 2026 like-for-like, ticket pricing held up. The median venue raised its average ticket and its top ticket, with most venues positive on both. Gross per show declined at most venues over the same window, driven by about a fifth fewer tickets sold per show (smaller configurations and event-type mix at several arenas, with some genuine capacity softening). Read this as price per seat staying firm into 2026, not as box-office growth.
A21: Method notes: blue cells are sourced Pollstar per-engagement averages. Source: Pollstar Data Cloud, Boxoffice, Promoter = World Wrestling Entertainment, accessed Jun 2026. Top Tkt = Ticket Price Max. Sample is 10 venue comparisons; each point is a single engagement, so individual rows are card and configuration dependent. The Frost Bank top-ticket figure reflects a premium tier added in 2026 and is an outlier; the median and share-positive lines, not any single row, carry the read. 2026 covers Q1 to Q2.

Sheet Raw Data
A1: Event Date | B1: Year | C1: Quarter | D1: Year-Qtr | E1: Shows | F1: Headliner | G1: Support | H1: Venue | I1: City | J1: State | K1: Country | L1: Avg. Tickets Sold | M1: Avg. Gross / Show (USD) | N1: Engagement Gross (USD) | O1: Avg. Capacity | P1: Capacity Sold % | Q1: Min Ticket (USD) | R1: Max Ticket (USD) | S1: Avg. Ticket (USD)
A2: 44928 | B2: =YEAR(A2) -> 2023 | C2: ="Q"&ROUNDUP(MONTH(A2)/3,0) -> Q1 | D2: =B2&" Q"&ROUNDUP(MONTH(A2)/3,0) -> 2023 Q1 | E2: 1 | F2: World Wrestling Entertainment | G2: Matt Riddle, Bobby Lashley, Seth Rollins, Bianca Belair | H2: Bridgestone Arena | I2: Nashville | J2: Tennessee | K2: United States | L2: 9762 | M2: 448873.15 | N2: =E2*M2 -> 448873.15 | O2: 10452 | P2: 0.93 | Q2: 24.7 | R2: 137 | S2: 45.98
A3: 44932 | B3: =YEAR(A3) -> 2023 | C3: ="Q"&ROUNDUP(MONTH(A3)/3,0) -> Q1 | D3: =B3&" Q"&ROUNDUP(MONTH(A3)/3,0) -> 2023 Q1 | E3: 1 | F3: World Wrestling Entertainment | G3: Drew Mcintyre, The New Day, The Usos, Liv Morgan, Sami Zayn | H3: FedExForum | I3: Memphis | J3: Tennessee | K3: United States | L3: 9083 | M3: 437038.5 | N3: =E3*M3 -> 437038.5 | O3: 12619 | P3: 0.71 | Q3: 20 | R3: 115 | S3: 48.12
A4: 44935 | B4: =YEAR(A4) -> 2023 | C4: ="Q"&ROUNDUP(MONTH(A4)/3,0) -> Q1 | D4: =B4&" Q"&ROUNDUP(MONTH(A4)/3,0) -> 2023 Q1 | E4: 1 | F4: World Wrestling Entertainment | G4: Kevin Owens, Roman Reigns, Baron Corbin, Jey Uso | H4: Legacy Arena at the BJCC | I4: Birmingham | J4: Alabama | K4: United States | L4: 7094 | M4: 310592 | N4: =E4*M4 -> 310592 | O4: 7136 | P4: 0.99 | Q4: 20 | R4: 110 | S4: 43.78
A5: 44946 | B5: =YEAR(A5) -> 2023 | C5: ="Q"&ROUNDUP(MONTH(A5)/3,0) -> Q1 | D5: =B5&" Q"&ROUNDUP(MONTH(A5)/3,0) -> 2023 Q1 | E5: 1 | F5: World Wrestling Entertainment | H5: Little Caesars Arena | I5: Detroit | J5: Michigan | K5: United States | L5: 13466 | M5: 625642 | N5: =E5*M5 -> 625642 | O5: 14000 | P5: 0.96 | Q5: 25 | R5: 120 | S5: 46.46
A6: 44949 | B6: =YEAR(A6) -> 2023 | C6: ="Q"&ROUNDUP(MONTH(A6)/3,0) -> Q1 | D6: =B6&" Q"&ROUNDUP(MONTH(A6)/3,0) -> 2023 Q1 | E6: 1 | F6: World Wrestling Entertainment | H6: Wells Fargo Center | I6: Philadelphia | J6: Pennsylvania | K6: United States | L6: 13528 | M6: 1181835 | N6: =E6*M6 -> 1181835 | O6: 13528 | P6: 1 | Q6: 20 | R6: 500 | S6: 87.36
A7: 44956 | B7: =YEAR(A7) -> 2023 | C7: ="Q"&ROUNDUP(MONTH(A7)/3,0) -> Q1 | D7: =B7&" Q"&ROUNDUP(MONTH(A7)/3,0) -> 2023 Q1 | E7: 1 | F7: World Wrestling Entertainment | G7: Matt Riddle, Bobby Lashley, Seth Rollins, Bianca Belair | H7: BOK Center | I7: Tulsa | J7: Oklahoma | K7: United States | L7: 5734 | M7: 289938.5 | N7: =E7*M7 -> 289938.5 | O7: 11992 | P7: 0.47 | Q7: 24 | R7: 114 | S7: 50.56
A8: 44961 | B8: =YEAR(A8) -> 2023 | C8: ="Q"&ROUNDUP(MONTH(A8)/3,0) -> Q1 | D8: =B8&" Q"&ROUNDUP(MONTH(A8)/3,0) -> 2023 Q1 | E8: 1 | F8: World Wrestling Entertainment | G8: Bron Breakker, Grayson Waller | H8: Spectrum Center | I8: Charlotte | J8: North Carolina | K8: United States | L8: 5462 | M8: 245698.98 | N8: =E8*M8 -> 245698.98 | O8: 6008 | P8: 0.9 | Q8: 20 | R8: 150 | S8: 44.98
A9: 44963 | B9: =YEAR(A9) -> 2023 | C9: ="Q"&ROUNDUP(MONTH(A9)/3,0) -> Q1 | D9: =B9&" Q"&ROUNDUP(MONTH(A9)/3,0) -> 2023 Q1 | E9: 1 | F9: World Wrestling Entertainment | G9: Seth Rollins, Austin Theory, Bianca Belair, Becky Lynch | H9: Amway Center | I9: Orlando | J9: Florida | K9: United States | L9: 9453 | M9: 414498.5 | N9: =E9*M9 -> 414498.5 | O9: 11411 | P9: 0.82 | Q9: 20 | R9: 120 | S9: 43.85
A10: 44967 | B10: =YEAR(A10) -> 2023 | C10: ="Q"&ROUNDUP(MONTH(A10)/3,0) -> Q1 | D10: =B10&" Q"&ROUNDUP(MONTH(A10)/3,0) -> 2023 Q1 | E10: 1 | F10: World Wrestling Entertainment | H10: Mohegan Sun Arena | I10: Uncasville | J10: Connecticut | K10: United States | L10: 5752 | M10: 311110 | N10: =E10*M10 -> 311110 | O10: 5752 | P10: 1 | Q10: 20 | R10: 130 | S10: 54.09
A11: 44970 | B11: =YEAR(A11) -> 2023 | C11: ="Q"&ROUNDUP(MONTH(A11)/3,0) -> Q1 | D11: =B11&" Q"&ROUNDUP(MONTH(A11)/3,0) -> 2023 Q1 | E11: 1 | F11: World Wrestling Entertainment | G11: Seth Rollins, Austin Theory, Bobby Lashley, Bianca Belair | H11: Barclays Center | I11: Brooklyn | J11: New York | K11: United States | L11: 11739 | M11: 664282.5 | N11: =E11*M11 -> 664282.5 | O11: 13215 | P11: 0.88 | Q11: 20 | R11: 150 | S11: 56.59
A12: 44974 | B12: =YEAR(A12) -> 2023 | C12: ="Q"&ROUNDUP(MONTH(A12)/3,0) -> Q1 | D12: =B12&" Q"&ROUNDUP(MONTH(A12)/3,0) -> 2023 Q1 | E12: 1 | F12: World Wrestling Entertainment | G12: Asuka, Liv Morgan, Ronda Rousey, Sami Zayn | H12: Bell Centre | I12: Montreal | J12: Quebec | K12: Canada | L12: 11744 | M12: 649680.63 | N12: =E12*M12 -> 649680.63 | O12: 11746 | P12: 0.99 | Q12: 55.32 | R12: 55.32 | S12: 55.32
A13: 44975 | B13: =YEAR(A13) -> 2023 | C13: ="Q"&ROUNDUP(MONTH(A13)/3,0) -> Q1 | D13: =B13&" Q"&ROUNDUP(MONTH(A13)/3,0) -> 2023 Q1 | E13: 1 | F13: World Wrestling Entertainment | G13: Asuka, Liv Morgan, Brock Lesnar, Bobby Lashley | H13: Bell Centre | I13: Montreal | J13: Quebec | K13: Canada | L13: 13807 | M13: 997636.68 | N13: =E13*M13 -> 997636.68 | O13: 13809 | P13: 0.99 | Q13: 72.25 | R13: 72.25 | S13: 72.26
A14: 44977 | B14: =YEAR(A14) -> 2023 | C14: ="Q"&ROUNDUP(MONTH(A14)/3,0) -> Q1 | D14: =B14&" Q"&ROUNDUP(MONTH(A14)/3,0) -> 2023 Q1 | E14: 1 | F14: World Wrestling Entertainment | H14: Canadian Tire Centre | I14: Ottawa | J14: Ontario | K14: Canada | L14: 7663 | M14: 312662.09 | N14: =E14*M14 -> 312662.09 | O14: 8604 | P14: 0.89 | Q14: 18.55 | R14: 92.74 | S14: 40.8
A15: 44981 | B15: =YEAR(A15) -> 2023 | C15: ="Q"&ROUNDUP(MONTH(A15)/3,0) -> Q1 | D15: =B15&" Q"&ROUNDUP(MONTH(A15)/3,0) -> 2023 Q1 | E15: 1 | F15: World Wrestling Entertainment | G15: Charlotte Flair, Rhea Ripley, Rey Mysterio, Karrion Kross, Braun Strowmann, Ricochet | H15: Ford Center | I15: Evansville | J15: Indiana | K15: United States | L15: 7530 | M15: 334188 | N15: =E15*M15 -> 334188 | O15: 7530 | P15: 1 | Q15: 25 | R15: 115 | S15: 44.38
A16: 44983 | B16: =YEAR(A16) -> 2023 | C16: ="Q"&ROUNDUP(MONTH(A16)/3,0) -> Q1 | D16: =B16&" Q"&ROUNDUP(MONTH(A16)/3,0) -> 2023 Q1 | E16: 1 | F16: World Wrestling Entertainment | H16: BMO Harris Bank Center | I16: Rockford | J16: Illinois | K16: United States | L16: 4431 | M16: 231642.45 | N16: =E16*M16 -> 231642.45 | O16: 7307 | P16: 0.6 | Q16: 20 | R16: 110 | S16: 52.28
A17: 44988 | B17: =YEAR(A17) -> 2023 | C17: ="Q"&ROUNDUP(MONTH(A17)/3,0) -> Q1 | D17: =B17&" Q"&ROUNDUP(MONTH(A17)/3,0) -> 2023 Q1 | E17: 1 | F17: World Wrestling Entertainment | G17: Braun Strowmann, Bray Wyatt, Gunther, Ronda Rousey | H17: Capital One Arena | I17: Washington | J17: District of Columbia | K17: United States | L17: 11998 | M17: 727358.25 | N17: =E17*M17 -> 727358.25 | O17: 12676 | P17: 0.94 | Q17: 20 | R17: 125 | S17: 60.62
A18: 44989 | B18: =YEAR(A18) -> 2023 | C18: ="Q"&ROUNDUP(MONTH(A18)/3,0) -> Q1 | D18: =B18&" Q"&ROUNDUP(MONTH(A18)/3,0) -> 2023 Q1 | E18: 1 | F18: World Wrestling Entertainment | G18: Roman Reigns, Sami Zayn, Braun Strowmann, Drew Mcintyre | H18: Coca-Cola Coliseum | I18: Toronto | J18: Ontario | K18: Canada | L18: 7294 | M18: 349709.25 | N18: =E18*M18 -> 349709.25 | O18: 7294 | P18: 1 | Q18: 18.36 | R18: 117.5 | S18: 47.94
A19: 44991 | B19: =YEAR(A19) -> 2023 | C19: ="Q"&ROUNDUP(MONTH(A19)/3,0) -> Q1 | D19: =B19&" Q"&ROUNDUP(MONTH(A19)/3,0) -> 2023 Q1 | E19: 1 | F19: World Wrestling Entertainment | G19: John Cena, Kevin Owens, Dolph Ziggler, Austin Theory | H19: TD Garden | I19: Boston | J19: Massachusetts | K19: United States | L19: 12239 | M19: 884269 | N19: =E19*M19 -> 884269 | O19: 13169 | P19: 0.92 | Q19: 20 | R19: 150 | S19: 72.25
A20: 44995 | B20: =YEAR(A20) -> 2023 | C20: ="Q"&ROUNDUP(MONTH(A20)/3,0) -> Q1 | D20: =B20&" Q"&ROUNDUP(MONTH(A20)/3,0) -> 2023 Q1 | E20: 1 | F20: World Wrestling Entertainment | G20: Alexa Bliss, The Usos | H20: PPG Paints Arena | I20: Pittsburgh | J20: Pennsylvania | K20: United States | L20: 9019 | M20: 457689.1 | N20: =E20*M20 -> 457689.1 | O20: 13143 | P20: 0.68 | Q20: 20 | R20: 125 | S20: 50.75
A21: 44997 | B21: =YEAR(A21) -> 2023 | C21: ="Q"&ROUNDUP(MONTH(A21)/3,0) -> Q1 | D21: =B21&" Q"&ROUNDUP(MONTH(A21)/3,0) -> 2023 Q1 | E21: 1 | F21: World Wrestling Entertainment | G21: Drew Mcintyre, Braun Strowmann, Charlotte Flair, Sami Zayn | H21: MGM Grand Garden Arena | I21: Las Vegas | J21: Nevada | K21: United States | L21: 10529 | M21: 685715 | N21: =E21*M21 -> 685715 | O21: 13718 | P21: 0.76 | Q21: 26 | R21: 206 | S21: 65.13
A22: 44997 | B22: =YEAR(A22) -> 2023 | C22: ="Q"&ROUNDUP(MONTH(A22)/3,0) -> Q1 | D22: =B22&" Q"&ROUNDUP(MONTH(A22)/3,0) -> 2023 Q1 | E22: 1 | F22: World Wrestling Entertainment | H22: Madison Square Garden | I22: New York | J22: New York | K22: United States | L22: 10529 | M22: 685715 | N22: =E22*M22 -> 685715 | O22: 13718 | P22: 0.76 | Q22: 26 | R22: 206 | S22: 65.13
A23: 45003 | B23: =YEAR(A23) -> 2023 | C23: ="Q"&ROUNDUP(MONTH(A23)/3,0) -> Q1 | D23: =B23&" Q"&ROUNDUP(MONTH(A23)/3,0) -> 2023 Q1 | E23: 1 | F23: World Wrestling Entertainment | H23: Fiserv Forum | I23: Milwaukee | J23: Wisconsin | K23: United States | L23: 5953 | M23: 276757 | N23: =E23*M23 -> 276757 | O23: 11546 | P23: 0.51 | Q23: 30 | R23: 115 | S23: 46.49
A24: 45009 | B24: =YEAR(A24) -> 2023 | C24: ="Q"&ROUNDUP(MONTH(A24)/3,0) -> Q1 | D24: =B24&" Q"&ROUNDUP(MONTH(A24)/3,0) -> 2023 Q1 | E24: 1 | F24: World Wrestling Entertainment | G24: Cody Rhodes, Kevin Owens, Sami Zayn, Roman Reigns | H24: MGM Grand Garden Arena | I24: Las Vegas | J24: Nevada | K24: United States | L24: 9409 | M24: 439268 | N24: =E24*M24 -> 439268 | O24: 11088 | P24: 0.84 | Q24: 25.8 | R24: 140.25 | S24: 46.69
A25: 45009 | B25: =YEAR(A25) -> 2023 | C25: ="Q"&ROUNDUP(MONTH(A25)/3,0) -> Q1 | D25: =B25&" Q"&ROUNDUP(MONTH(A25)/3,0) -> 2023 Q1 | E25: 1 | F25: World Wrestling Entertainment | H25: BMO Harris Bank Center | I25: Rockford | J25: Illinois | K25: United States | L25: 5206 | M25: 285881 | N25: =E25*M25 -> 285881 | O25: 7306 | P25: 0.71 | Q25: 20 | R25: 115 | S25: 54.91
A26: 45012 | B26: =YEAR(A26) -> 2023 | C26: ="Q"&ROUNDUP(MONTH(A26)/3,0) -> Q1 | D26: =B26&" Q"&ROUNDUP(MONTH(A26)/3,0) -> 2023 Q1 | E26: 1 | F26: World Wrestling Entertainment | G26: "Stone Cold" Steve Austin, Triple H, Chris Jericho, Randy Orton | H26: Footprint Center | I26: Phoenix | J26: Arizona | K26: United States | L26: 10857 | M26: 572538 | N26: =E26*M26 -> 572538 | O26: 11001 | P26: 0.98 | Q26: 20 | R26: 500 | S26: 52.73
A27: 45016 | B27: =YEAR(A27) -> 2023 | C27: ="Q"&ROUNDUP(MONTH(A27)/3,0) -> Q1 | D27: =B27&" Q"&ROUNDUP(MONTH(A27)/3,0) -> 2023 Q1 | E27: 1 | F27: World Wrestling Entertainment | H27: Crypto.com Arena | I27: Los Angeles | J27: California | K27: United States | L27: 13050 | M27: 823440 | N27: =E27*M27 -> 823440 | O27: 13050 | P27: 1 | Q27: 25.9 | R27: 310.5 | S27: 63.1
A28: 45017 | B28: =YEAR(A28) -> 2023 | C28: ="Q"&ROUNDUP(MONTH(A28)/3,0) -> Q2 | D28: =B28&" Q"&ROUNDUP(MONTH(A28)/3,0) -> 2023 Q2 | E28: 1 | F28: World Wrestling Entertainment | H28: Crypto.com Arena | I28: Los Angeles | J28: California | K28: United States | L28: 7816 | M28: 307923 | N28: =E28*M28 -> 307923 | O28: 8989 | P28: 0.86 | Q28: 20.7 | R28: 103.5 | S28: 39.4
A29: 45017 | B29: =YEAR(A29) -> 2023 | C29: ="Q"&ROUNDUP(MONTH(A29)/3,0) -> Q2 | D29: =B29&" Q"&ROUNDUP(MONTH(A29)/3,0) -> 2023 Q2 | E29: 2 | F29: World Wrestling Entertainment | G29: Roman Reigns, Cody Rhodes, Asuka, Bianca Belair, Charlotte Flair, Rhea Ripley | H29: SoFi Stadium | I29: Inglewood | J29: California | K29: United States | L29: 68397 | M29: 9874535.5 | N29: =E29*M29 -> 19749071 | O29: 73252 | P29: 0.93 | Q29: 25 | R29: 5000 | S29: 144.37
A30: 45019 | B30: =YEAR(A30) -> 2023 | C30: ="Q"&ROUNDUP(MONTH(A30)/3,0) -> Q2 | D30: =B30&" Q"&ROUNDUP(MONTH(A30)/3,0) -> 2023 Q2 | E30: 1 | F30: World Wrestling Entertainment | H30: Crypto.com Arena | I30: Los Angeles | J30: California | K30: United States | L30: 13616 | M30: 920190 | N30: =E30*M30 -> 920190 | O30: 13616 | P30: 1 | Q30: 25.9 | R30: 310.5 | S30: 67.58
A31: 45023 | B31: =YEAR(A31) -> 2023 | C31: ="Q"&ROUNDUP(MONTH(A31)/3,0) -> Q2 | D31: =B31&" Q"&ROUNDUP(MONTH(A31)/3,0) -> 2023 Q2 | E31: 1 | F31: World Wrestling Entertainment | G31: Kevin Owens, Drew Mcintyre, Xavier Woods, Braun Strowmann, The Usos | H31: Moda Center | I31: Portland | J31: Oregon | K31: United States | L31: 9314 | M31: 482774 | N31: =E31*M31 -> 482774 | O31: 12071 | P31: 0.77 | Q31: 20 | R31: 110 | S31: 51.83
A32: 45026 | B32: =YEAR(A32) -> 2023 | C32: ="Q"&ROUNDUP(MONTH(A32)/3,0) -> Q2 | D32: =B32&" Q"&ROUNDUP(MONTH(A32)/3,0) -> 2023 Q2 | E32: 1 | F32: World Wrestling Entertainment | G32: Becky Lynch, Seth Rollins, Bianca Belair, Bobby Lashley, Kevin Ownes | H32: Climate Pledge Arena | I32: Seattle | J32: Washington | K32: United States | L32: 9906 | M32: 579150.5 | N32: =E32*M32 -> 579150.5 | O32: 10074 | P32: 0.98 | Q32: 25.5 | R32: 130.5 | S32: 58.46
A33: 45033 | B33: =YEAR(A33) -> 2023 | C33: ="Q"&ROUNDUP(MONTH(A33)/3,0) -> Q2 | D33: =B33&" Q"&ROUNDUP(MONTH(A33)/3,0) -> 2023 Q2 | E33: 1 | F33: World Wrestling Entertainment | G33: Brock Lesnar, Bianca Belair, Cody Rhodes, Austin Theory | H33: Simmons Bank Arena | I33: North Little Rock | J33: Arkansas | K33: United States | L33: 7640 | M33: 384749 | N33: =E33*M33 -> 384749 | O33: 12000 | P33: 0.63 | Q33: 24 | R33: 124 | S33: 50.36
A34: 45040 | B34: =YEAR(A34) -> 2023 | C34: ="Q"&ROUNDUP(MONTH(A34)/3,0) -> Q2 | D34: =B34&" Q"&ROUNDUP(MONTH(A34)/3,0) -> 2023 Q2 | E34: 1 | F34: World Wrestling Entertainment | G34: Damian Priest, Rey Mysterio, Cody Rhodes, Finn Balor | H34: Allstate Arena | I34: Rosemont | J34: Illinois | K34: United States | L34: 12446 | M34: 619116.5 | N34: =E34*M34 -> 619116.5 | O34: 12446 | P34: 1 | Q34: 20 | R34: 150 | S34: 49.74
A35: 45047 | B35: =YEAR(A35) -> 2023 | C35: ="Q"&ROUNDUP(MONTH(A35)/3,0) -> Q2 | D35: =B35&" Q"&ROUNDUP(MONTH(A35)/3,0) -> 2023 Q2 | E35: 1 | F35: World Wrestling Entertainment | G35: Cody Rhodes, Brock Lesnar, Seth Rollins, Bianca Belair, Becky Lynch | H35: Dickies Arena | I35: Fort Worth | J35: Texas | K35: United States | L35: 11199 | M35: 506369 | N35: =E35*M35 -> 506369 | O35: 11457 | P35: 0.97 | Q35: 24 | R35: 129 | S35: 45.22
A36: 45057 | B36: =YEAR(A36) -> 2023 | C36: ="Q"&ROUNDUP(MONTH(A36)/3,0) -> Q2 | D36: =B36&" Q"&ROUNDUP(MONTH(A36)/3,0) -> 2023 Q2 | E36: 1 | F36: World Wrestling Entertainment | H36: Thompson-Boling Arena | I36: Knoxville | J36: Tennessee | K36: United States | L36: 9379 | M36: 495462.5 | N36: =E36*M36 -> 495462.5 | O36: 9885 | P36: 0.94 | Q36: 20 | R36: 130 | S36: 52.83
A37: 45058 | B37: =YEAR(A37) -> 2023 | C37: ="Q"&ROUNDUP(MONTH(A37)/3,0) -> Q2 | D37: =B37&" Q"&ROUNDUP(MONTH(A37)/3,0) -> 2023 Q2 | E37: 1 | F37: World Wrestling Entertainment | H37: Thompson-Boling Arena | I37: Knoxville | J37: Tennessee | K37: United States | L37: 9379 | M37: 528902.5 | N37: =E37*M37 -> 528902.5 | O37: 9885 | P37: 0.94 | Q37: 20 | R37: 130 | S37: 56.39
A38: 45079 | B38: =YEAR(A38) -> 2023 | C38: ="Q"&ROUNDUP(MONTH(A38)/3,0) -> Q2 | D38: =B38&" Q"&ROUNDUP(MONTH(A38)/3,0) -> 2023 Q2 | E38: 1 | F38: World Wrestling Entertainment | G38: Zelina Vega, Lacey Evans, Bianca Belair, The Usos | H38: Mohegan Sun Arena At Casey Plaza | I38: Wilkes-Barre | J38: Pennsylvania | K38: United States | L38: 6828 | M38: 372623 | N38: =E38*M38 -> 372623 | O38: 6828 | P38: 1 | Q38: 24.5 | R38: 139.5 | S38: 54.57
A39: 45081 | B39: =YEAR(A39) -> 2023 | C39: ="Q"&ROUNDUP(MONTH(A39)/3,0) -> Q2 | D39: =B39&" Q"&ROUNDUP(MONTH(A39)/3,0) -> 2023 Q2 | E39: 1 | F39: World Wrestling Entertainment | H39: SNHU Arena | I39: Manchester | J39: New Hampshire | K39: United States | L39: 4861 | M39: 278707 | N39: =E39*M39 -> 278707 | O39: 5000 | P39: 0.97 | Q39: 25 | R39: 115 | S39: 57.34
A40: 45093 | B40: =YEAR(A40) -> 2023 | C40: ="Q"&ROUNDUP(MONTH(A40)/3,0) -> Q2 | D40: =B40&" Q"&ROUNDUP(MONTH(A40)/3,0) -> 2023 Q2 | E40: 1 | F40: World Wrestling Entertainment | G40: Bianca Belair, AJ Styles, The Usos, The Brawling Brutes | H40: Rupp Arena | I40: Lexington | J40: Kentucky | K40: United States | L40: 9084 | M40: 438042.5 | N40: =E40*M40 -> 438042.5 | O40: 9084 | P40: 1 | Q40: 20 | R40: 120 | S40: 48.22
A41: 45095 | B41: =YEAR(A41) -> 2023 | C41: ="Q"&ROUNDUP(MONTH(A41)/3,0) -> Q2 | D41: =B41&" Q"&ROUNDUP(MONTH(A41)/3,0) -> 2023 Q2 | E41: 1 | F41: World Wrestling Entertainment | G41: Austin Theory, Sheamus, Kevin Owens, Sami Zayn | H41: Charleston Coliseum | I41: Charleston | J41: West Virginia | K41: United States | L41: 4280 | M41: 216540 | N41: =E41*M41 -> 216540 | O41: 9153 | P41: 0.46 | Q41: 20 | R41: 110 | S41: 50.59
A42: 45096 | B42: =YEAR(A42) -> 2023 | C42: ="Q"&ROUNDUP(MONTH(A42)/3,0) -> Q2 | D42: =B42&" Q"&ROUNDUP(MONTH(A42)/3,0) -> 2023 Q2 | E42: 1 | F42: World Wrestling Entertainment | G42: Cody Rhodes, Bianca Belair, Seth Rollins, Kevin Owens | H42: Rocket Mortgage Fieldhouse | I42: Cleveland | J42: Ohio | K42: United States | L42: 9432 | M42: 561928 | N42: =E42*M42 -> 561928 | O42: 14278 | P42: 0.66 | Q42: 20 | R42: 125 | S42: 59.58
A43: 45103 | B43: =YEAR(A43) -> 2023 | C43: ="Q"&ROUNDUP(MONTH(A43)/3,0) -> Q2 | D43: =B43&" Q"&ROUNDUP(MONTH(A43)/3,0) -> 2023 Q2 | E43: 1 | F43: WWE Live | H43: Enmarket Arena | I43: Savannah | J43: Georgia | K43: United States | L43: 5977 | M43: 320630 | N43: =E43*M43 -> 320630 | O43: 6500 | P43: 0.91 | Q43: 53 | R43: 53 | S43: 53.64
A44: 45110 | B44: =YEAR(A44) -> 2023 | C44: ="Q"&ROUNDUP(MONTH(A44)/3,0) -> Q3 | D44: =B44&" Q"&ROUNDUP(MONTH(A44)/3,0) -> 2023 Q3 | E44: 1 | F44: World Wrestling Entertainment | G44: Brock Lesnar, Cody Rhodes, Becky Lynch, Rhea Ripley | H44: CFG Bank Arena | I44: Baltimore | J44: Maryland | K44: United States | L44: 8808 | M44: 589549 | N44: =E44*M44 -> 589549 | O44: 9226 | P44: 0.95 | Q44: 20 | R44: 135 | S44: 66.93
A45: 45114 | B45: =YEAR(A45) -> 2023 | C45: ="Q"&ROUNDUP(MONTH(A45)/3,0) -> Q3 | D45: =B45&" Q"&ROUNDUP(MONTH(A45)/3,0) -> 2023 Q3 | E45: 1 | F45: World Wrestling Entertainment | G45: Bianca Belair, The Usos, AJ Styles, Rey Mysterio | H45: Madison Square Garden | I45: New York | J45: New York | K45: United States | L45: 13393 | M45: 1243276 | N45: =E45*M45 -> 1243276 | O45: 13393 | P45: 1 | Q45: 31 | R45: 406 | S45: 92.83
A46: 45122 | B46: =YEAR(A46) -> 2023 | C46: ="Q"&ROUNDUP(MONTH(A46)/3,0) -> Q3 | D46: =B46&" Q"&ROUNDUP(MONTH(A46)/3,0) -> 2023 Q3 | E46: 1 | F46: World Wrestling Entertainment | G46: Seth Rollins, Finn Balor, Natalya, Rhea Ripley | H46: EagleBank Arena | I46: Fairfax | J46: Virginia | K46: United States | L46: 6492 | M46: 328914 | N46: =E46*M46 -> 328914 | O46: 7789 | P46: 0.83 | Q46: 20 | R46: 120 | S46: 50.66
A47: 45124 | B47: =YEAR(A47) -> 2023 | C47: ="Q"&ROUNDUP(MONTH(A47)/3,0) -> Q3 | D47: =B47&" Q"&ROUNDUP(MONTH(A47)/3,0) -> 2023 Q3 | E47: 1 | F47: World Wrestling Entertainment | G47: Brock Lesnar, Cody Rhodes, Seth Rollins, Becky Lynch | H47: State Farm Arena | I47: Atlanta | J47: Georgia | K47: United States | L47: 11082 | M47: 513206 | N47: =E47*M47 -> 513206 | O47: 11082 | P47: 1 | Q47: 20 | R47: 125 | S47: 46.31
A48: 45128 | B48: =YEAR(A48) -> 2023 | C48: ="Q"&ROUNDUP(MONTH(A48)/3,0) -> Q3 | D48: =B48&" Q"&ROUNDUP(MONTH(A48)/3,0) -> 2023 Q3 | E48: 1 | F48: World Wrestling Entertainment | G48: Roman Reigns, Jey Uso, Charlotte Flair, Iyo Sky | H48: Amway Center | I48: Orlando | J48: Florida | K48: United States | L48: 11458 | M48: 494954.93 | N48: =E48*M48 -> 494954.93 | O48: 12172 | P48: 0.94 | Q48: 20 | R48: 120 | S48: 43.2
A49: 45136 | B49: =YEAR(A49) -> 2023 | C49: ="Q"&ROUNDUP(MONTH(A49)/3,0) -> Q3 | D49: =B49&" Q"&ROUNDUP(MONTH(A49)/3,0) -> 2023 Q3 | E49: 1 | F49: World Wrestling Entertainment | H49: Hertz Arena | I49: Estero | J49: Florida | K49: United States | L49: 4606 | M49: 226217.25 | N49: =E49*M49 -> 226217.25 | O49: 6108 | P49: 0.75 | Q49: 18.78 | R49: 125 | S49: 49.11
A50: 45137 | B50: =YEAR(A50) -> 2023 | C50: ="Q"&ROUNDUP(MONTH(A50)/3,0) -> Q3 | D50: =B50&" Q"&ROUNDUP(MONTH(A50)/3,0) -> 2023 Q3 | E50: 1 | F50: World Wrestling Entertainment | G50: Wes Lee, Dominik Mysterio, Tiffany Stratton | H50: H-E-B Center At Cedar Park | I50: Cedar Park | J50: Texas | K50: United States | L50: 3812 | M50: 209199 | N50: =E50*M50 -> 209199 | O50: 4560 | P50: 0.83 | Q50: 20 | R50: 160 | S50: 54.88
A51: 45151 | B51: =YEAR(A51) -> 2023 | C51: ="Q"&ROUNDUP(MONTH(A51)/3,0) -> Q3 | D51: =B51&" Q"&ROUNDUP(MONTH(A51)/3,0) -> 2023 Q3 | E51: 1 | F51: World Wrestling Entertainment | G51: Seth Rollins, Cody Rhodes, Rhea Ripley, Kevin Owens | H51: Canada Life Centre | I51: Winnipeg | J51: Manitoba | K51: Canada | L51: 9716 | M51: 310376.58 | N51: =E51*M51 -> 310376.58 | O51: 10716 | P51: 0.9 | Q51: 18.98 | R51: 94.9 | S51: 31.94
A52: 45158 | B52: =YEAR(A52) -> 2023 | C52: ="Q"&ROUNDUP(MONTH(A52)/3,0) -> Q3 | D52: =B52&" Q"&ROUNDUP(MONTH(A52)/3,0) -> 2023 Q3 | E52: 1 | F52: World Wrestling Entertainment | G52: Cody Rhodes, Bianca Belair, Rhea Ripley, Seth Rollins, Sami Zayn, Kevin Owens | H52: Place Bell | I52: Laval | J52: Quebec | K52: Canada | L52: 6506 | M52: 288932.22 | N52: =E52*M52 -> 288932.22 | O52: 6512 | P52: 0.99 | Q52: 15.18 | R52: 113.88 | S52: 44.41
A53: 45159 | B53: =YEAR(A53) -> 2023 | C53: ="Q"&ROUNDUP(MONTH(A53)/3,0) -> Q3 | D53: =B53&" Q"&ROUNDUP(MONTH(A53)/3,0) -> 2023 Q3 | E53: 1 | F53: World Wrestling Entertainment | G53: Finn Balor, Damian Priest, Cody Rhodes, Sami Zayn | H53: Centre Vidéotron | I53: Quebec City | J53: Quebec | K53: Canada | L53: 10147 | M53: 368510.5 | N53: =E53*M53 -> 368510.5 | O53: 12269 | P53: 0.82 | Q53: 15.18 | R53: 87.31 | S53: 36.32
A54: 45171 | B54: =YEAR(A54) -> 2023 | C54: ="Q"&ROUNDUP(MONTH(A54)/3,0) -> Q3 | D54: =B54&" Q"&ROUNDUP(MONTH(A54)/3,0) -> 2023 Q3 | E54: 1 | F54: World Wrestling Entertainment | G54: Becky Lynch, Seth Rollins | H54: PPG Paints Arena | I54: Pittsburgh | J54: Pennsylvania | K54: United States | L54: 11680 | M54: 1161555 | N54: =E54*M54 -> 1161555 | O54: 12468 | P54: 0.93 | Q54: 25 | R54: 600 | S54: 99.45
A55: 45177 | B55: =YEAR(A55) -> 2023 | C55: ="Q"&ROUNDUP(MONTH(A55)/3,0) -> Q3 | D55: =B55&" Q"&ROUNDUP(MONTH(A55)/3,0) -> 2023 Q3 | E55: 1 | F55: World Wrestling Entertainment | G55: Charlotte Flair, Austin Theory, AJ Styles | H55: TD Garden | I55: Boston | J55: Massachusetts | K55: United States | L55: 11048 | M55: 805489 | N55: =E55*M55 -> 805489 | O55: 13229 | P55: 0.83 | Q55: 20 | R55: 160 | S55: 72.91
A56: 45180 | B56: =YEAR(A56) -> 2023 | C56: ="Q"&ROUNDUP(MONTH(A56)/3,0) -> Q3 | D56: =B56&" Q"&ROUNDUP(MONTH(A56)/3,0) -> 2023 Q3 | E56: 1 | F56: World Wrestling Entertainment | H56: Norfolk Scope Arena | I56: Norfolk | J56: Virginia | K56: United States | L56: 6798 | M56: 328873 | N56: =E56*M56 -> 328873 | O56: 6798 | P56: 1 | Q56: 20 | R56: 120 | S56: 48.38
A57: 45193 | B57: =YEAR(A57) -> 2023 | C57: ="Q"&ROUNDUP(MONTH(A57)/3,0) -> Q3 | D57: =B57&" Q"&ROUNDUP(MONTH(A57)/3,0) -> 2023 Q3 | E57: 1 | F57: World Wrestling Entertainment | G57: Seth Rollins, The Miz, Iyo Sky, Charlotte Flair | H57: Save Mart Center | I57: Fresno | J57: California | K57: United States | L57: 7744 | M57: 356780 | N57: =E57*M57 -> 356780 | O57: 10513 | P57: 0.73 | Q57: 15 | R57: 100 | S57: 46.07
A58: 45194 | B58: =YEAR(A58) -> 2023 | C58: ="Q"&ROUNDUP(MONTH(A58)/3,0) -> Q3 | D58: =B58&" Q"&ROUNDUP(MONTH(A58)/3,0) -> 2023 Q3 | E58: 1 | F58: World Wrestling Entertainment | H58: Toyota Arena | I58: Ontario | J58: California | K58: United States | L58: 7602 | M58: 400535 | N58: =E58*M58 -> 400535 | O58: 7602 | P58: 1 | Q58: 20 | R58: 125 | S58: 52.69
A59: 45199 | B59: =YEAR(A59) -> 2023 | C59: ="Q"&ROUNDUP(MONTH(A59)/3,0) -> Q3 | D59: =B59&" Q"&ROUNDUP(MONTH(A59)/3,0) -> 2023 Q3 | E59: 1 | F59: World Wrestling Entertainment | H59: Mechanics Bank Arena | I59: Bakersfield | J59: California | K59: United States | L59: 4308 | M59: 262262 | N59: =E59*M59 -> 262262 | O59: 4767 | P59: 0.9 | Q59: 20 | R59: 150 | S59: 60.88
A60: 45201 | B60: =YEAR(A60) -> 2023 | C60: ="Q"&ROUNDUP(MONTH(A60)/3,0) -> Q4 | D60: =B60&" Q"&ROUNDUP(MONTH(A60)/3,0) -> 2023 Q4 | E60: 1 | F60: World Wrestling Entertainment | G60: Gunther, Damian Priest, Jey Uso | H60: SAP Center At San Jose | I60: San Jose | J60: California | K60: United States | L60: 9624 | M60: 531394 | N60: =E60*M60 -> 531394 | O60: 11974 | P60: 0.8 | Q60: 24 | R60: 129 | S60: 55.22
A61: 45206 | B61: =YEAR(A61) -> 2023 | C61: ="Q"&ROUNDUP(MONTH(A61)/3,0) -> Q4 | D61: =B61&" Q"&ROUNDUP(MONTH(A61)/3,0) -> 2023 Q4 | E61: 1 | F61: World Wrestling Entertainment | G61: John Cena, LA Knight, Jimmy USO, Solo Sikoa | H61: Gainbridge Fieldhouse | I61: Indianapolis | J61: Indiana | K61: United States | L61: 12046 | M61: 1181229 | N61: =E61*M61 -> 1181229 | O61: 12046 | P61: 1 | Q61: 29 | R61: 554 | S61: 98.06
A62: 45212 | B62: =YEAR(A62) -> 2023 | C62: ="Q"&ROUNDUP(MONTH(A62)/3,0) -> Q4 | D62: =B62&" Q"&ROUNDUP(MONTH(A62)/3,0) -> 2023 Q4 | E62: 1 | F62: World Wrestling Entertainment | G62: John Cena, Roman Reigns, LA Knight, Solo Sikoa | H62: BOK Center | I62: Tulsa | J62: Oklahoma | K62: United States | L62: 9759 | M62: 413102.3 | N62: =E62*M62 -> 413102.3 | O62: 11874 | P62: 0.82 | Q62: 19 | R62: 114 | S62: 42.33
A63: 45215 | B63: =YEAR(A63) -> 2023 | C63: ="Q"&ROUNDUP(MONTH(A63)/3,0) -> Q4 | D63: =B63&" Q"&ROUNDUP(MONTH(A63)/3,0) -> 2023 Q4 | E63: 1 | F63: WWE Live, WWE Live | H63: Paycom Center | I63: Oklahoma City | J63: Oklahoma | K63: United States | L63: 7412 | M63: 321928.75 | N63: =E63*M63 -> 321928.75 | O63: 11114 | P63: 0.66 | Q63: 20 | R63: 105 | S63: 43.43
A64: 45219 | B64: =YEAR(A64) -> 2023 | C64: ="Q"&ROUNDUP(MONTH(A64)/3,0) -> Q4 | D64: =B64&" Q"&ROUNDUP(MONTH(A64)/3,0) -> 2023 Q4 | E64: 1 | F64: World Wrestling Entertainment | G64: John Cena, Charlotte Flair, Iyo Sky, Santos Escobar | H64: Frost Bank Center | I64: San Antonio | J64: Texas | K64: United States | L64: 13452 | M64: 593480 | N64: =E64*M64 -> 593480 | O64: 14043 | P64: 0.95 | Q64: 20 | R64: 115 | S64: 44.12
A65: 45222 | B65: =YEAR(A65) -> 2023 | C65: ="Q"&ROUNDUP(MONTH(A65)/3,0) -> Q4 | D65: =B65&" Q"&ROUNDUP(MONTH(A65)/3,0) -> 2023 Q4 | E65: 1 | F65: World Wrestling Entertainment | H65: American Airlines Center | I65: Dallas | J65: Texas | K65: United States | L65: 10839 | M65: 661292.91 | N65: =E65*M65 -> 661292.91 | O65: 12088 | P65: 0.89 | Q65: 30 | R65: 135 | S65: 61.01
A66: 45226 | B66: =YEAR(A66) -> 2023 | C66: ="Q"&ROUNDUP(MONTH(A66)/3,0) -> Q4 | D66: =B66&" Q"&ROUNDUP(MONTH(A66)/3,0) -> 2023 Q4 | E66: 1 | F66: World Wrestling Entertainment | G66: John Cena, Roman Reigns, Rey Mysterio, LA Knight | H66: Fiserv Forum | I66: Milwaukee | J66: Wisconsin | K66: United States | L66: 10857 | M66: 508035 | N66: =E66*M66 -> 508035 | O66: 10857 | P66: 1 | Q66: 30 | R66: 115 | S66: 46.79
A67: 45236 | B67: =YEAR(A67) -> 2023 | C67: ="Q"&ROUNDUP(MONTH(A67)/3,0) -> Q4 | D67: =B67&" Q"&ROUNDUP(MONTH(A67)/3,0) -> 2023 Q4 | E67: 1 | F67: World Wrestling Entertainment | H67: Mohegan Sun Arena At Casey Plaza | I67: Wilkes-Barre | J67: Pennsylvania | K67: United States | L67: 6461 | M67: 399125 | N67: =E67*M67 -> 399125 | O67: 6461 | P67: 1 | Q67: 24.5 | R67: 139.5 | S67: 61.77
A68: 45243 | B68: =YEAR(A68) -> 2023 | C68: ="Q"&ROUNDUP(MONTH(A68)/3,0) -> Q4 | D68: =B68&" Q"&ROUNDUP(MONTH(A68)/3,0) -> 2023 Q4 | E68: 1 | F68: World Wrestling Entertainment | H68: Capital One Arena | I68: Washington | J68: District of Columbia | K68: United States | L68: 8756 | M68: 604277.74 | N68: =E68*M68 -> 604277.74 | O68: 12760 | P68: 0.68 | Q68: 25 | R68: 145 | S68: 69.01
A69: 45247 | B69: =YEAR(A69) -> 2023 | C69: ="Q"&ROUNDUP(MONTH(A69)/3,0) -> Q4 | D69: =B69&" Q"&ROUNDUP(MONTH(A69)/3,0) -> 2023 Q4 | E69: 1 | F69: World Wrestling Entertainment | G69: Rey Mysterio, Charlotte Flair, LA Knight, Austin Theory | H69: Ford Center | I69: Evansville | J69: Indiana | K69: United States | L69: 5149 | M69: 351420 | N69: =E69*M69 -> 351420 | O69: 7643 | P69: 0.67 | Q69: 20 | R69: 120 | S69: 68.25
A70: 45254 | B70: =YEAR(A70) -> 2023 | C70: ="Q"&ROUNDUP(MONTH(A70)/3,0) -> Q4 | D70: =B70&" Q"&ROUNDUP(MONTH(A70)/3,0) -> 2023 Q4 | E70: 1 | F70: World Wrestling Entertainment | G70: Damian Priest, Finn Balor, Becky Lynch, Charlotte Flair | H70: Allstate Arena | I70: Rosemont | J70: Illinois | K70: United States | L70: 15777 | M70: 982372 | N70: =E70*M70 -> 982372 | O70: 17570 | P70: 0.89 | Q70: 20 | R70: 200 | S70: 62.27
A71: 45255 | B71: =YEAR(A71) -> 2023 | C71: ="Q"&ROUNDUP(MONTH(A71)/3,0) -> Q4 | D71: =B71&" Q"&ROUNDUP(MONTH(A71)/3,0) -> 2023 Q4 | E71: 1 | F71: World Wrestling Entertainment | G71: Bianca Belair, Charlotte Flair, Shotzi Blackheart, Becky Lynch, The Miz, Cody Rhodes | H71: Allstate Arena | I71: Rosemont | J71: Illinois | K71: United States | L71: 16579 | M71: 2240645 | N71: =E71*M71 -> 2240645 | O71: 17570 | P71: 0.94 | Q71: 30 | R71: 750 | S71: 135.15
A72: 45256 | B72: =YEAR(A72) -> 2023 | C72: ="Q"&ROUNDUP(MONTH(A72)/3,0) -> Q4 | D72: =B72&" Q"&ROUNDUP(MONTH(A72)/3,0) -> 2023 Q4 | E72: 1 | F72: World Wrestling Entertainment | H72: Peoria Civic Center Arena | I72: Peoria | J72: Illinois | K72: United States | L72: 2995 | M72: 186739 | N72: =E72*M72 -> 186739 | O72: 8452 | P72: 0.35 | Q72: 24 | R72: 119 | S72: 62.35
A73: 45257 | B73: =YEAR(A73) -> 2023 | C73: ="Q"&ROUNDUP(MONTH(A73)/3,0) -> Q4 | D73: =B73&" Q"&ROUNDUP(MONTH(A73)/3,0) -> 2023 Q4 | E73: 1 | F73: World Wrestling Entertainment | H73: Bridgestone Arena | I73: Nashville | J73: Tennessee | K73: United States | L73: 10803 | M73: 612297.5 | N73: =E73*M73 -> 612297.5 | O73: 11488 | P73: 0.94 | Q73: 24.7 | R73: 167 | S73: 56.68
A74: 45261 | B74: =YEAR(A74) -> 2023 | C74: ="Q"&ROUNDUP(MONTH(A74)/3,0) -> Q4 | D74: =B74&" Q"&ROUNDUP(MONTH(A74)/3,0) -> 2023 Q4 | E74: 1 | F74: World Wrestling Entertainment | G74: Rey Mysterio, Bobby Lashley, Charlotte Flair, Iyo Sky, Bianca Belair, Jimmy USO | H74: Barclays Center | I74: Brooklyn | J74: New York | K74: United States | L74: 13330 | M74: 1021359.3 | N74: =E74*M74 -> 1021359.3 | O74: 13330 | P74: 1 | Q74: 30 | R74: 350 | S74: 76.62
A75: 45262 | B75: =YEAR(A75) -> 2023 | C75: ="Q"&ROUNDUP(MONTH(A75)/3,0) -> Q4 | D75: =B75&" Q"&ROUNDUP(MONTH(A75)/3,0) -> 2023 Q4 | E75: 1 | F75: World Wrestling Entertainment | H75: PPL Center | I75: Allentown | J75: Pennsylvania | K75: United States | L75: 5205 | M75: 307439.5 | N75: =E75*M75 -> 307439.5 | O75: 6258 | P75: 0.83 | Q75: 20 | R75: 105 | S75: 59.07
A76: 45264 | B76: =YEAR(A76) -> 2023 | C76: ="Q"&ROUNDUP(MONTH(A76)/3,0) -> Q4 | D76: =B76&" Q"&ROUNDUP(MONTH(A76)/3,0) -> 2023 Q4 | E76: 1 | F76: World Wrestling Entertainment | H76: MVP Arena | I76: Albany | J76: New York | K76: United States | L76: 6608 | M76: 410369 | N76: =E76*M76 -> 410369 | O76: 6608 | P76: 1 | Q76: 25 | R76: 135 | S76: 62.1
A77: 45271 | B77: =YEAR(A77) -> 2023 | C77: ="Q"&ROUNDUP(MONTH(A77)/3,0) -> Q4 | D77: =B77&" Q"&ROUNDUP(MONTH(A77)/3,0) -> 2023 Q4 | E77: 1 | F77: World Wrestling Entertainment | H77: Rocket Mortgage Fieldhouse | I77: Cleveland | J77: Ohio | K77: United States | L77: 8417 | M77: 600553.5 | N77: =E77*M77 -> 600553.5 | O77: 14011 | P77: 0.6 | Q77: 20 | R77: 130 | S77: 71.35
A78: 45275 | B78: =YEAR(A78) -> 2023 | C78: ="Q"&ROUNDUP(MONTH(A78)/3,0) -> Q4 | D78: =B78&" Q"&ROUNDUP(MONTH(A78)/3,0) -> 2023 Q4 | E78: 1 | F78: World Wrestling Entertainment | H78: Resch Center | I78: Green Bay | J78: Wisconsin | K78: United States | L78: 5574 | M78: 410532.5 | N78: =E78*M78 -> 410532.5 | O78: 6381 | P78: 0.87 | Q78: 23 | R78: 128 | S78: 73.65
A79: 45276 | B79: =YEAR(A79) -> 2023 | C79: ="Q"&ROUNDUP(MONTH(A79)/3,0) -> Q4 | D79: =B79&" Q"&ROUNDUP(MONTH(A79)/3,0) -> 2023 Q4 | E79: 1 | F79: World Wrestling Entertainment | H79: Vibrant Arena at The Mark | I79: Moline | J79: Illinois | K79: United States | L79: 4616 | M79: 234394 | N79: =E79*M79 -> 234394 | O79: 5038 | P79: 0.91 | Q79: 20 | R79: 120 | S79: 50.78
A80: 45278 | B80: =YEAR(A80) -> 2023 | C80: ="Q"&ROUNDUP(MONTH(A80)/3,0) -> Q4 | D80: =B80&" Q"&ROUNDUP(MONTH(A80)/3,0) -> 2023 Q4 | E80: 1 | F80: World Wrestling Entertainment | H80: Wells Fargo Arena | I80: Des Moines | J80: Iowa | K80: United States | L80: 6483 | M80: 392243.5 | N80: =E80*M80 -> 392243.5 | O80: 6500 | P80: 0.99 | Q80: 25 | R80: 120 | S80: 60.5
A81: 45286 | B81: =YEAR(A81) -> 2023 | C81: ="Q"&ROUNDUP(MONTH(A81)/3,0) -> Q4 | D81: =B81&" Q"&ROUNDUP(MONTH(A81)/3,0) -> 2023 Q4 | E81: 1 | F81: World Wrestling Entertainment | H81: CFG Bank Arena | I81: Baltimore | J81: Maryland | K81: United States | L81: 5660 | M81: 372160.75 | N81: =E81*M81 -> 372160.75 | O81: 6777 | P81: 0.83 | Q81: 25 | R81: 135 | S81: 65.75
A82: 45286 | B82: =YEAR(A82) -> 2023 | C82: ="Q"&ROUNDUP(MONTH(A82)/3,0) -> Q4 | D82: =B82&" Q"&ROUNDUP(MONTH(A82)/3,0) -> 2023 Q4 | E82: 1 | F82: World Wrestling Entertainment | H82: Madison Square Garden | I82: New York | J82: New York | K82: United States | L82: 15722 | M82: 1134966 | N82: =E82*M82 -> 1134966 | O82: 15722 | P82: 1 | Q82: 32 | R82: 307 | S82: 72.19
A83: 45287 | B83: =YEAR(A83) -> 2023 | C83: ="Q"&ROUNDUP(MONTH(A83)/3,0) -> Q4 | D83: =B83&" Q"&ROUNDUP(MONTH(A83)/3,0) -> 2023 Q4 | E83: 1 | F83: World Wrestling Entertainment | G83: Becky Lynch, Zoey Stark, Kofi Kingston, Ludwig Kaiser, Ricochet, Bronson Reed, Cody Rhodes | H83: TD Garden | I83: Boston | J83: Massachusetts | K83: United States | L83: 9109 | M83: 666243 | N83: =E83*M83 -> 666243 | O83: 9788 | P83: 0.93 | Q83: 20 | R83: 160 | S83: 73.14
A84: 45287 | B84: =YEAR(A84) -> 2023 | C84: ="Q"&ROUNDUP(MONTH(A84)/3,0) -> Q4 | D84: =B84&" Q"&ROUNDUP(MONTH(A84)/3,0) -> 2023 Q4 | E84: 1 | F84: World Wrestling Entertainment | H84: Little Caesars Arena | I84: Detroit | J84: Michigan | K84: United States | L84: 7779 | M84: 516999 | N84: =E84*M84 -> 516999 | O84: 14329 | P84: 0.54 | Q84: 66.46 | R84: 66.46 | S84: 66.46
A85: 45289 | B85: =YEAR(A85) -> 2023 | C85: ="Q"&ROUNDUP(MONTH(A85)/3,0) -> Q4 | D85: =B85&" Q"&ROUNDUP(MONTH(A85)/3,0) -> 2023 Q4 | E85: 1 | F85: World Wrestling Entertainment | G85: LA Knight, Jimmy USO, Kevin Owens, Solo Sikoa | H85: MGM Grand Garden Arena | I85: Las Vegas | J85: Nevada | K85: United States | L85: 6808 | M85: 366122 | N85: =E85*M85 -> 366122 | O85: 6808 | P85: 1 | Q85: 25.8 | R85: 167.5 | S85: 53.78
A86: 45292 | B86: =YEAR(A86) -> 2024 | C86: ="Q"&ROUNDUP(MONTH(A86)/3,0) -> Q1 | D86: =B86&" Q"&ROUNDUP(MONTH(A86)/3,0) -> 2024 Q1 | E86: 1 | F86: World Wrestling Entertainment | H86: Pechanga Arena San Diego | I86: San Diego | J86: California | K86: United States | L86: 9526 | M86: 449625 | N86: =E86*M86 -> 449625 | O86: 10404 | P86: 0.91 | Q86: 20 | R86: 110 | S86: 47.2
A87: 45297 | B87: =YEAR(A87) -> 2024 | C87: ="Q"&ROUNDUP(MONTH(A87)/3,0) -> Q1 | D87: =B87&" Q"&ROUNDUP(MONTH(A87)/3,0) -> 2024 Q1 | E87: 1 | F87: World Wrestling Entertainment | G87: Cody Rhodes, Seth Rollins, LA Knight, Bobby Lashley | H87: Spokane Arena | I87: Spokane | J87: Washington | K87: United States | L87: 5309 | M87: 332595 | N87: =E87*M87 -> 332595 | O87: 10724 | P87: 0.49 | Q87: 20 | R87: 115 | S87: 62.65
A88: 45299 | B88: =YEAR(A88) -> 2024 | C88: ="Q"&ROUNDUP(MONTH(A88)/3,0) -> Q1 | D88: =B88&" Q"&ROUNDUP(MONTH(A88)/3,0) -> 2024 Q1 | E88: 1 | F88: World Wrestling Entertainment | G88: CM Punk, Cody Rhodes, Shinsuke Nakamura, Drew Mcintyre | H88: Moda Center | I88: Portland | J88: Oregon | K88: United States | L88: 9422 | M88: 527563 | N88: =E88*M88 -> 527563 | O88: 12188 | P88: 0.77 | Q88: 35 | R88: 125 | S88: 55.99
A89: 45306 | B89: =YEAR(A89) -> 2024 | C89: ="Q"&ROUNDUP(MONTH(A89)/3,0) -> Q1 | D89: =B89&" Q"&ROUNDUP(MONTH(A89)/3,0) -> 2024 Q1 | E89: 1 | F89: World Wrestling Entertainment | H89: Simmons Bank Arena | I89: North Little Rock | J89: Arkansas | K89: United States | L89: 6793 | M89: 373267 | N89: =E89*M89 -> 373267 | O89: 10000 | P89: 0.67 | Q89: 24 | R89: 139 | S89: 54.95
A90: 45310 | B90: =YEAR(A90) -> 2024 | C90: ="Q"&ROUNDUP(MONTH(A90)/3,0) -> Q1 | D90: =B90&" Q"&ROUNDUP(MONTH(A90)/3,0) -> 2024 Q1 | E90: 1 | F90: World Wrestling Entertainment | H90: State Farm Arena | I90: Atlanta | J90: Georgia | K90: United States | L90: 12342 | M90: 584840 | N90: =E90*M90 -> 584840 | O90: 12342 | P90: 1 | Q90: 20 | R90: 150 | S90: 47.39
A91: 45317 | B91: =YEAR(A91) -> 2024 | C91: ="Q"&ROUNDUP(MONTH(A91)/3,0) -> Q1 | D91: =B91&" Q"&ROUNDUP(MONTH(A91)/3,0) -> 2024 Q1 | E91: 1 | F91: World Wrestling Entertainment | H91: Kaseya Center | I91: Miami | J91: Florida | K91: United States | L91: 9484 | M91: 572494 | N91: =E91*M91 -> 572494 | O91: 9484 | P91: 1 | Q91: 20 | R91: 150 | S91: 60.36
A92: 45320 | B92: =YEAR(A92) -> 2024 | C92: ="Q"&ROUNDUP(MONTH(A92)/3,0) -> Q1 | D92: =B92&" Q"&ROUNDUP(MONTH(A92)/3,0) -> 2024 Q1 | E92: 1 | F92: World Wrestling Entertainment | H92: Amalie Arena | I92: Tampa | J92: Florida | K92: United States | L92: 11843 | M92: 613031.5 | N92: =E92*M92 -> 613031.5 | O92: 11843 | P92: 1 | Q92: 20 | R92: 150 | S92: 51.76
A93: 45326 | B93: =YEAR(A93) -> 2024 | C93: ="Q"&ROUNDUP(MONTH(A93)/3,0) -> Q1 | D93: =B93&" Q"&ROUNDUP(MONTH(A93)/3,0) -> 2024 Q1 | E93: 1 | F93: NXT Vengeance Day | H93: F&M Bank Arena | I93: Clarksville | J93: Tennessee | K93: United States | L93: 3737 | M93: 190099.5 | N93: =E93*M93 -> 190099.5 | O93: 4206 | P93: 0.88 | Q93: 23 | R93: 163 | S93: 50.87
A94: 45331 | B94: =YEAR(A94) -> 2024 | C94: ="Q"&ROUNDUP(MONTH(A94)/3,0) -> Q1 | D94: =B94&" Q"&ROUNDUP(MONTH(A94)/3,0) -> 2024 Q1 | E94: 1 | F94: World Wrestling Entertainment | H94: Spectrum Center | I94: Charlotte | J94: North Carolina | K94: United States | L94: 12219 | M94: 578726.75 | N94: =E94*M94 -> 578726.75 | O94: 12810 | P94: 0.95 | Q94: 23.5 | R94: 153.5 | S94: 47.36
A95: 45334 | B95: =YEAR(A95) -> 2024 | C95: ="Q"&ROUNDUP(MONTH(A95)/3,0) -> Q1 | D95: =B95&" Q"&ROUNDUP(MONTH(A95)/3,0) -> 2024 Q1 | E95: 1 | F95: World Wrestling Entertainment | G95: Cody Rhodes, Rhea Ripley, Jey Uso, Sami Zayn, Drew Mcintyre, Kofi Kingston | H95: Rupp Arena | I95: Lexington | J95: Kentucky | K95: United States | L95: 9855 | M95: 578865.75 | N95: =E95*M95 -> 578865.75 | O95: 14903 | P95: 0.66 | Q95: 25 | R95: 25 | S95: 58.74
A96: 45339 | B96: =YEAR(A96) -> 2024 | C96: ="Q"&ROUNDUP(MONTH(A96)/3,0) -> Q1 | D96: =B96&" Q"&ROUNDUP(MONTH(A96)/3,0) -> 2024 Q1 | E96: 1 | F96: World Wrestling Entertainment | H96: Oakland Arena | I96: Oakland | J96: California | K96: United States | L96: 7270 | M96: 457936.5 | N96: =E96*M96 -> 457936.5 | O96: 7700 | P96: 0.94 | Q96: 37.14 | R96: 189.52 | S96: 62.99
A97: 45340 | B97: =YEAR(A97) -> 2024 | C97: ="Q"&ROUNDUP(MONTH(A97)/3,0) -> Q1 | D97: =B97&" Q"&ROUNDUP(MONTH(A97)/3,0) -> 2024 Q1 | E97: 1 | F97: World Wrestling Entertainment | H97: Save Mart Center | I97: Fresno | J97: California | K97: United States | L97: 9367 | M97: 425845 | N97: =E97*M97 -> 425845 | O97: 9543 | P97: 0.98 | Q97: 20 | R97: 100 | S97: 45.46
A98: 45341 | B98: =YEAR(A98) -> 2024 | C98: ="Q"&ROUNDUP(MONTH(A98)/3,0) -> Q1 | D98: =B98&" Q"&ROUNDUP(MONTH(A98)/3,0) -> 2024 Q1 | E98: 1 | F98: World Wrestling Entertainment | H98: Honda Center | I98: Anaheim | J98: California | K98: United States | L98: 10204 | M98: 753167.6 | N98: =E98*M98 -> 753167.6 | O98: 10249 | P98: 0.99 | Q98: 30 | R98: 155 | S98: 73.81
A99: 45352 | B99: =YEAR(A99) -> 2024 | C99: ="Q"&ROUNDUP(MONTH(A99)/3,0) -> Q1 | D99: =B99&" Q"&ROUNDUP(MONTH(A99)/3,0) -> 2024 Q1 | E99: 1 | F99: World Wrestling Entertainment | H99: Desert Diamond Arena | I99: Glendale | J99: Arizona | K99: United States | L99: 11565 | M99: 607750 | N99: =E99*M99 -> 607750 | O99: 12171 | P99: 0.95 | Q99: 25 | R99: 225 | S99: 52.55
A100: 45353 | B100: =YEAR(A100) -> 2024 | C100: ="Q"&ROUNDUP(MONTH(A100)/3,0) -> Q1 | D100: =B100&" Q"&ROUNDUP(MONTH(A100)/3,0) -> 2024 Q1 | E100: 1 | F100: World Wrestling Entertainment | H100: Acrisure Arena in Greater Palm Springs | I100: Palm Desert | J100: California | K100: United States | L100: 7062 | M100: 426503.75 | N100: =E100*M100 -> 426503.75 | O100: 9006 | P100: 0.78 | Q100: 26 | R100: 131 | S100: 60.39
...
